<?xml version="1.0" ?>
<PyBrain>
	<Network class="pybrain.structure.networks.feedforward.FeedForwardNetwork" name="FeedForwardNetwork-15">
		<name val="'FeedForwardNetwork-15'"/>
		<Modules>
			<LinearLayer class="pybrain.structure.modules.linearlayer.LinearLayer" inmodule="True" name="LinearLayer-8">
				<dim val="400"/>
			</LinearLayer>
			<SoftmaxLayer class="pybrain.structure.modules.softmax.SoftmaxLayer" name="SoftmaxLayer-16" outmodule="True">
				<dim val="10"/>
			</SoftmaxLayer>
			<TanhLayer class="pybrain.structure.modules.tanhlayer.TanhLayer" name="TanhLayer-7">
				<dim val="10"/>
			</TanhLayer>
			<TanhLayer class="pybrain.structure.modules.tanhlayer.TanhLayer" name="TanhLayer-17">
				<dim val="10"/>
			</TanhLayer>
			<TanhLayer class="pybrain.structure.modules.tanhlayer.TanhLayer" name="TanhLayer-18">
				<dim val="10"/>
			</TanhLayer>
			<TanhLayer class="pybrain.structure.modules.tanhlayer.TanhLayer" name="TanhLayer-19">
				<dim val="10"/>
			</TanhLayer>
			<TanhLayer class="pybrain.structure.modules.tanhlayer.TanhLayer" name="TanhLayer-20">
				<dim val="10"/>
			</TanhLayer>
		</Modules>
		<Connections>
			<FullConnection class="pybrain.structure.connections.full.FullConnection" name="FullConnection-14">
				<inmod val="LinearLayer-8"/>
				<outmod val="TanhLayer-19"/>
				<Parameters>[10.028876377500756, 1.8983263820900544, -1.4856294418663887, 1.3404407675554175, -0.05466711569416599, -0.12133607394194629, 0.6038212175726911, 0.5316166291681619, -0.9120942981374123, -2.1377427877675093, -3.857469815747596, -3.3619627901899896, -4.865717798913033, -3.0162307043203196, -5.06398366446618, -1.7059091788829168, -1.9963356836693134, -1.0955699205685707, 1.4255023749533986, 2.6597630454761547, 0.33328572086004005, -1.2986000995750138, -0.7961595500831963, -0.47727034319290473, -0.2639739582706195, 0.5440544917437233, 0.28189785528885997, 0.1606390104409163, 1.049489494908442, 1.2456543188836986, 0.5979761843011961, 0.6629455670969234, 1.3183049891618819, 2.301930640549422, 3.2316143538087045, 2.0871886121293457, 1.39643672785949, -0.5192490984941888, -2.126393957531649, 0.7765900998396075, 0.5258986637077137, 1.0084052121778826, 0.5679954180409091, 1.0211630532048799, 0.8686276405838029, -0.7733378969289204, 0.6501149855601399, -0.2600125257179411, -1.1478063467135562, 0.6068881019577487, 0.5358465978292535, 0.33492326935935374, -0.26218421052519636, 1.484669567138198, -0.7245790364957441, 0.5738032786123817, -0.6188185976077089, 0.5697804695222749, -0.6100879940645013, 0.28527978210116667, -0.46211950530190443, 0.2903152641113726, 0.9212287105289975, 0.7192075506957534, -1.0675130763892227, -0.33371314827049336, -1.3758521548277902, -1.5947052012682916, -2.8101029622928904, 0.6594751699777591, 1.0660120158949788, -2.057138109335407, 0.868969524930301, -0.3401941646269606, -3.2794213523004503, -3.465707347435707, -3.6682130159938513, -3.098697265580499, -2.163411930540856, -0.6711881479776465, -0.5314102481725279, -0.028589584894498157, 0.2666334239705512, -0.175204608694203, -0.6466240535883924, 0.24478759432940211, 0.747479523739169, 0.07708805841583304, 1.1330428768174132, -1.1041024821546466, 0.5798852993852084, -1.4406988808040453, 0.2820601649233071, -0.21061946887796365, 0.5416749620153967, -0.27902177436695363, -0.06968370777833877, -0.06433255222225556, -1.0316921981540579, -0.689895412480713, 0.06966133934092389, 1.1805131330914918, 0.48486470048104185, -0.45561221693947085, 0.4103674371857724, -0.6674095880450049, 1.570190003359011, 0.3018086039594387, 0.055622719937799825, -0.04179625024443835, -0.6429023528570704, -0.9540138492723264, 1.029405416329648, -0.2427519831349793, 1.1959933757874255, -0.9768572808140705, 1.6309036894802527, 0.6330107655945687, 1.194724427292491, -1.2873039342742776, 0.9450713517083122, 0.18418503076545212, 0.12688938942260622, 0.7243199829700636, -1.6441030822892488, 0.17933341283184343, -0.3817596950618845, -0.33202851060933636, 0.4429214944875096, -0.21475091854369124, 0.30165019322731823, 0.14105018658383944, 0.09397611100907975, -0.2477469692804478, 0.052154129795911865, 0.12276382773600245, -0.27203650997520135, -1.1958107908523046, -0.84747746602512, -0.5377192283697697, 1.4806051634052557, -0.5862159085302985, 0.592098493862837, -0.540650862556319, -0.21854791761359915, -0.13189635870257105, 0.9131279990566474, -0.97176630950955, -1.9518951613833446, -1.4013291559974859, 0.634671023923838, -0.46614115251436183, -0.2845791660742864, -0.4865876855767577, -0.9861886647643555, -0.11518640807553715, -1.3172542525165998, 0.9366260621018063, -0.6785948788784307, -0.23256786712935668, -0.5665608955056602, -0.7198703586928212, 0.10540848582756865, 0.06910215246265684, -1.2880330591151143, -0.050508308544820676, -1.0681587061397375, -0.9620251100400175, 0.6103838198261812, -0.7495265499562267, -1.9792743999012956, 1.6223795663005889, -0.6121461155240592, -0.5368422770351416, -0.6761738837812767, -2.138082355657656, 1.7779885283727395, -0.5131503773964364, -1.8714048396841032, -0.023834344411865244, -1.2473301997811486, -1.2132419522828235, -1.0423776629693795, -0.21414131577159184, 0.18522171816643582, -0.5906760535191078, 0.8119918465726054, 0.9248947531031495, -0.04137899723174663, 0.39205148826921116, -0.8838372128237497, 0.3445838515226552, -1.2908145564273312, 0.6026587529408465, -0.6274039307842044, 1.3984449035291675, 0.48909478610660395, -0.7464599187894272, 1.0431993054554125, 1.4026352913801667, 0.4589889925046826, -0.6018793233399066, -0.17708900278022108, 1.558066536558425, 0.44208137153834604, -0.14870667295678097, 0.33486723714852823, 1.593370566989415, 2.919685493881099, -1.119718600777803, 0.3336688096247791, 1.230506066119492, 0.11786095552081409, 0.6681599323727431, -1.3358122002699504, 1.018433499792053, -0.571747769608729, 1.7858178424849471, 2.603399898004443, -1.9503284309801983, 2.8212523777112697, -0.6451635086601037, -0.5402311526958499, -0.20758543837524907, 2.0696977329967887, 0.5642492406450388, 1.5564640821841738, 0.3967150919548919, 1.1496596095909641, -0.41995533553210185, 0.8263592233178151, 0.4124137650754073, 0.18580462360839778, -0.2339972446189847, -1.885826979988986, 2.0975597312341514, -1.036751298753632, 0.5880282076468326, -0.9522282730184656, -1.2527932441844767, 0.10120353376614656, -0.5988274460548196, 0.9944002659201095, -0.6932225899285551, -0.05561307171337135, -0.9837661553330013, 0.6721485569756159, 0.9219976106376699, 0.3398134001639842, -0.498490269189082, 0.891555752866307, -1.1357384583532406, 2.0297370185430696, -1.0524483159233646, -0.8966953255410972, -0.6062640503402309, 0.3806548290882063, -0.9011847752600348, 0.85213238419642, 2.6102320875695573, -0.08037784934908349, 0.0472631906671933, -0.2843969410188868, 1.8362187399539012, -0.7608168557864178, -0.7099890142428498, 0.06276506292403954, -0.5811623454955421, 1.27123145824486, 0.2936770987013165, -1.2129481026597146, 1.4591396968664723, -0.6989843405799295, -0.35700924418135527, -0.23564406433842736, -0.0591478307253617, 1.199893721257075, 1.2835650082740013, 0.14085812050383564, -0.48177142371566845, -1.3035787661129137, -1.2745337869683904, 0.8173085338609114, 1.3732670430843985, -0.8058718952802061, 0.052792430748166766, -1.1388063210119657, -0.365473599440229, 1.347283274434275, -0.47893858314086496, -0.6017883620553395, -0.11995004850970596, 0.34257825032647066, 0.500452800171935, -0.4442750183794479, -0.44661184311839264, 0.06862152630232436, 1.0801407673461574, -1.5284273424830899, 0.7264448872704299, 0.5037041240663328, -0.6393515912401373, -0.5098248931531241, 0.581090841234722, -0.5192848809625779, -0.6846554793078509, 0.3085195988179512, 1.0005666352921005, -1.6728595093348642, 0.7026310492620796, 0.5236204036139022, -0.984255758071444, 0.3235893115387331, -0.6744641770723903, -0.5450379551378299, -0.5977668197001929, 0.7784122987071245, 0.08435253939281646, -0.6275369934310575, -0.06544107832254191, 0.49449717459732256, -0.12387861873297992, -0.11480253255604135, -0.34097256952148547, 0.6733229057672293, -0.09719273360285872, 1.3796335345176534, -0.6513860770023082, 0.52247857402243, -0.03815776344019875, 0.195325061869271, 0.04099497003418612, 0.11917665400283664, -0.13820465115486122, 0.584691817492461, 0.19127000923764784, 0.040814527001987407, 0.016916852928540047, -0.9147476150123951, -0.15388266655035596, 0.42887889154552883, -0.4319947286518925, -0.3944934711094899, 0.3517564172668533, -0.2685785134229232, 0.9409193869597349, -0.32326018221541747, 0.17946188475189803, 0.35037778336701797, 0.07296174116910692, -0.44589105238937055, 0.22111638190346908, 0.15162002124376978, -0.8354484086413694, 0.32936785942616303, 0.08791466488735275, -0.04312264001299501, -1.714243555429597, 1.557815579907361, -0.1773045540417158, -0.35896389329900524, 1.1610412705086157, -0.8422687361387023, -0.5546176185191141, 0.48017210820699546, 0.26766221933312984, 0.09901334503620222, 1.0888628544031551, -0.3529999514908975, -0.08024817014146625, -0.024680431018763615, 0.2447703815624152, 0.41178440358858565, 0.2072436124008939, 0.05754004049726257, 0.4377965740543276, 0.4742942600593267, -0.8283295833815021, 0.5604573810936836, 0.33043277055881626, 0.928627505342187, -0.04034305631997598, 1.2636855277918007, -1.5163655227002732, -0.013275565299551062, -0.7784779621420065, 0.9014168487304277, 0.8842056669505457, 0.5521739922476572, 0.52821455197628, -0.34496849640604127, 0.25841318589496365, -0.4360309377214882, 0.4311021549803046, -0.18076724539290653, 1.0174534869045972, -0.2923171943332342, 0.7413821177405127, 0.2204870690759296, 1.3492799151437658, 3.363173312220325, -1.1866058877391812, -1.9713562982943098, -1.1893325881743921, -1.731638166608816, 4.381404826609725, 4.947444032149706, 0.2457686237096543, 2.5782292210091753, 3.124545513169284, 1.5603687775649804, 2.347618602911488, 0.8439781339783847, 4.189310496821196, 2.8433624775285833, 2.3965165864724427, -1.8040071965407847, 1.6709507955511722, 3.069213266696884, 1.3483299746375073, 2.108809297157508, 1.7901493913187587, 2.6776154542442834, 0.7266361275133173, 1.6792218086970112, 1.923395562270148, 1.9726831480557174, -0.049499924978770975, 1.3966085534242307, 3.942731442430072, 1.2092771669408238, -0.6156989158726269, 1.6865602295346742, 2.6481645459342436, 1.1099931238491503, -1.055722911390623, 0.9012056166919856, 0.2531825904358451, -0.5886850396582914, 0.36539727069462413, 1.4140982688974497, 0.6513498356001509, 0.5865667124922956, -0.38706951600664097, 2.2616894402037193, -0.5333519713688649, 0.14402901508247334, 1.1770337579934014, 0.8376228671537701, -1.174893108142743, -0.09967646583349546, -0.9523373071563501, 0.9052626835923414, 0.7444271285480073, 0.4503364686451212, -0.49042367362638, 2.0820698123729096, 2.085005573918094, 0.908435998565196, -1.6656785833036885, 2.728739055487359, -0.6024009790470193, -1.1957474730098396, 0.6900461549184957, 2.99926978944335, 0.4807431209183005, 1.7658406971638239, 1.1367511152615841, -1.2643160841049714, -1.7457810853839955, 1.1957607641034709, 1.0015156828667855, 2.006779569839555, 0.4864474886750787, -0.43171011506834545, 1.309268642416856, 0.7305659142447477, 1.1633219121009792, -0.704860023578955, -1.0278537839877036, 0.8860895638539896, 0.0993928555680818, -1.2535242008016882, -1.1859134911148834, 1.2433141088958402, -0.539341246251431, 0.5218903283822889, 0.9702573317592667, 0.5356751054956077, 1.0569920318315111, -2.009032898943129, 1.1922927166648418, -0.614590686893, 1.6320754408238114, -1.04908929973211, 0.99246095826234, -0.7460052032632946, -0.4932984784714009, 0.6108260893922556, -1.8944058089994384, 1.6583148576772302, -1.414282764020075, 3.2508049044624725, 0.4500183133652028, -0.34901976938974616, -0.8433440496895437, -0.5977961299848327, 0.006750346854876141, 0.7859757049927723, 1.6507446872492533, -1.034025513808849, -0.10911732799742146, -0.5711529081752166, -1.5706462282271092, 1.1534364542464057, -0.33007227449124915, 3.810558190903961, 0.7290443550707741, 0.4040334392426327, -0.9135622352855696, 0.20701430739777266, -1.6312693609129671, 1.090690782639046, 1.652620061716453, -0.8821458748189847, -2.291945914495986, 0.5140925914029704, 1.3804584796960975, -0.46834317789564295, 0.7764094914527438, -0.6287787974499943, 1.0335904111478693, -1.5398986464972062, 0.5903880211589607, -1.4485627172548725, 0.5886356506625824, -0.3575595833595017, -0.2981042891884873, -0.16733265549962514, -0.4289538804735021, 0.2232428350335924, -0.4812809720249912, 0.3596350580687701, 0.8673594475622357, -1.2157924299550964, 0.06519766919369956, 1.1739135493176753, -1.0669723307722858, -1.223780472255849, -0.28413274457587717, 0.3062269418205793, -0.8316264906167892, 1.241050708069663, 0.334800330059164, -1.1924705592255094, -8.307384911704313e-05, -0.3968870600848957, 1.8305592898727292, -0.1087593580168204, -1.4743284843581357, -1.8418762825838468, 0.6699201853078368, -0.13758415971178434, 0.8248058298764716, -0.6255311187940927, 0.7411281183298827, -0.9303872127312133, -0.03412434949347973, 0.8939172320744618, -1.0437895478258954, 2.347757945238087, 0.7511465683538892, 3.758843826943545, 0.5189574265888195, 0.8958513123841441, 1.7924965232309453, 0.3590477543328537, 0.5763017039171241, 1.0278233006542752, 1.3894731208107454, -2.2894181611845514, -1.3977301932212727, -1.0211299907164841, 0.6015038658091076, 3.3439339761380187, 0.791941707063583, 4.2197204977792655, 1.63887608692661, 0.008588882611938, -1.2469735577139627, 0.5547604233413359, 0.9955000241425636, 0.208223376070218, 4.200213010158131, 4.601497317550893, 2.305504385562782, -1.1779419564855222, 0.927724635493113, 1.0940971244887108, -1.9115654364668182, 0.16836027884031912, 0.17728365696756446, 0.5645920608954351, 2.0952909861773756, -1.9149881241530904, 1.5332755573803525, -0.6674040796369441, 2.500839568395562, 2.0179625276516204, 0.7445842291498364, 1.087468240187753, -0.02028840068593987, 1.8857324050251931, -1.572677819359895, -1.2776852721885061, -0.9399508812070663, 2.3970436556271837, 0.5546941421885532, 0.49643842308342273, 1.5403650260220112, -0.7729513361920847, 1.246739136522562, -0.5986847890673231, -0.6087976334617395, -0.3723975885272888, 0.9307203105338692, 1.3467268490240956, 1.4986724256933073, -0.18744085246156506, 1.6958855694093498, 0.8599040405118289, -0.17252063107295373, -0.22469515923013017, -0.7950013752437481, 1.258429815001725, -0.15482334518821061, 0.8776460152150114, 0.18925531375868893, -2.990975227300268, -0.2595707749779696, -0.3447658127883287, -1.500309662894035, -0.19470564710007585, -1.1682615133745793, 1.2208518693361121, 0.9450921953450966, 0.6921609103427032, -2.2446344416622597, 1.1107502675594796, -0.14540346020714864, 0.7821781413989071, 0.5014950730206439, -1.114129833123262, 1.8996210282932844, -0.07337752102932404, -0.5645905979216603, -1.1465236336388867, 2.8428802587791324, -0.7513311330935091, -0.9284327664898679, 1.0907287207129828, 0.2327179812660037, -2.545255184702112, -0.5047547178819253, 0.13764836994728372, -1.2846345930578271, 0.9279635725101523, -0.022591920089787217, -1.5534096895924692, -0.18531488743395977, -0.7521841795620343, 0.0324210264092978, 0.0022136638357324687, -0.11331813267172759, 0.39946112464893385, 1.2334598320541246, -1.8710434779307894, -0.5969241774674061, -1.242300867247715, 0.581439852010628, 0.3255498654074513, 0.3432901696165457, -1.136146537967015, 0.27824897483662575, 0.8891717264869841, -1.601482892676785, -0.2819941885326815, 0.2445558814795922, 2.7530462022991786, 1.9275770694882057, -1.0953760083990283, -0.21666710025440564, -1.0616327020707608, -2.0141811016863116, 0.11755675661374637, -0.22629250279745647, 0.16781927046083422, 1.5211203005902496, -0.6828895875012249, 0.6744375557737761, 0.05497214546434319, 1.5166959915571065, 0.17582985617352756, -1.778467824745109, 0.6790371323700608, 0.552011725446627, -1.1334729858465329, 1.9956400526177869, -0.8460197292722959, 1.1378751766089827, -0.7248102962637475, 1.7554804118383402, -1.0468560028334049, 2.2509579899655208, -1.0430366286820019, -0.14589602586697947, 0.848819567622337, 0.040819195754765183, -1.7624143670579038, 0.6224913620091178, -0.010557932653287319, 1.5033251709319326, 1.05385356175294, 0.5581343559708317, 0.5723852029649649, -0.5869464668951936, 0.5641435546113097, 0.8498230800416863, 1.2218305746846563, -0.33234936891388833, -0.7562980580307732, 1.2607091470297818, -0.15846876249908745, -1.710459139768602, -0.10260557830174336, 0.9927976082266254, -0.29492017917593144, -0.5557707876215162, -0.7714296947540009, 2.627076078697055, -1.9634493506100854, -0.3973714774552517, 1.5864145935630742, -0.7890184141679423, -0.830251221219685, 0.17465169302068353, 0.042364641947024564, 3.1750907709064498, -0.5897669858984745, 0.4647649262454558, -1.2357539682828813, 0.011463739514425713, -0.5825967179763877, -0.28165119172968045, 1.6578307162356167, -0.08902641927588598, -0.8618623954910206, -1.6903717597672792, 2.6156174530008123, -1.1880609644883307, 1.4664987259513025, 0.5396704539393083, 1.9294311429398212, -0.35819370473911916, 0.8297014019904017, 0.38192902452555105, 0.24528295288230545, -1.611821995280748, -0.8632453886773608, 0.02880987936893965, 0.4029171739851556, 0.805147481983025, 0.17486365714075655, -0.5757220210381457, 0.13393167686120874, -0.03169285381165014, -0.5464532606685936, 0.8379746640324648, -1.2086584364359378, -1.3609251725677651, 1.6433820015243703, 0.28119160668437815, -1.6772731767386622, 0.7451804659937507, -0.5325616182567582, 0.21686085241178188, 0.4292819578263254, -1.927486382016064, -1.3026915455931207, 0.7251280257182983, 0.7531702997588363, -0.8701111903070843, 1.3303249196886295, -0.5779197718215732, -1.6795208101664783, 2.4219823182575992, 0.6235031279469133, 0.9783643075728409, -0.12883888162739102, -0.6426229720498079, 5.86734942897623, 1.5038695784767777, -6.42951139212831, -3.682636135369235, 0.9704896535175075, 0.24274188486041162, -1.317168883795172, -0.6828531471548583, 1.7142294908429514, 1.4716837949915818, 4.17421627298157, 1.6396819165131076, 0.20502828440662701, -1.5499169617885327, -4.120171904870658, -3.252116779374192, 1.7935362123793714, 1.2892087727645958, -1.500687437649649, -2.5146104104433444, -0.5964161109895402, -0.028846744415485993, -1.5915359206672834, -1.5468460111630504, -1.17819028958282, -2.3910302331408624, -2.688553648465495, -0.7429915873878961, -2.2023593043574343, -1.96237021065646, -1.8106926947185118, 0.4934816197376396, -0.14912814067605867, -0.1739983366134433, -1.2819524897324723, -1.4553363783131077, -2.035144795391728, -0.8682839308030011, 1.25467250904597, 1.3037837174334115, 1.4935472636207616, 1.2072345999142462, 0.31737919641953993, 0.49157116340440654, -1.7766572430512297, -0.1399787398975119, -0.04769595449098327, 2.1926308668204366, -0.18990456873928405, -1.1954014346650101, -1.0506206414097468, -0.761146282117897, 0.6190702600110095, -0.3562398685925018, -0.22424086484551528, -0.07636821984085085, 0.47111018937318744, 1.3841008221607087, 0.14676652109509572, 0.9496460101110309, 1.467754757719573, 0.7559658933734456, 0.5318984768334989, 0.5555589205088407, 0.931920569069572, 1.4863339411284586, -0.3745139007807256, 1.123208552689323, 2.1712757149979285, 1.3676628347015916, -0.32066828554841037, 0.5969284862678412, -2.353062612721898, -1.9581734676336775, 2.0538878840072585, -1.5611833642250783, -1.3803053436764077, 1.3489990407451133, 1.0582418558644955, 0.20082370060476856, -1.328824945800646, 0.04650455558384564, 1.2524922308450237, 0.5562696681217475, 0.04419231310240464, -0.4289275230550461, 0.7034190589146759, 0.12312662107729652, -0.7687545820075355, -0.5134702580107996, 0.21562530202362723, 0.43291500979585534, 0.5371467269518129, -0.8188520366968149, -0.46546623620182964, 2.0217903152483383, -1.1672524923086962, -0.31274361224706015, 2.756793482615556, -0.054304887482857854, -0.5850694967730925, 0.0185376379499014, -0.127679185583598, -1.0467305487365521, 1.0841557227277294, 0.04798168790812039, -0.8760430170413896, -0.822867115869456, -0.12714179670439021, 2.705070496485888, 1.905564841855649, 0.6377333482253262, 0.023248637245784683, -0.5672356240227869, -1.3919692931722272, 0.5808053289108203, 0.12712921553985895, 0.24657048175998225, -0.046630977347325575, 1.977582636202073, -0.5731271994467352, -0.7635635827755747, -0.4156304770620375, 0.2072090266957407, -0.397560872035509, 0.8036808067855737, 0.5530886544393964, -0.125418583316783, -0.12221438993636982, -0.7671450160912849, 1.2897455386371983, -0.27495682673567384, 0.03395906706191768, -0.4166300826253143, -0.3693992768780591, 0.6207679297028479, -0.8484330033741596, 0.3387416809001242, 1.041725900165914, -0.30309424838843796, -1.3222075709540653, 0.30865625518260176, -0.6261279365959143, 0.38580844014909993, 1.982078961222633, -0.6787406669815411, -0.44688387349531417, 0.6900384244044434, -0.4493610385603199, 0.5430845634360536, -0.8838246516270484, 0.045763525471724895, 0.20844949064523943, -0.9452081451666708, 1.2901476731758832, -1.8616458003274294, 1.2381123939254057, -0.7244152062645345, -1.1554020675081518, 0.599604890856379, 0.2169176896449813, 0.7373204813475929, 0.2183237544195822, -1.3631942398921448, 1.3167100491576378, -1.9166586319631325, 0.6800724052020767, 1.1357370705262941, -0.9878091050917356, 0.5267189203606809, -0.9256701524702424, -1.351726691157833, -1.785728863404338, -2.1882775466838775, -0.9910600122638239, -1.8409297412575483, -0.5486669472400859, 1.2579466644965658, 0.9722655173160087, -2.114195700907094, 3.4814022445876303, -1.8194352517289414, -0.46084468840936976, -1.1070762259511284, -2.0209607489582373, -3.649127185553805, 0.71380198124514, -1.99740043688286, 0.5362487074120642, -2.819590896981181, -3.0177183558754987, -1.7477639875148492, -0.4783550012998483, 1.7557067922723342, 3.098345248675254, -0.9492234425079049, -1.837066563999987, -2.8645935162827043, -2.7641972223094498, -0.9290737346993966, 1.1272533130186315, 2.081024414053991, -0.679932005922003, -1.8710690560280376, -0.7180361024330363, 0.8505728056575559, 2.605302631820411, -0.6699793627675902, -2.1560046467734115, 1.0022293960895052, -0.10691193767045191, -1.425223272058633, 1.3662377384888023, 0.2271877822436691, 2.0744715630921453, -2.110339652344156, 0.3780132467595091, 1.979808089405582, 0.6468148205657134, -1.1654534821624025, 0.8701409246271472, 1.0786494864268004, 1.5789864973096335, -0.6088691281862377, -1.804655345389678, -2.678299858859706, -1.3193450891298013, -1.2393338802397107, 0.5414229688301033, 2.546084598611175, -0.8803858809912298, 0.04927212229409273, 0.9915938755368968, 0.10645289550306244, 2.9625549161731306, 0.9294041851360538, 1.6858982116629078, 1.3804324931586553, -0.37268479156647905, 1.9583302105857487, 1.3309848720527795, -1.2042916936504897, 1.7853128672474594, -0.9841948296603867, 1.4903865005638743, 0.32768183042280624, -0.8995152385420511, 0.1786284589419183, 0.2222412080824303, 0.44662627074332295, -1.3048411449079758, 0.6140561963246118, 1.0343771842757739, 0.45190172036809434, -0.2142597843010148, -0.11993540339239006, 0.746876412972174, 0.9870636749869599, 0.15410373173724298, -1.6040495084196535, 0.29885506332311035, 0.22065333684036592, 1.1761061750045458, -1.8826390703188849, -0.7079931616846576, 2.440461602974581, 0.9626938617540268, -0.24499125491817866, -0.49929115168573895, -0.09327869250038508, 0.7836380498756863, -1.0288276332870212, 1.243513235084205, -1.3666564486723274, 1.271770333878005, -1.1125640288729737, -0.3450402609894884, -0.5640469592190893, 0.34575457500976936, -1.6204889578506094, 2.6114586882523745, -0.4353980220772823, 1.3000639611665548, -0.39987020950182395, 0.20229619476384364, 1.0238338625447274, -1.4301218189306517, 0.6495768037905414, -0.13567309893632784, -0.5498475028073726, -1.3966267621566928, 1.115792642254378, 0.43223945779066836, -1.3652779030860456, 0.5873725433689343, 0.2197257304330196, -1.842118238448119, 0.6134144012164426, 0.6069097861427638, -0.08366254746511004, 0.23301141385509067, 0.3471468993707055, -0.19844748470647944, 0.8471089260076083, 0.886128905611126, -0.02359717208854617, 0.23573808321441933, -0.6541220694757002, 0.11969498333996896, 0.17790280792547147, -1.5209561872596422, 1.1942174102288625, 0.9481876300200306, 0.31446555295673895, 0.33384029275975635, -0.5064242828830569, -0.10230981792566966, 0.5273383271953894, 0.1481955611656545, -0.17082336974581971, 1.4191046139494887, 0.3692323529304633, 0.23497960483200514, -0.995478971694591, 0.9848596751220448, 0.21612840068996922, 0.984766388802721, -0.36211006475217533, -0.11854646391207652, 0.1921084664145323, 0.7731205807144166, -0.14067478253504445, -1.6456479218393725, 0.029719999357132487, 0.9097748941807015, -1.9573070349465724, 0.5874089027624718, 0.9465785675082542, -0.5887765766050549, -0.2763525494571169, 1.385305287737876, -0.137943453675919, 1.7117213401299893, 0.00185008996259989, -1.0124599790635296, 0.41976293916305896, -0.42863946077403176, 1.966822441645203, -1.1345615481928042, 0.43376291447098647, 1.1549818615961152, -0.6187130793880494, -0.012655032988995011, 0.8898934961127156, -0.361020077097126, 0.6784296359986399, 0.8011834756902817, 0.978435135363942, 1.3295482796143312, 0.08853413665462301, 0.20345021133716867, -0.00011813569820257375, 1.023647937340513, -0.19475128768234298, -0.03561205138334632, -0.5431482434442015, 0.5897549948234135, -1.7530215987989568, 0.28800861001246275, -0.5623471604782998, 1.6204298053928587, 0.05662874040810415, -0.41642138755711566, 0.018253420251601368, -0.19328530379607922, -1.202436224480287, -0.3894516431836352, 1.2571397333991123, -0.8098272442068454, -1.0888792764661024, -0.44090987004741095, 0.6019234499559011, 1.5188512151465243, 0.12082918149601096, 1.0933031172261785, -0.3930444528737939, 0.009943703626480966, -1.2432232373127021, -0.19228390483547741, -0.9600881158304889, 0.671217951770914, 1.6155717489306125, -0.4066617561091142, -0.2063125048664763, 0.6636709594343354, 0.49010397443560144, 0.1296529002444095, 0.976333340826374, 0.49608134631121586, 2.1122600428571974, 2.1418842925854227, 1.8813504878112337, -4.537165750791437, 6.400853606772541, -6.142855258458759, 3.2763769410470305, 5.496454274993754, 2.246098526042193, 2.2257325613170607, 3.5108392756985864, 3.907075532801046, 4.14607483217894, 0.5947942826584289, -0.19154263019352444, 1.6335949038172641, 2.378972427001639, 1.0950489088995732, 1.5992737269339325, 1.1554218840013604, 1.183430378936228, 0.4268756051963161, -0.4023375543767402, -0.3992806666408424, -0.8139477122436822, -0.8848953404079961, -0.7562938736757403, -0.22689032158612005, -0.4684605470206578, -0.18197831934062317, -0.4176364092672537, -0.21956507489190275, 0.2956255737607794, -0.10400897472607325, 0.22811954620775302, -0.5931382152400417, -0.7312905200547024, -0.018066463262159927, -1.1193875107289057, 1.6289844909584987, -1.788636249669257, 1.7236710667954638, 0.42030551703683927, 0.7848147839229171, 0.4510992532169727, -1.2871872439691725, -0.42084460022429004, 0.19560988568353002, 0.19786387191702456, 1.0583307400210449, -0.3180528967952176, 0.1071816604072025, -0.48268753518885427, 0.5844651131444628, 0.4201124901047805, -0.07850923382988174, 0.06610713786832663, 0.3849665014586787, 0.9811168234951296, 0.9352175379921219, 0.49282346725257187, 0.3501898751798798, 0.32819787250559346, -0.015374897024029423, 1.274723465878936, 0.27561847857960386, 0.6584080253494877, -1.7916070160758413, 1.8974627792042138, 2.1390518028684813, 0.15421262295395116, -0.03340849638739777, -0.47009187776767575, -0.044038198482238076, -0.8580711063128765, -1.1759974729017164, 0.178853422260806, 1.2157982450299682, -1.3246846610511567, 0.06132548626120763, -0.1851736964119307, 0.4296649330453445, 0.7495034530802855, -0.22361500866509532, 0.07535037803961625, 0.3885865837188297, -1.137958317569077, -0.7936311197993773, 1.4265337573813208, -1.274781382532988, -1.5319900379639104, -1.5200610269760895, -0.5237040362715236, -0.23523287587856934, -0.5309374410222728, -0.6139553521933139, -0.8419402744039494, 0.13956998673569246, 0.6896608741840417, -0.8756933997012083, -0.6686360095363691, -1.9121234039838189, 0.2740228818535006, -0.2997662614977683, -0.3222319229413777, 1.404999611134211, -0.3937789396984594, -1.7066986925509282, -1.600044737638282, -1.0721433737286628, -0.12761247425726382, -2.2626460240599946, -1.3255397310755548, -2.173623672537063, 1.5194967396367123, -0.9910398935481257, -2.2600096351131875, 1.9927948319771176, 1.0765699000539573, -0.6876524146350823, -0.7962219083608139, -1.63288813379166, -0.5225053673690284, -0.3307350048058117, 1.7205417861082766, 1.153751620902692, -0.7392074885825325, 0.6365309950325564, 1.627018640862527, -1.5367981385995513, -0.0017521514701106294, 1.4998904188163706, 0.537090091351608, -0.6171597174805361, 0.2843885176692608, 0.6324348392753586, -0.775742139172308, -2.162331094779615, -0.06509590168206773, 0.44491224425624837, -0.0024862986196713664, -0.5140516207220993, -1.4970375134864407, 1.9094662590872788, -0.3796263766308207, 0.8435148739381622, 0.3401287153775562, -0.8608290240531933, -0.5928854199890417, -1.6959176775441525, 3.102186051466945, -2.07797123208448, -0.3777174966384709, 1.3068237013397674, -0.7714541619535973, 0.47613562348898414, -1.94997654966199, -0.3177858032659767, 0.8362093222898106, -1.9014001850502191, 0.014524658989502247, -3.6631553905362084, -1.1394735348895346, -0.7872313771042975, -1.3022457668600094, 2.3180674279685385, -2.242103236118398, -1.2650707799580534, -1.4053193149108048, 0.39005357028259485, -0.9361693053234154, -1.5300632933119465, -0.9490656306532905, 0.602956685692268, 0.019800486912807388, -0.6319463823341624, -1.2001560673311615, 0.22398470949744476, -1.768827012756571, 0.5358173408559421, -1.6100920798108465, 0.6411869106773916, -1.6110449894121552, -0.1720090722737355, 0.2900617215015572, -1.9242570705992208, -0.8184466934863489, 0.2741396353963828, -0.43962842459951784, -1.7755867103216507, 1.9709565809391811, 1.6741499200251897, 1.5427292612662111, -1.8240428386370233, -1.08984224088859, 0.24772386128524032, 3.3189961003093043, 3.4140509529324876, -2.7128696612988845, 0.6713019182339847, 2.278329398941612, 2.08912835423864, 0.43349007832348757, -2.118930863731404, 1.8148183731272887, -1.4842003988237327, 1.0808168444325754, 2.6057022821101534, 2.8166903265186334, 1.356723294719154, 0.7592894921537026, -1.2569467392218625, -1.0648760253646599, 0.697724167876645, -0.26948413233125196, -0.9887277119580521, 2.1129229667559906, 1.7407090834117023, 0.3017095347987637, -0.3428596759963559, -1.7933181654836352, 1.1524234109699698, 0.37822544575566425, 1.5151640195862843, 1.074994347411359, -0.7476568088118474, -0.6545912861193937, 1.225186513139884, 1.8779014887127587, 0.6531744322868398, 1.3199208260389603, 0.20970494412520324, -0.4880756498876222, 2.1384302099690196, -0.6907560859452487, 1.787880384985674, 1.5261450339897322, -1.299900118872966, -0.7451993373400247, 0.12612760719564425, -0.8121296106284589, -0.839705956788565, 1.1446000358291963, -1.3678085738629604, 0.6487594392829119, -0.5161509950879937, 0.18648792229119793, -0.5262795144424696, 0.6793020827441411, 0.6344300689786088, 0.4103292188478, -2.1245035240623658, 1.2650091858669317, 0.06838190524133722, -1.926364118045115, -0.3178379254442724, 0.23555443757705327, 1.9681711277011347, -1.9929977994797503, -1.2510636220125835, -0.5375238249164151, -0.3314406005984355, 1.5505382334932052, -2.6323013551042576, -0.4478172070772537, 0.7266552542362653, 0.7041692406378195, 0.35232920141582874, -0.774311328069737, 1.4219558388458253, -2.1499836972002333, 0.467121191115768, 1.7215603857707835, 0.48884355265047214, -1.4686185491417851, 0.5851826889121128, -0.5483150776246059, 1.525258526073815, 0.36263502109348794, 0.31211218816978964, -1.4666251554037393, 1.3353473917014744, 1.0596247005436745, -1.2634839731768717, 2.5490631445346863, 0.9395900802564005, -2.511047197018777, 3.008008699868771, 2.3390441109100957, 1.103911800034631, -0.13149929709370584, 2.6924271597980045, -1.4646770370108908, 2.160826607677167, 1.5119166670275241, 1.5957649164153944, 0.8364079451057232, 1.0333685793332412, -1.1083753375152183, 1.67162917794162, 0.07376903690539116, 1.0874514505256956, 0.22605472051769498, 0.24894267819572286, 0.05172307056126258, -0.7411520157371969, -1.457102232656223, 2.4066669730398185, 1.2869402548548927, 1.825018959805107, 0.8840033543769517, 0.5400694528591261, -1.3764242194122458, -0.36316808441724324, 0.6624812255992345, -0.36348359750205717, -1.3131370348391047, 1.3723569997390266, -0.29730230461212986, 0.8594563975650187, -1.0106686768044888, 0.9300229764945301, 0.12090729570828199, -0.4783500413672171, 1.9099690800482825, 1.072173483810501, 0.3022265875530342, 0.594425866269915, -2.134513010901387, 0.6278838749647148, 1.6436647040183698, 2.0324390890474726, 0.6971761030111686, -0.4784360707831235, 2.296181531832694, -0.7785603946089791, 0.40802935047298533, 0.2474733712596427, -0.2508500827494637, -2.574207600945896, 1.906646694623274, 1.084540470578761, 1.7852136435282295, -1.2943899118414632, 0.1962323448592709, -0.31026533424457403, 1.141169087780313, 0.6275032399036987, -0.7881034309993986, 0.5357395813376559, -0.6200628143041311, 0.8904995197828282, 0.4108585172435786, -0.8027200361055766, 0.254176151733697, 1.1762351521790284, 1.6222345627342756, -2.769314155511405, -1.147515376040104, -0.9872171193777315, 0.15077370178678676, -0.17569577365991593, -0.8147571337423043, 1.723865056071791, -0.45164312243683724, -0.5467323348136607, -0.01236483913796671, -0.15251354282527624, -0.9021358634334227, 1.2278923813517482, -0.46532068695710266, 1.1693730134537954, -0.14909190924368976, 1.0504976600619627, -0.35982898293110355, 1.1054637020573617, -0.9981239043492599, -1.1227255560899156, 0.16673018364254752, 1.2196070235715468, -0.01653266286230325, -0.39782799747653874, -0.10312971754762454, -0.6250772549741662, 0.8853817739730881, 0.05030703734832173, 0.8364469257180116, 0.3324814876238778, -1.2178098877879089, 0.607473131863058, 0.08771364984379623, -0.23367447395707042, 0.16103095989203867, 0.07370010808318879, 0.5841607688906053, -0.5280528866167361, -0.5316093683194087, -0.3501311153833424, -0.7748961453691532, 0.032278128480508476, -0.6610981377299946, -3.7655341208858255, -6.008017281297542, -29.025694644775566, -9.000192483761321, 6.928649074713738, -3.3237302427353663, -1.811200144857945, -0.3582898370596133, -1.5201634419825727, -0.8490633067769157, 0.19922259765789446, -0.5692590073198833, -0.13867578619516352, -0.05413672377346743, -2.6791952554225, 0.7106821421169359, 0.8022829290253786, -0.8534074405433314, -2.0358187320227925, -1.1781770136025347, -2.0453852563848356, -1.670922061851588, 0.2387270255159206, -1.118759065847786, -0.6949086895736847, 0.025894049980534316, -0.35183284572237467, 0.2873383503216405, -0.1619213206949538, 0.2966762437708376, -0.2660262259262689, -0.7153737732584039, 0.009937073891513902, 0.4788643352563532, -0.14553671163596987, -0.6880669964401415, -0.14556391848321912, 1.2840522551538442, 0.44629343827487394, -0.30350270905106635, 0.09605539353462832, -0.43836402569926247, 0.3739610162390688, 0.36974312809704585, 0.22826091922511735, 0.23548997609637987, 1.4247177909395397, 0.24582452000397995, 0.17099768509640592, 0.4544504912643775, 0.3987361292291702, 0.7652876665174673, 0.6612383435150359, 0.14211845583539445, -0.20419654863425032, -0.10991275203589272, 0.6104249854749086, 0.8378283752569503, 0.9926857359329676, -0.13034617154033853, -0.1170876875715916, 0.42856705264618483, 1.0868977354473415, -0.22285742269002926, 0.533805204822823, 0.15420831404682858, -0.6387682279712166, 0.39818892224237157, 0.3035112511905357, 0.5761291338164323, 0.29522271069606243, 0.6738167557088861, -0.06753461288207598, 0.1801799761944335, 0.48476903206502037, 0.041577375871290415, -0.17895199002711804, -0.0520268849574128, 0.7392983033775642, 0.06234408882380132, -0.4303404408458649, 0.01776212383566608, 0.9282054004615637, 0.23252007522815024, -0.6135196983114112, -0.6286583068505996, 0.48647057059183807, 0.28861991275491305, -0.041640173393518165, 0.35541212418702456, -0.4122753457245237, 1.1373747990281247, -0.41026456251829074, -0.16872247169083435, 0.7325065606610852, -0.9113970985709504, -0.47249300797425536, 0.1079619620344344, 1.2167286198809102, -0.32317089063254806, -0.12185988180060078, 0.2942003195404641, -0.0722629429993079, -1.0630575192995675, -1.0305503799609104, 0.6296883770320226, -0.3505183517282757, -0.5059986715416562, -0.13256948236256083, -0.29590460360234105, 1.101642177384856, 0.06301015873995297, -0.1798700366377771, -0.5495266832919232, -0.7211385646124557, -0.11080125739129308, 0.9959877906616056, 0.3689199144333548, -0.28554779483526044, 0.6340435946139815, -0.05247979774570572, 0.057539772970441626, -0.8884152702378953, -0.16245393409555706, 0.4040438974782565, -0.22067970056570968, 0.30565016332467293, -0.39824722761470865, 0.4282669326284619, -0.4357666563156848, -0.43254092367227326, 1.2677869689832173, 0.10412665164468951, -0.3908500272757224, -0.6874125762441264, 0.13441438765190755, -0.4151791068585002, 0.3526367830661118, -0.8577920822733448, 0.4533512715106142, 0.5880107007790654, 0.6846739780551364, -1.0288846689497464, 0.6209016900217128, -0.5400870138407365, 0.03285581659485944, 0.09598977206477845, -0.34213769413066064, -0.2615127579800403, -0.9621076050951154, -0.04534743077764738, 0.19185590004919595, 0.18970608237328962, 0.23833549642758728, -0.519050741236139, 0.007361012316600227, 0.14621666900974298, 0.7406940452881556, 0.12142551138097257, -0.40706817488963665, 0.5807259035428347, 0.10781902677227732, -0.09607251681414065, -0.09096186188493526, -0.5991484428205418, 0.03754925225612713, 0.17920384476369544, 0.32477053374644493, -0.4778889405185267, 0.34105716173391454, 0.6957419831132536, -0.17958831141425413, -0.23778081349875302, 0.35673481068359975, 0.2300747744451996, -0.4013439180465439, -0.42706020716242793, 0.8699540429035792, -0.07175145665252601, 0.23666617639238938, 0.3096818409904853, -0.6286936879822257, -0.16483859130275638, 0.5818389427200931, 0.37766624468146665, -0.6610809978089395, 1.0391718655508548, -0.5597607747380287, 0.08696435609205136, -1.0417835296537434, -0.45490350143797587, 0.15724088715005627, -0.8554776721524117, 1.1280750567503384, 0.36441450349401433, -0.5377322231548869, 1.8144416089371318, -0.33136584379793366, -1.1063025718275268, -1.1424960004595475, 1.5418232134385559, 0.4303738462319587, -1.5544405365520195, 1.1712846410794355, -0.1657187496571099, 0.25036335954145916, -0.007909763112358569, 0.2787413386421972, -0.615920593647991, 0.07807255450177117, 0.06349472027762108, 0.47831362535448313, 0.2983349999252548, -0.11452909276754746, -1.7984604107979132, 0.15924151883211102, 1.0486539153236791, -0.16781573537681455, 1.741807235700187, -0.7187678568815585, 0.16586828447001353, 0.017528102113642287, 0.3665609249917486, 0.5863388430819026, -1.1472531540349193, -0.44284551698920105, -1.2062631405199222, -0.2696044952813325, 0.8754094085779828, 1.5814965757928288, -0.5079670079972067, 0.3670397047649567, -0.011030176991241342, 1.1580739781694294, -0.5268625729326428, 0.7992131931968883, -1.544189782842231, 1.238977143176149, 0.13591397573028813, 1.2581069107664844, -0.442647888905399, -0.246633717354473, 0.21962021911645419, -1.1427671374833344, 0.45011275451464167, 0.9532205195414715, -0.5322114940317472, 0.47233091986854636, -0.07338145704217448, 0.42590791696931457, 0.186462419338818, -0.7370160694493245, 0.7763761470164082, 0.2472851404333654, -0.7451469655625113, 0.7978157807688767, 0.6399566518849183, -1.0138609935351768, 0.29256606339889785, 0.405925926212447, 0.6123366946534061, 0.5593411292193117, 0.32837419903623755, -0.24815700041430735, 0.20258672451624604, -0.04800243986519585, 0.8490326933354447, -0.6456535120733182, 0.4420106107849047, 0.37617368496919856, -0.07646034685843693, 0.5054870053553842, -0.08705917565956282, -0.8541968387330555, 0.13841273958976566, 0.10909230271459866, -0.07080644451705416, -0.07897860779711695, 0.21872781508615974, 0.11431730001680943, -0.02135449768704529, -0.4232508367047918, 0.09726548447454722, 0.3587551727441687, -0.839270313439248, 1.237554457025901, 0.4199994426032023, -0.242928860841025, -0.9193203695611606, 0.4855644977075402, -1.1001793137157567, -0.3199836805632977, -0.31144150348850635, -1.8931066521913795, 0.0983732249837495, -0.054416143664456816, -0.4634250164161042, 1.139991133789067, -0.9416312253000044, 0.3623996122064338, -0.35177710802855006, -0.06417400773237507, 0.18214179817139625, 0.3724493700475607, 0.5411520331541539, 0.16756394768701383, 0.26150343368924067, -0.7882169916323107, -1.4662128694378602, 1.2622582110091911, -1.0046194042804069, -0.8079732321619388, 0.48366785663250006, -1.0097518365018152, 0.5130159411944376, -0.6617771889647565, -0.024060187806421843, -0.388930371702664, -1.8819987483003189, 0.33982734237634143, 0.5804587944595394, 0.3278134159800236, 0.14823376918788367, -0.2576855822952923, 0.17506229171652601, -0.6244235666056256, 0.6340268041921173, -1.0368113452084158, 0.10970400093934125, -0.5031610779967742, 0.48754911790212024, -0.832057349156899, 0.0982147516154687, -0.19990026753922266, -0.12278981382880227, -0.5996846783753657, -0.17258075401949027, 0.3758139217133965, -1.082866653909653, 0.7019613318847561, 0.5233590370881921, 0.8980459248248779, -0.6669162336796747, 0.6742121996619976, -0.727679577979906, 0.07509834215725514, -0.31380319036956644, 1.7995534792911103, 0.01323334042258498, -0.27548478904114965, -0.4968654103714724, 0.36976269996452327, -0.2657720919882561, 0.09483390387095508, -1.0448375617219945, 0.8996613412669227, 0.8603330097559903, 0.4056383277026637, -0.21469274996975696, 0.21277439185430289, 0.06203811670271908, 1.8155272767964261, -1.1937476573805168, 0.27678090459119764, -0.3073503174771262, -0.04823997944699978, -0.2486716595796712, -0.17959559188885596, -0.3749607829332692, 0.41070928636983717, 0.2319202265295312, 0.6938675293535016, -0.08555541540525494, -0.14714204630186412, -0.5306714197388608, 0.07370479984855015, 0.7137560114894282, -0.2985705580836792, -0.1619478868717515, -0.24868835013054855, 0.13347611592345215, 0.7787601995859378, 0.7629853371217054, -0.5792303134648321, 0.4307075491610335, -0.9165357713095877, 0.2870189901247999, 0.5234821250700757, -0.3704332631872842, 0.2583467742674732, 0.2352804921397026, 0.17274174445591733, 0.4574461855802342, -0.3020118521704595, 0.5809939851299665, 1.1114855268551933, -0.04789948218759244, 1.3673623018876144, -0.031804351121251594, 0.4161376215487979, 3.372405590453129, -0.508329005937329, 6.698894225102408, 0.09378425081298589, 0.2717219835184488, 0.0015161923895616468, -1.3609203645303474, -3.37622375723617, -4.0995882584808125, -7.43664300325849, -5.769758750627619, -5.143970086597784, -8.834965413478933, -7.827387376681071, -2.6661233087860507, -3.5898321669635287, -4.387919200354305, -4.061560023861922, -4.119511507486069, -3.6227998136191726, -2.31286017724112, -1.3080073598513333, -2.1659537397654294, -2.700107152460859, -1.5610722582355234, -0.8638115416968819, -0.18647139663131315, -0.29757816731835973, -0.5144070862641138, -0.15270886480143828, -0.2695813795189211, -0.9399539125669806, -1.2847105804820995, 0.11577304921212679, 0.41526513671162213, -0.8742299919899924, 0.0937974512924259, 1.1722691937868235, 1.2382571931242867, -0.3556986365140035, 0.43082612393542485, 1.3926026792727815, -0.47944361557664283, 1.2396127508889192, -1.3728876607408032, 2.409201464700706, 0.6597855356260544, 1.4167907206625783, -0.0006123075905372934, 0.5327347314476997, 1.5038302475728171, -0.054028668300971416, 0.6811263637765859, -0.23741499217345874, 1.0926156937335656, 0.536614074318161, 0.18593930240163084, 0.8528854104780061, 2.066464899329636, 0.1706951053667179, 0.014277534050216555, 0.23303102204410886, -0.6128143861679086, 0.8219353699136943, 0.3221291532237073, 0.3373085571368325, -1.037589246173814, 0.7068242988440174, 1.0664706966110722, 0.14348340600195347, -0.36111713635368475, 1.021513419371897, 0.21978723822810556, 0.7094635909680188, -0.02103085050386386, 0.9703024799685709, -0.16290622521062317, 0.016165810276374464, 1.1645619571898675, -0.5404491766544788, -0.08416680810806802, -0.08410435589827747, 0.19794384844678478, 0.7435197129497594, -0.009821316355241123, -0.9106573582290659, 0.29876184862923266, 0.21819366362710657, -1.5143273106382231, 1.6985445192509576, -0.994563717625014, 1.2424179516058422, 0.20709341094291212, -0.5261607242352875, 0.17723270551985312, 0.14793408740079705, -0.23106479164292837, 0.39209949273378686, 1.2264172614115332, 0.28137816181570846, -0.886440043240837, 0.43395978793583845, -0.17374787717008505, -0.7397313704349335, 0.07182239963431923, 0.7043686515575267, -1.5438817143468218, -0.04085847580288673, -0.1588447554610532, 0.17570617227804805, -0.16689581870669667, 0.026891405886570515, -0.8326024584678132, 0.21760035022495333, -0.3000132109878817, -0.8177130233318959, -0.3063349532207123, 0.3775282655868997, -1.4149101107214184, 0.3677151192346665, 1.0483715340210313, -1.5738022368615174, -0.2396163295563359, 0.8909912688874125, 0.22832969485770646, -0.25517102196719577, -0.016890072879647392, 0.4145128691982581, -0.13308489395693124, -0.9975946959343728, 0.956129739932448, 0.6078643498969182, 0.11195244958276872, -1.0426406086099111, -0.20717428397284532, -0.4059844535759993, -0.3634207497424183, 1.0716461902734533, -0.5879100044940012, -0.006001548024058043, 0.3868008604846107, -0.14908549690673345, -0.13717919322269514, 0.5349432225800844, 0.2271721058455488, 0.06122362472644042, -1.092961939716328, -0.1552863691545048, 1.32476621368314, -0.23268955758556406, -0.06325718241041794, 0.8149851010499355, 0.8600999662990444, -0.46167095893331744, -0.03377579500568965, -0.22506923079409888, 0.28144300066789313, 0.30548089275242535, 0.2697967864113979, -0.4443972194728491, 0.8407285492111006, -0.2354424641134074, -0.034779889011896784, -0.7861685041998551, 1.930316294038342, -0.6810938258944371, 0.2189649924153739, 0.4016690872445061, 0.2757108103648276, -0.12111559207410182, 0.9670580205401922, -0.20766950856454372, 0.2577018343360389, 1.1864149091739395, 0.04909945008786886, 0.2262359727617379, 0.7232232760861257, -0.020277680258107864, -0.07694945247105499, -0.16083156433398182, 0.7655367226871308, 0.4853642307799285, 0.3275603729330944, 2.770892467983975, -0.513831369415316, 0.27141511407903207, 0.8050186643871464, 0.032934991541450985, -0.5492876652449026, 0.0167675778626067, 0.2605813267950846, 0.6501291117531602, -0.07525835644978929, 0.3730217393704138, 0.240946308921475, 0.21304236264945092, 3.242758557514567, -2.0001213786409995, -0.018209144193019337, 0.2755019532174912, -0.20434661060570972, -0.6519768558364041, 0.11769046884666817, 0.3665542825152472, 1.4790064572679102, -1.2831530587362003, 0.2280556387916462, -0.8626355346328121, 0.4939510165807446, 0.8231046831560607, -0.03449656831610097, -1.1270446798067177, -0.3387005917796963, -0.5951100571063039, 0.764387322880699, -0.2201898830032085, 0.6367324998359473, 0.444051433561914, -1.3675171176128174, -0.9061898560545882, 0.765497096814759, -0.463230552716399, 0.2869926644665019, 1.433924383323766, -1.3700999117577304, -0.4488098704980811, -0.058270217865811144, 2.0377812975842873, -1.1167144994875366, -0.3993529657975064, -0.16637890689101292, -0.9630505521159372, 0.4404989823714079, 1.7718405544980564, -0.6555870011715184, -0.27033727736684426, -0.042585469125402835, 0.36843070233054315, 0.22544679379537771, 0.17217330927376961, -0.4103977889835845, 0.7845549450222734, -0.7305043157306608, 1.055861595598961, -1.0552488289602733, -0.11665210135592441, 0.23566410134948004, 0.4120300314502389, -0.7330593128062719, 1.0627052276659243, -0.23008213278174414, -0.7612397076311234, -1.2351732183235138, 0.4205583037464446, -0.2512428286310083, 0.5205298764611836, -0.4434049134765645, 0.5659905093969304, -0.21988788240723944, -0.722547322335143, -1.2349540949309916, 0.09139849660746487, 0.11986421393716311, -0.6713403207066644, 0.35901341843987805, 0.7123019385414544, -0.1971745499812293, -0.0748198783334245, 0.13054584932073626, -0.41800622402788584, 0.22983354917598747, 0.21809907611372242, -0.053013130989369696, -1.0839756603278232, 0.25755240072596436, 0.33850217659138526, -0.30855603358870515, -0.5404072435149501, 0.7472116001611374, -0.586136438756972, 0.8956481771767546, -0.10795087012733168, 0.318974397737614, -0.421252003633749, -0.3020947460508989, -0.04420048853379771, 1.2945324054241378, 0.2033346389198302, 0.7372169885507432, -0.4482145356243729, -0.7022911940972142, 1.9081408255652068, -1.1400924461939317, 0.24505979776075001, 0.3291271674844497, 0.9941749064366721, -1.1469640894965498, -0.5818608770157517, 0.6292630708153211, 0.5491165880141493, -0.5281809203927579, 0.055243923663584125, 0.8632290596093088, -0.5189295971993276, 0.9041404349929683, -0.6998257756924989, 0.720147831900466, -0.1258819504402034, 0.36384710047497987, -0.25060799044867366, -0.5530897431468086, 0.2804909218957768, -0.09637762021534242, -0.09156055308158798, -0.301962315292526, 0.9380760220908057, -0.6958884303780236, -0.20684955061389435, 0.9991267814484861, 0.08777979727239275, -0.2804231728764311, -0.07245376816743289, -0.6111217734421279, 0.7528840329317621, 0.49299251349199774, -0.9612680786703742, 0.3111071123121117, -0.3109632776580447, -0.5441169482334041, -0.30488571113504076, 0.36964296191243373, -0.14952430975506834, -0.0439532437825528, 0.10313921459043478, -0.15365436564821944, 0.21215291188702817, -0.24376279840361395, 0.0065775708836344395, -0.554850144526409, 1.4889490014732853, 0.25777617914310086, 0.30198532922378396, -0.3972459341647225, 0.4519786988144829, -0.3098670412851289, 0.5384753479195531, -0.8358783623376496, 1.3662616732220119, 0.2119289100646757, -0.19051103538365807, 0.318098800213944, 0.020703882924259683, -0.2532057555541635, 0.795686330114513, 0.17590976904675087, 0.16910743052214552, -0.21766282778597806, 0.38290951876758617, -0.31689378816295194, 0.2293031904318376, -0.552632234639447, 0.6711308706408651, -0.13881225638112288, 0.31472021270316053, -0.47174548622395185, 0.08291656807848284, 0.19866065268461958, -0.17729657430923124, -0.7703202058483045, 0.8352964868110053, 0.08571756348101663, 0.2873423689204033, -0.28281527820363406, 0.24351536641631735, -0.15729208370238226, 0.4258081787222116, -0.7927033862407927, 0.19009758324399667, 0.6950758266311771, -0.03417881689114114, -0.03416240401323828, 0.28968915226212877, 0.056693879694040904, -0.15486282287280959, 0.18640586106964768, -0.24590390432811468, -0.24087035831079412, 0.06670173018475284, 0.3754648030067739, 0.3526927728755255, 0.34470697545725965, -0.19433232924602664, 0.339489592999066, 0.3010038169227276, -0.24964334885666362, -0.09902002420463764, -0.3270364240126725, 0.5942736819188483, -0.13492492374864623, -0.734324660200778, 1.7878584038565746, 6.2676490823112445, -8.201906338299814, 11.306200832849646, 2.7976634097594784, 2.1108215664188945, -1.8251142382430814, -2.2771728080708784, -2.783406603148889, -2.716506978959097, -3.806310736541885, -2.103579867499202, -0.49375942157993047, -0.546463251830961, 0.574019338158787, 3.479558868671849, 2.3793162762632734, 2.2585777366160613, -0.46065226603713055, -0.9587505550276634, 0.0932370266420936, 1.2291188987901376, 1.844044076219161, 3.148406352522497, 2.831076655574404, 1.3406729965202537, 1.1528449953450077, 0.45582994206051747, 0.4595276450008764, 0.4852365089941332, 0.5492396551234943, 2.6142706053050073, 1.856217543004129, -1.2545784026983209, 0.25679460996328757, 1.4434739094929183, -1.152846118232133, 0.6334623515799046, 0.8462832290223166, 0.6246246312251245, -2.3576660137361105, -3.1147475625312646, -0.1312597651890068, -0.5529827165438855, 1.8973447319325911, 1.1344050245522477, 1.700817546305249, -0.8087704058082567, 2.0990885502588736, 2.5534695208500766, -0.41500628325839584, 0.490961600225628, -0.7270153137944596, 0.3490934210855917, 0.5711009618483749, -1.0957719097577576, 0.05675533320479861, -0.7909387018326777, -2.4253574804952875, -0.7797648321667148, -0.7154228521014577, -0.2597809440646141, -0.6732799911142168, -2.0621682338191594, -0.9364990063173154, -0.7987699666425336, 1.417380980315397, -0.3616115149870365, -1.3881752448911078, -1.3314151083685786, -0.10295826313994294, -1.2329043504696622, -0.5520694368285061, -1.2185027999083407, -0.27863262553676593, -0.001480552054695969, 2.2789998148880453, 0.5784085074609256, -0.5397263940806296, 0.37445107773772507, -0.23999084620665903, -0.7945777926578232, 0.7819306106660874, 0.9224735687236547, -0.4496790335509754, 0.5549085946903893, -1.0590576433295642, -0.4154184749070381, 0.5433936172434483, -3.1029878411055454, 0.9634242421147011, -1.1062688688048352, -0.3979016242787218, -0.9241767422291488, 0.36876471755638474, -0.16612821181316043, 1.2973524908786809, -1.391437896575816, -1.2433733937816978, -0.2607696751192457, 1.6666366134024753, 0.024886543990559572, 0.11351594225791171, 1.2858677148357462, 0.0916088895226529, -0.620333316982674, -0.6105212646752574, 0.5295723523416289, 0.6201497900166418, 1.1275780368875066, -1.130585420083335, -0.8937876961788888, 0.12589641226698667, 1.1709287846190897, 0.20846240390385323, 0.462770562871297, -1.1083213822362024, 1.3527870721713686, 1.5802246776644981, -1.4199487456138766, -1.2446083343492955, 1.5731898550772623, 0.044214559492193176, -0.44732115355666563, 1.3099494533041312, -0.683662143625535, -0.9420034383754289, 1.2764095778091304, -0.42885579285855774, 1.8664394722478328, -0.9788100905362143, -1.1361302536204327, 0.36478544372364, 0.007814514355156753, 1.5774654294388837, 0.23434653068607364, -0.18806366133187213, 0.44947927924073905, 0.5129350771486174, 0.2623142646724147, -0.29260549348086, -0.6362614355808249, 0.4486197845928227, -1.5007381094651215, 1.6592915821671526, 0.5836269981862988, 1.0215486985428825, -0.22537951429347644, 0.9469338270183517, -0.5407101545121491, -0.9728805147010986, -1.754804241814654, 0.742301492523512, -0.4305407712954813, 0.45443209860688905, 0.12082615127334699, -0.413003123369756, 0.6800860817830967, -1.8140811680455147, 0.8853016472265155, -0.827466428937367, 0.3956619037348724, -0.5367278431161792, 0.41211155538041616, -0.5060437095300754, -0.12809365019851432, -0.3248267755526757, -0.47613927467251727, -0.2643477513814231, -1.7474962722230587, 1.416440483228604, -1.3239450669432309, 0.7301496753241421, -0.7365768074647163, -1.466294901504301, -0.876607810930551, -0.505631844994237, 0.5456386712305561, -0.9289016948837474, 0.5091732207962623, -0.001699642865252187, -2.150992530563573, -0.2033941772307042, 2.106322446495821, -1.2763751506035552, 0.15814805853781783, -2.1187614708005698, -0.16671185026602217, -0.30841774887799756, 0.5989420646149805, 1.0299829771328055, 0.2462510779049632, 1.4501011261725067, 1.3015606023225559, -3.1587752198736205, -0.9326374039837071, 1.290310074683008, -1.9159843498754092, 1.0020958600260659, -1.1314187503935895, -0.18520332695377956, -0.08286775750449155, 0.03294836692087177, 0.2060880339762526, 1.0499883829795447, 0.221095832199636, 0.11015643861829788, -2.150884054565122, -2.4007616785078327, 0.5018704641851183, 0.006887058362637812, 0.8631328081829891, -1.1891214891526714, -0.5872327121833152, 0.1545936171654925, 0.20482818104481426, -0.9282459753729125, 1.0319337087456302, 0.8780050193862114, -1.6964454647393843, -0.68780835225203, 0.3000408560861409, -0.3914927663139081, -2.0466486295010493, -0.3179703999791333, -1.351647307384937, 1.5197888484917665, -0.7744041942202582, 0.5633254569256401, -1.3657622328818342, 1.8080370323894746, -1.7986515144516468, 1.7476010196161125, -1.016449574944417, -1.1964958076959817, 0.6700460577775372, -1.331063625013874, 1.652184228652502, 0.5416086074943138, -1.3055505027712948, -0.46889778574994445, 0.5148121052361037, -0.058942047010999754, 0.38871347957613345, -0.8190166131586815, 1.9009894802509733, -0.06958558057047233, -2.0048777518438983, 2.2055123246247414, -0.6340826819175777, -0.01358918868676376, 0.4652268742143367, 1.1588013584621648, -0.07088424369137264, -0.8704166819492801, -0.026920095764135833, 0.09842945090750486, -1.5310945300857024, 1.2229915970084866, 0.5291618129353657, 1.000330155875639, -0.0564392593926918, -1.7161273244424289, 1.6375362629723247, -0.02781607589923263, 0.5450183130840192, 0.12554488416524398, 0.38537738384891346, -1.5179636730018098, 0.7743224061737235, -1.0358519597200702, -0.46621549266758444, 0.9534837321229508, -0.13742610169866146, 0.1496681839755557, -0.45658904920579513, 0.4185448056165467, 0.021444779258644832, -1.1927189225213313, 0.4605493958071549, 0.6440652580148704, -0.19826169921916673, 0.1654899210113292, -0.1201419392383077, 0.009353055353924715, -0.19712112970806311, 0.14104958617575739, -0.3690449886199894, -0.5889842629828826, -0.31285317820212294, -0.07687996037658275, 0.44480723489873375, -2.1456450970453282, 0.3278291073186496, -0.8301095436800343, -0.14357544606764538, 0.5617898845060592, 0.5771493618709201, -0.6227457477967794, -0.9095811962806174, 2.169259838962153, -1.0497551106401724, -0.8952714429095302, 0.8828590317092678, -1.6354882392873473, -0.2559331259889617, -0.6447949293267123, 0.6885505399612509, -1.0049480914612237, 0.6476396972817682, -0.2937745247876528, 0.815213355343786, 0.20588664661647615, -0.06326089565293265, -0.6611997121761538, -0.2590105847967686, 0.3881775615502383, 0.5962440852213903, -0.781587531102608, -0.3629992576586882, 1.2299334042854564, 0.006162562388525509, 0.3701410469189126, -1.493126280846312, 0.3662343706963125, 1.8202820733737586, 1.1477822112369556, -0.5603150304805947, 0.6709510622907799, -0.3931583018678904, 0.39384510403179207, 0.1854991393067202, 0.7642103265111039, 0.4033864145160534, 0.046186724104807717, -0.045225845369300986, 0.3275826291889389, 0.42884895181893007, 0.7990499030892707, -1.5640754192969823, 0.05135586261409237, 0.5258807293045306, -0.825678008740395, -0.5343443315286638, -0.17831342500021402, 0.5690296950708358, -0.6061834947729423, 0.12750256609262484, -1.1860307346787449, -0.29271204844713217, -0.47834638676671487, 0.24116930677845225, -0.6481899206132802, -0.4240826759098222, 0.78660724682973, -2.4735910523866522, -0.15309908501562827, -0.5975852977839293, 0.3187865412483831, -0.3715550427385813, 0.8139788687993463, -1.1501470646248069, -0.49129001620270785, -0.40858496520614473, -0.08446747975572161, 0.15245887290386628, 0.7555269605267251, 1.4580137307512868, -0.9152386773696565, -0.09253589557352986, -0.0820598466839631, -0.3946487062217768, 0.4071187828481864, 0.41522478526834466, 1.6473275483886767, -0.5970936166493341, 1.0774160325170006, -0.018699017132996966, -0.5874869570282107, 1.2481898020499835, 0.7574498982933884, -1.837177650537959, 0.4051323829886539, 0.7224851443876589, -0.859587464429288, 0.4321804626049377, 0.6936622802984644, -0.5486705144780395, 0.0014844301083167216, -0.8005933928756742, -1.0139077753217165, 0.15487547903101803, -1.100145524922687, 0.8373272576997977, -1.0621332932487215, -1.1091615266142618, -0.9377066722626988, -1.3703032489763687, 0.8460186605338627, -1.3000281597748513, 9.852040186091973, -0.6800097632294366, -10.01684133375632, -4.92684645392069, -7.0376823567278555, -0.18746764498196472, -2.064195715701265, -1.2923244395757485, -1.6238697168004315, -1.4003069559770351, -2.9421568788987758, -1.479466418142968, -0.085796899248982, -1.2095207167422795, 0.42887592520673157, -0.2381014636037158, 0.5910440544113548, -0.03065503414181713, -0.48283268150094244, 0.5645153420200584, 1.3907120895923915, -0.3245174020820688, -0.05553011245237659, -0.1388621175833761, -0.25499108584211405, 0.5376471158316324, 0.3315196955095491, 0.3922641089270754, -0.030659380576248594, 0.7924469374512647, 0.3328464953164191, 0.2840802926613498, 0.3261591621018639, -0.19081165775395156, -0.03921534082237722, 0.15540386265242415, 0.2768857175137233, 0.7337031186850017, -1.0411355967330256, 0.5963863036046388, -0.21005253569412305, -0.6995411244242156, -0.43800376593902873, -0.12233429036047558, 0.989906899377392, -0.4470823319865113, 0.859343804009986, -1.020795998532533, -0.3727087841328302, 0.4275018664915789, -0.21964092057060447, 0.46039852681027127, -0.01214067718667961, 0.11795877630500892, -0.36380990216986037, 0.4437542517603281, 0.06291868599201283, -0.9774204448445497, 0.5681741019588532, -0.787232671619354, -0.5158885470026803, 0.44206131649529984, -0.6469413695069434, -0.05103536321081264, -0.3323036867122401, -0.27465769661409023, -0.4472959869381606, -1.0516283067687475, -0.8824939160928443, -0.7178083328624565, 0.16785639499282337, 0.6080458497696671, -1.1403430238772767, -0.34140877095911254, 0.37343840674735057, 0.9317997827786849, -0.44804041801421096, 0.5728589660564675, 0.3687815204272783, 0.03513054652927226, -0.42307595129660014, -0.22519320493044745, -0.8161121245033284, -0.10885488832744751, -0.3769032512518291, 0.4061808781356273, 0.7377747836921517, -0.05680726554018733, 0.09772749236306637, -0.22955522014573715, 0.18286394476913104, 2.3711293571498753, 0.039902716776467305, 0.062236143332690334, 1.9955230579886998, -1.0314417812924264, -0.4665317331200556, -0.11786285421236595, 0.13434620537740158, -0.42296820231111854, 0.3969913903564764, 0.10727220500569025, 1.2828682866843666, 0.30851555173726997, -0.5273863481387837, 0.751813526398322, 0.8275756977901984, 0.446382033978271, 0.894708539642571, 0.25201742484343215, 1.3410473898648734, 0.729364543776826, 1.787865992293084, -1.7338982714898838, 1.2257220000369815, -0.10143840780999439, 2.0232739762692655, -2.9421301470858974, -0.057049932764988945, -0.19522268800976247, 1.5842707506125253, 0.35733965670942885, -0.39556008206287524, 0.01310369162739765, -0.6115635245111132, 0.3083071538955785, -0.7011876615279061, 0.32559949528457705, 0.4608306588623138, -0.39148959839055497, -0.06369998573062866, 0.528924213120142, -0.22389100840794157, -0.5427105925722164, -0.9417248046674653, -0.26363747013010014, 0.9988620911989751, 0.924739701344132, -0.8966845103771726, 0.244462778095856, -0.479874962721488, 0.2970990554630508, 0.18613397107518878, 0.21866592397648782, -0.4834029911098151, 0.13229607976073707, -0.3855693557297362, -1.2166777180181463, 0.8170557353454511, 0.3879850739357653, 1.4274684518248113, -0.008262444321003513, -1.3225286122982087, 0.31639611243702426, -1.0800640495658123, 1.8754048678528814, 0.7862368382876396, -0.0924541268392814, 1.0942165142363816, -1.1037775680326936, 0.8238534822062783, 0.9313086029029856, 0.2116522542002698, -0.19301472532680877, 0.0030848731547693424, 0.6194714089832327, 0.09328380590963162, 1.3028093012630868, 0.23140412722732132, 0.6245728336414177, 0.361125551478232, 2.6057039109316396, 0.6441019481638647, -1.4480142828185143, -0.42967283106957715, 0.6023614183158639, -0.5852309135795892, 1.1305979170171412, -0.9294415575695758, 0.9321776342824301, 0.8684503589226433, 0.9427808713513429, -1.071649238849341, 3.0490472680477745, 0.6617646065395439, -0.626427236409294, 1.0420185071757586, 1.2602530680030657, 0.6512346991732417, -0.9860080995879485, -1.557960073917221, 0.38222838444337304, 1.7076269809419669, 1.5419535604030796, 0.6169276393779916, -1.3742233434738227, 2.1567941251355887, -2.6141646123357307, 0.8266524495916134, 0.3198693991843762, 0.4569364639158196, -0.9376186618716197, 0.8888812029373206, -0.02710551083108737, 0.5867515550768115, 0.6463960999235394, -0.2687689072362539, -1.4583589818999376, 0.7546047126168304, -0.27071413898086155, -1.1410689812356387, -0.2325040000829006, 0.6536052028610956, 1.5068099837860807, -1.2526946660207763, 1.5127313382299885, -1.444315356786576, -0.4718810058735337, 1.581576086897118, -1.392791109500713, 0.8066505590993271, -0.07423402221020392, -0.876752567368145, 0.3811842937391567, 0.2920415869660387, 0.2849779046486244, -2.646169851032762, 2.352231069635243, -2.4435903903946734, -3.070546666620909, 0.6136916854389662, -1.0272902793180032, -0.05886738674346234, -1.3798083388024445, -2.0576086774635787, -0.7230891942763247, 0.928429276764087, -1.870897882601934, -1.4618792670598864, 0.17928928637199743, -1.3466528691794355, -0.6687388979607192, -1.4159723032633122, 0.5567511362442148, -0.5327704071878102, -0.5954319292537175, -0.08469941699172161, 1.0624384884621267, -1.7152416002637194, 0.5980809967928399, -0.8897174918236815, -2.0998391091456363, 0.04624921846880717, -1.2017467068184373, -1.8331752565915127, -0.8223713184848207, -0.4983328570887619, -0.9990664244346634, -0.942794574668093, 1.2135960871934737, -1.733532260494533, -1.6945936204428613, 0.7141489769363635, 1.1007447647105912, 1.5319943899091368, -1.8138702089684662, -2.282457815719383, -0.7916604444887787, 0.5524708815117583, -0.43814104290192524, -0.9451138193347319, 0.08332260580179693, -1.9141164374684834, -0.9364378125796259, 0.7070535155083331, 0.8902435240101169, -0.1154239889086577, -0.8929446111632328, -0.102781371477556, -0.6731432297281817, -0.6802552005565915, 1.362039292869741, 0.8691837722455219, 1.0501041886058908, -2.48019699305941, -0.23916881103806475, -0.4617559490477588, 6.826132352814881e-05, -1.06807282449301, 0.3061416231186175, 1.057374617108737, 0.7132281112764158, 1.9477337420877079, 0.42012361324478226, 0.36000248551114317, 0.6365688677439434, 0.8886613718219603, -1.0977208826693405, 1.167116831871048, 0.10468195277870689, -1.3687964318872279, 0.5341039315670295, 0.5288430988183581, 1.9129316384293424, -1.0458643967782806, 0.6849077403211093, 1.4311591816089757, 1.4896790869305798, 0.22527192645721725, 0.7065026724510461, 1.8327557632452975, 0.2561996238351267, -0.7165006432702834, 3.0819460660135585, 0.7881835299479539, 2.5436532988471043, -1.50397434323137, 2.147051900534665, 1.521034647268421, 0.28873969267747185, 0.18607168750231384, -1.01514247327446, 0.7793506815327113, 1.8185894689046593, 0.6450531651610388, 0.4727664701647321, 0.6653074723887785, 1.402151278725402, -0.7329480483273051, 0.25330856511461314, -0.10090610442865439, 0.00013573793874980953, -0.7730022622193644, 0.7381178528678969, -0.482684017965583, 2.1238613709639083, -0.4000396358607364, -1.4845943916692628, -0.5837925265996113, 0.18662713467157657, 0.1389385039705137, -0.3256374251245588, -0.8808508465967985, 1.3276841046472194, 0.22400549772191078, -0.29708038214259325, -0.10838002663859996, 1.017167818612034, -0.9811861872504616, -0.3455855569217323, -0.4326316559625676, 0.9340048734320523, 0.21444854387988244, 0.19714403324119828, -0.4809324334554216, 0.22494842261662368, 0.4464748347539679, 0.8687263996366579, -0.46812505208865784, -0.7865600493740632, -0.07326773112852693, 0.4948960976137918, 0.014546268195768281, -0.3740998542255999, 0.21695783081768316, -0.12438296842579664, -0.26061251475254776, 0.10247383284110706, -1.110709775101056, 0.34185528994493747, -0.8916848778906457, 0.40518108296519556, -0.3880994454821821, 0.48604327224843086, -1.6448025843826979, 1.614864179165705, 0.22763577245884922, -1.9092996553351353, 0.03567572102943407, -0.1528171279280264, -0.02110099542746517, 1.5050427014195256, -1.229165938754468, 0.08769239117276109, -0.671077540906023, -0.9666728048571882, -0.035005093332003946, 0.938545929429422, -0.5163128547480267, -0.36394143441425275, 1.1063147238216797, -0.32722608742057674, -0.0812701620506572, -0.42802381450399996, 0.26979521180483185, 1.0643169664643684, -0.08008565083577814, 0.3723596955210758, -0.9865402229430267, -0.10182104639002026, 5.19643961102991, 6.039406346667202, -0.5912120563819822, 2.3021253505792343, 3.6792051432500172, 3.7551718379498156, 3.4398493774123335, 2.1591669338035118, 1.9443953393821407, 1.5101365461873997, 1.3034093343385704, -0.08866992120233202, 1.0317209853228169, 3.4775882072416873, -1.1294157163886807, 1.1132643421393822, 0.4037780572047316, 1.0079479443095827, 1.1061785066018657, 1.6660417407974968, 1.7274234745454393, 0.9699165622221122, 2.0244022928674554, 0.5174155567453725, 0.9847306270311049, 0.5092212739065456, -0.02667519308938811, 0.40736963172143725, 0.46873231567887713, 0.4124239070327719, 0.2251221875957446, 0.034636380586148784, 0.37806018568629035, 0.6515162945448693, 0.38730813006588, -0.6405748437400913, 0.16999455689337312, -0.02117844730920989, 0.7999718647883474, -0.243323211420806, -0.018143111767187983, -0.6869546442905425, 0.489158970745133, 0.048538717089550154, 0.9459107961598272, -1.628577670036712, -1.9912023858682848, 0.8311928540025755, -0.35642264365552423, -1.9473352721050936, 0.27595043592481067, 0.31634702238043444, -0.14413637706239213, -1.0581739170182578, 0.27399451585900836, -0.5345100634569393, 0.8244847624163248, -0.8536080273740263, -0.5827595834045831, -0.6386779488877175, -0.22751659249106163, 0.2308361312797761, 0.15150413053845035, -0.06108980175160694, -1.0930871283852395, -0.12206981857920775, 0.4096083813435744, -0.20058603338818798, -0.32705423435112857, -0.431120666942355, 0.24218388823040332, 0.26516488039931013, 0.3518822905040201, 0.669840845789783, 0.8224697403040452, 0.14719503495100186, -0.745867218070678, 0.5099104061784541, 0.1348775680019878, -0.30841075777787436, 0.6793980305041996, -0.1621921494507753, 0.3152198473957077, -0.13716566802988225, -0.540778985276976, 0.1364975962453537, 0.060111398519965775, -0.47811582867085606, -0.3501612712066035, 0.5115610955847475, -0.5081056189516816, 0.4657440625824041, 0.5015089414879161, 0.2981124896030877, -0.22475364400633518, -1.1810189373288547, 0.454736892266232, -0.7033377510750445, -0.5406521400052045, -0.38054722464486707, 0.7737496729615131, 0.17658818582849248, -0.010800681025429299, -0.3021418547265275, -0.3986670359328995, -0.05840233438354331, -0.28898107046581933, 0.17734825175964336, 0.34398922501004475, -0.2785138196912234, -0.6389672193817956, -0.17832856843140132, -0.25755680606040504, -0.12061464965496516, -0.19035945186650224, 0.37963994312336896, -0.501911036785978, -0.8685100468588407, -1.108545233844645, 0.7271196620314672, 0.4886329382432579, -0.6424731865555462, -0.2898392502451339, 0.6423953885650904, -1.161030330369766, -1.1781092998528544, -0.000353395166126881, -0.00779271007090007, -0.35549449898755886, -0.8112041202744936, -0.05231834441343787, 0.6045918224444996, -0.4093791521326034, -0.5955198491962869, -0.38171353912722933, -0.46822500955119467, 0.01750075677271586, 0.44186262495641904, 0.19703005051917027, 0.36183198650626125, -0.7507769839202291, 0.21847732920343832, -1.168641902500114, 0.02672120538164667, 0.3410970812197951, -0.3201530203720939, -0.7184067568812124, -0.45578179525136037, 1.5076251027969345, 0.2662976968557948, -0.5282864189862038, 0.4854955077024349, -0.4427396978903748, -0.14422854693279444, 1.2247550197007093, -1.1808983866563985, 0.8601653389486335, 0.7751320409502921, 0.25370945926497673, -1.2797133253041086, 0.5721388745074176, 1.3770767426741475, 0.9675815188410218, -0.7521016045189268, 0.8923690274636622, 0.2558663046610935, 0.11848874299873355, 1.4907709700275111, -0.3864604975716606, 1.239155090021318, 0.7386133166709828, -0.9171101471550506, 0.03750209942180917, 0.45552855541664655, 1.1590472414856545, 0.8841138561628351, 0.24227906265419108, -0.2928480704253337, 0.45204776769871324, 1.2366450442149053, 0.6733375256052351, 0.5287474815350015, 0.7667972491082843, 0.32185719851435496, 1.348265147566819, -0.8813426572944464, 1.0835014175781725, -0.6491172754552714, 0.1241212187465439, 0.8830117091174451, -0.41764299771076957, 1.3572304183287511, 0.27041544528072925, -0.3787318700620481, -0.6500936354239368, -0.6340989841404856, 0.6468870371550286, 0.23597532253539832, 0.19863467757845513, -1.4668990137654965, 0.7005092940834026, -0.14078357709329534, 0.4096992940390649, 1.7885450834544714, -1.9254518824509914, 0.028612016871124843, -0.22817534316150448, -0.18211983772787424, -0.14636038404844565, 1.4807316331372296, -0.31733990275731105, -1.3013368758272894, -0.175823440827423, -0.9541202194254697, 0.30804848146023694, 1.3620923066649455, -1.1786304565910488, 1.3237883176433847, 0.3108073565425663, -3.5374649559549307, 0.3798656969195846, 0.35830063448453103, 0.694794233209391, -0.3023348603503847, 0.06937748351129674, -0.9862100695850627, -1.2942242157800183, 0.7895007680299703, -1.2822929724677643, -0.8480882013286328, 0.07227830135986907, -0.0566960683012406, 0.047054595404621744, -0.14552857198437863, 0.8122665923296811, -0.2987652946863926, -0.8674635055612935, 1.4618746936486144, -1.076474776132668, 0.10072168160816018, -0.46917042151080396, -0.733666235474897, 0.8039139466036728, -0.42522832114861275, 0.6749994956468611, 0.19948667651915097, -0.3569245011900125, 0.6497059065857975, 0.016382241716783263, -0.2833116809234915, -0.08285582780095492, -0.970894041422196, -1.2141782576613223, 0.2665135940735738, -1.0459882385425174, 0.9674825496579313, -0.42942191662754453, 0.191034526756099, 1.8392307044233964, -1.0288865254011965, 0.3228105677613549, -0.16780238728134286, 0.07652487575180394, -0.07264289910472958, 0.6898099501601509, 0.7919321370548063, -1.0423336856342515, 0.4138195715301091, -0.5078779731544548, -0.47194552462828476, 0.28418406213527125, 0.2296151798708231, -0.6180267086610832, -0.7894573392079417, 0.3987027007642688, -0.1905890659760038, 0.044279859737457995, -0.4115746686321233, 0.019178347355838562, -0.2106435484846859, 0.823869100758928, -0.3697312053062341, 0.23390737118815563, -0.35447476995615074, -0.973998217465431, 0.33292026935458174, -0.8538871567537887, 0.21010272587152873, -0.5145513593249591, 0.10186606900483769, -0.9549286392443699, 0.7791212437406042, -0.3054688555047318, -1.739047263175914, 0.7265068180844408, 0.8798453541947611, -0.6555351428840461, -0.6514636000943815, -0.09379531960834067, 0.4195424260769116, 0.12612673112368614, 0.17430544400763984, -0.13861974802583446, 0.5871631334991292, -0.1644216159212357, -0.028312167737446083, -0.36373422567972086, 0.6792878564049711, -0.37924570193951684, 1.2790474068192086, -1.0785605869138313, 1.1415833504537878, 0.2572603417548728, -0.09038120190499661, 0.2052965004421576, 0.4043694631961904, 0.2743896515303728, -0.3653222316812719, 0.35275213106761677, -0.5215603875703505, 1.0537638495030126, -0.3705260837301488, 1.2709276851409566, -0.538208611200243, -0.058195669836187916, 0.1239025060835999, 0.3886195623702226, -0.0022605724142211146, 0.2524091128425063, -0.5287761851737494, 0.6413931662687049, -0.6336876644762742, -0.3808204982579037, 0.8552533742504533, -1.1216332000703426, 1.428162772052882, -0.6197100031215201, 0.25223065797892463, -0.18709030354704367, 0.8199541910993511, 0.5111488649316419, 0.5084910862361246, -1.1606852495417845, 0.8439398990526524, -0.5888704573512962, 0.2538099344012725, -0.15593381062328535, 0.8979601540206232, -1.046344168776031, 0.6055776384974794, 0.39974115204173827, -0.025917318476341062, 0.054705442407581066, 0.28725461750903997, 0.00898019083727815, 0.8741169185415351, -0.45340967963158263, -0.17251645348866704, 1.4298843907016405, -0.5548942136933099, 0.3267171451551591, -0.48015671815930244, -0.18354567858571158, 0.7618794051484872, -1.0074392767346179, 0.010031073963220078, 0.6631103163984708, -0.9826103252347183, -0.016778985481967244, 0.5140992139720515, -0.005766134114424647, 0.4792170639134645, -0.1766256151675269, 0.03440052889637581, 0.06541382161094761, -1.3329849031926362, -0.11894338264802669, 0.051246175341945865, -0.3550069279366197, -0.6788849128611311, 0.30465704285791967, -0.6547739642514612, 0.8145594127419982, 0.25959829439502147, 0.078947908755065, -0.05956422249006891, -0.16729397988019337, -0.6512988321348279, 0.3043434876451234, 0.13310177058408731, 0.15290687046769386, 0.1330550468102754, -0.04899801457006011, 0.5564535625307404, 0.4977682845841592, 0.44355782758252305, 0.16779948116791013, 0.94932569431944, 0.5444222515126723, 1.6185862433026723, -18.314653714093577, -9.64474176141041, 7.824408058386888, -2.1176036089953403, 12.083634770994943, 3.6761407619183033, -1.709136099049496, -1.175948033772375, -0.6225817732585758, 0.16549796352012672, -0.6565723497483568, 0.03865746797520126, 0.07456856540008187, -1.006621572222915, 1.0680572579604648, -1.330466438057836, 1.9466667342382618, 2.5565310923698608, 1.686413916997429, -0.5002143310187791, 1.4287543787164425, 1.7983513065672703, 2.299261372131199, 2.501145160493567, 1.0349758404004545, 1.120466800564228, 0.9820132065496319, 0.8346905921596752, 0.1591606775113457, 0.5692849706707653, 1.6952059619010347, 2.4393899817064044, 0.9492824162068662, -0.25118451717325796, 0.5354377451960303, 0.15310108746534798, 0.6002496023804346, -0.11354240085152668, 0.6046364783742201, -0.34822682034406716, 1.2279571316941742, 0.36709300379431975, 0.5125498286305875, 0.332124152013948, 1.1148985686620527, -0.5045228220088116, 0.7550600390679206, 0.5734667404546475, 0.2370134216656244, -0.5127388970157025, -0.06192651379688125, 0.2213586996395414, 0.7281804380538055, 0.0974200409406959, 1.4425430575298592, 0.61833640447903, 0.0016197569737127805, 0.8143042377302449, 1.670175389684781, -0.565089639520624, 1.59161142987751, -0.2583952392930286, -0.28041397245751987, 1.3135643132897952, 0.7380486588653792, 0.3445266301280277, 0.3849987375607372, 0.29422539728556907, 1.5695158380292895, -0.5020433466091714, -0.5677077139161952, -0.15486388664215062, -0.8665925860456327, -1.1604494587198466, 0.9351790004696042, 0.9956878668385456, -0.1256798596292261, 0.27004006375794726, 0.5760627450334662, -0.48955705050585463, -0.2812707967365487, 0.4707200778989345, -0.6551103856653091, -0.5648524822063427, 0.9458454899934018, -0.3708139717729757, 0.2365096725751677, 0.3674233517865274, -0.5968933925604998, -0.21667606981383075, -0.6547935105502452, 1.678758561651554, -0.4643134840843068, 0.2917829424353243, 0.7888137918694325, -1.4618525558120257, -0.452228544049304, 0.1622304217351638, 1.4904738338673118, -0.7319104502853949, 0.425260634330967, -0.185916861265908, -0.09376599032908718, -0.5198208246448657, -0.2610168173964096, 0.499744890850247, 0.6591285530832568, -0.5692352456639063, -0.7068987701529358, 0.6360210688893284, 1.8347757094495805, 0.02643129868455641, -1.0018249526146825, 0.1846802459516264, 0.04677832723938003, 0.2022440743923535, -0.0632258202123274, -1.2466715830846165, -0.16723576070235027, -0.4592841860226556, 0.1451568408365952, 0.8981143043909656, -0.42996488282309797, 0.451645462579169, 0.31263774404959166, 0.35836019131009794, -0.17468701208216453, 0.4953001133093473, -0.09970625197149295, -0.3827901522441087, 0.0996872412824222, 0.46369141314815376, -0.5640580999131324, 0.09715386630122665, 0.08792014400021368, 0.03279924009263135, 1.0923368616406768, 0.41178252808571086, 0.9534433236893195, 0.05135194974831417, -1.8969282490952886, 0.08948435925021975, 0.7009016221721234, 0.18754069540268825, -0.04366780835279681, -0.02243219852528312, -0.07220106353542576, -0.9327208470283788, 1.2043101368797644, 0.9937940451904974, -0.01690913092651369, -0.13173318340932638, -1.0306403607417194, 0.0770968908914928, -0.10891287452635205, 0.21881649526609614, -0.585329183492591, 0.48481609252991426, 0.12869150928675283, -0.4752215582145094, 0.0481277721411713, 0.14453644787969655, 0.6431915147137441, -0.21781314053039105, -0.23612748995388133, 0.04025363148367043, -0.4527985357380236, 0.07433462828325527, 0.1707515524005168, 0.6341575206885003, -1.4884567703482687, -0.32512644588680223, 0.011166532241945916, 0.5691929451443115, -0.6830154680984378, -1.1937037106713508, 1.438832184503436, -0.5266004065410089, -0.4546083546230996, 0.19583096216951262, 0.6957154717850172, 0.22383374290965866, 0.02856549580898738, -1.4730116613254673, -1.04583203140948, 0.3742116195422699, -0.3547697169984079, -0.12132695271380017, -0.4194398957207108, -0.7340282565899714, -0.4569477796823453, 1.0211209592735455, -1.02038095150223, 0.6702253334651793, 0.01444444000955993, -0.02493464361553348, 0.406563488312783, -0.1716830602360146, -0.005535332161443317, -0.2447402984011956, 0.7564456940655442, -0.9608668020628599, 1.182326645439967, -1.1557398623844692, 0.3382457732534566, 0.626765954280174, -0.05076908379709405, -1.2666013824894522, 1.0062071556823353, -1.9247574351096433, -0.18826421707032484, -0.2621040046298322, 0.37536265792196166, 1.0838398024613292, -0.22225562702941676, 0.3073128038082506, 0.6494748044008584, -0.16623836238872075, 0.4753882721597705, -1.042635397854418, -0.3411281338337019, 0.06828825648356768, 0.6689166380553886, 0.01917667568453532, -0.5638007172754528, 0.7711012837299708, -0.30467585004329756, -0.5712026361175009, -1.040185775301797, -0.35857373351086447, 0.805803778821711, 0.07451511162623227, -0.11409745229555493, -0.08453654437413398, 0.15544676435765692, -0.27217372480335755, 0.554723009749061, -1.1983174168373905, -0.377733901717195, 0.406086229512655, 0.14347306956250558, -0.30213146361542914, 0.1252696328081784, -0.05377030087120714, 0.779258597675079, -0.2704656267615064, -0.22151345376706144, 0.08104621351405097, -0.5455190377793923, 0.03354203974048021, -0.1759683478809078, 0.11949988121974628, -0.21146899121521123, -0.4488599625827762, 0.2078989021504081, -0.2268115177175784, 0.3655401705164385, -0.4288795766389427, 0.26847556391705707, -0.6200758303258558, -1.1511112660471965, -1.2378565213203603, 0.6628073945549376, 0.40263886874895893, 1.0085717892581678, -0.972303267438379, 0.5616493470347785, 0.09640156865958736, -0.5192458562167789, 0.5827740099969194, -0.18401173395419343, -0.26757003425841647, 0.7248585647160478, -0.08899022171355271, 0.6079250209903034, -0.19561688378721928, -0.6551618939593135, -0.782387860100674, 0.3594395368974523, 0.2568142116233557, 0.7236896396383689, 0.1676775637343464, 1.063641468202325, 0.3876582228291455, -0.413511267721635, 0.3277787514709959, -0.8508981144261721, 0.5474175626843618, -0.07381778641832043, 0.23504142853622012, 1.5979149335066636, 0.1334263334388452, 0.8881728075005212, -0.489699403940608, 0.09947880943288859, 0.235235875250718, 0.29525884043100153, 0.4736121777562368, 0.005276295247975133, 0.16950813991477373, -0.49793311470086415, 0.18480537952325976, 0.5765143825379764, 0.20617558830222724, 0.2313901075758714, 0.5865573070876604, 0.3993433718069968, -1.6898566796004202, 0.2715715152449543, 0.6539987030828135, -0.23328775972957133, 1.105399213711542, -0.7549399187856669, 0.36687977267185995, 0.8371310249954077, 0.02970588207274103, -0.08746608614737272, 0.4455340033222042, -1.5818313633047572, 1.4113054532826275, -0.1418283240256705, 0.6396616771093292, -1.103086246973867, 0.6067624495258894, 0.049163389838973684, -1.5415182319553378, -0.2554269976910732, 0.8510551988121519, -0.5971007186238492, 0.10658678573501187, 0.04874982762450607, -0.4134647580705329, -0.3376277628488387, -0.2788252266077969, 0.09178904725846196, -0.09369065533019627, -0.29915641246787056, 0.35393461074481825, -0.48586296063101675, 1.1639183702332614, -0.9470354473224302, 0.8563009954432032, 0.2400133957820948, -0.08712108617674458, -0.6898415503067771, -0.29839891058999535, 0.29037502187148967, 0.9164653509051607, -0.6280167475386741, -0.8759884829807456, -0.17679884199731072, 0.05572658020328191, 0.5249422630061631, -0.5973449380464277, 0.056150071171312724, 0.605476461717687, -0.15658296365777508, 0.08849768517190473, -0.5162447389863575, 0.22345814491881455, -0.14846790895063372, 0.6570785190918709, -0.03292236029877765, 0.1137834520183535, -0.5134074536631972, 0.14985326507809393, -0.8794384343084904, -0.35917785777237304, -0.6012907898163982, 0.28422245764727466, 0.6617490299939184, -0.4560970056986096, 0.271753439709239, 0.21187323342655967, -0.30109652053359287, 0.2274446680013772, 0.6338669019322003, -0.057354636042448746, -0.6179416334766727, 0.7004687543112968, 0.45875907129685517, 1.19042684543993, -1.7378679747582448, 0.1900613253695428, 0.7632435572211852, -0.7503942606028917, -0.03861108687618339, 0.5067916592798827, -0.04105649795535101, 0.2475072402263866, -0.22450119242813937, 0.727622857665737, 0.3972946151974073, -0.7890231276163451, -0.644266207843394, 0.5809413165759929, 0.44871396995912227, 0.09423443088776655, -0.029529808530868812, -0.7601218658950897]</Parameters>
			</FullConnection>
			<FullConnection class="pybrain.structure.connections.full.FullConnection" name="FullConnection-13">
				<inmod val="TanhLayer-7"/>
				<outmod val="TanhLayer-17"/>
				<Parameters>[-0.05768934224685303, -0.3156353295429076, 0.8063018514154578, 0.2741988639616015, 1.4920595409288893, -1.1598409010023258, 0.5492273144822519, -1.6576414524587186, -0.9495156128215057, -0.3907392022718328, -0.49676502466170563, 2.06357968828677, 0.5703025267279493, 1.3753146208756633, 2.020836949600178, 2.0715513874107447, -0.291674938278093, -0.5733810448454072, 1.2016980246344666, 0.06251190777640528, 1.5506258860839872, -1.6035775520149946, -0.4273695886677031, 1.6765336317590505, 0.3094772090437592, -0.279886118564532, -0.31740673144143156, 0.1169848936267919, -0.22054975345169944, -0.9249417057274537, -0.6635863043552589, -0.6825649305067389, 0.6780335286611311, 1.0042331210017577, 1.3000029561914381, 0.6316173504059404, -0.7336839491807428, -1.6757075146634837, 0.19698456862653455, 0.10225449487383323, 1.8441600687753057, 0.1699208428825875, -0.20367372089096658, 0.2337656480485798, -0.7559318311997961, -0.9385487369110664, 0.9089081689693702, -2.9903725610010796, 0.47508720588262054, 1.484124160598864, 0.8284612408283292, 0.8518440005658271, 0.7566620440865469, -1.3569604974764824, -0.49903838489430713, 0.4889210096861652, -0.9676982991999484, 0.11959000822868206, -1.9011446252783257, 0.46922447694450525, 0.5295539960554159, 1.19592980666906, 0.38826768428839253, 0.05014292196184734, 0.2243474475337905, -0.14723746097294013, -0.7985322545333444, 0.47252915265652784, 0.7043353929213332, 0.5422479416211473, -2.459764206538898, -0.27777933693396645, -0.9265722042418302, 0.83924225368801, -1.2369122691028778, 1.621281949690092, -1.5104130510646716, 0.5861382965512226, -1.7882144621273015, -1.1894583645913115, 0.5952521210745277, -0.8235382202268507, -0.15926756072697704, -1.50392372894292, -1.2034537264621352, 2.2404973148811473, 0.7912443958384439, -2.1762604623192656, 1.5235351056192135, -1.4023921547258957, -0.2097008430356077, -0.645547544171042, -1.3259789560007655, 1.6015242740749447, 0.9318894000200106, 1.1167480867433208, 0.7697517167823401, -1.0448578301805105, 0.13999973262694532, -0.5668735761283344]</Parameters>
			</FullConnection>
			<FullConnection class="pybrain.structure.connections.full.FullConnection" name="FullConnection-12">
				<inmod val="TanhLayer-17"/>
				<outmod val="TanhLayer-18"/>
				<Parameters>[0.6085038831802496, 1.9982973600872898, -0.363750493307547, -2.6048283286389, 1.4449173437594063, 0.49714155112082425, -1.8467768814406431, -0.5036499205331376, 0.334440003859049, 0.08920698316547467, 0.5562840445452426, 0.9000120759386173, 2.2897726891145167, -0.5183554069423443, 1.493354776264789, 1.1449560104316894, 2.4494188597050233, -1.4707177451540407, 1.0106427492833132, 0.3700596896904909, 0.5490981214997851, 0.6583149337689571, -0.43675341713716687, -0.5712937728645849, -0.2517450855437494, 1.2301802763776688, -1.8504940056535464, -2.01108473181299, -1.9238744376564376, 0.6031120835989622, -1.063550875320102, -0.30680157955413717, 0.18290899107493017, -0.3527982242879278, -0.5505259623687973, 0.781322498084036, 0.48040558250851884, 0.5526472298671583, 1.4793649773873099, -0.6610483284347732, -0.4532500132097635, 0.4980477061433804, 0.6034855382984646, -1.3048126354610718, 0.7500571946347167, 0.04077094481328238, -0.11968696475179033, -1.4573646281343855, 0.7165067320477896, -2.108542728271007, 0.4679847745904096, 1.9364970974091484, 2.188205057173688, -0.8081577406971815, -1.8059573027267297, -0.052919488519802126, -2.8388882778483886, -0.8484845557544767, -0.8134345039415425, -0.4347665575715009, 0.10401420271753603, -0.8164897161453534, 0.5194885442194067, 1.780060286938618, 0.6777854589001419, 0.24263292538727643, 0.3075105927012521, -0.10369211651328995, -0.12239727180226394, -0.18837159368915926, 0.5338998664338153, 1.138257743932869, 0.4005477633029391, 0.7526006345103138, -0.7927632696659913, -0.1971462091683108, 0.9680407917183047, -1.1615010569248942, 0.8694480962682157, -0.5264022528046677, -0.9440267696743099, -1.924000226831055, 0.25946623493860954, -1.2955966768224683, -0.9030615707555558, -0.5565958352839727, 0.9131923414821647, -0.490429390547945, 0.6728652445516237, 0.8345324562454789, 1.7573802287929654, 1.4455751856461434, 0.45394235649985887, 0.5508177644245049, -0.2807280330349885, -0.6673319138348236, -1.0246421737601479, 0.6119340029977117, 1.6527372034776615, -0.8415809137833915]</Parameters>
			</FullConnection>
			<FullConnection class="pybrain.structure.connections.full.FullConnection" name="FullConnection-10">
				<inmod val="TanhLayer-18"/>
				<outmod val="TanhLayer-19"/>
				<Parameters>[-1.1041046991190442, 2.843898041061169, -0.2256409066204826, -0.6108095065579994, -0.33626903532639674, 1.7869644137820553, 0.6099748819919545, 0.33303982035383095, 2.389640281459619, 1.3190154143513162, 0.8675961828629738, -0.3634795222247223, -0.15759626271867755, 1.070134514979709, -1.0430981189821797, -1.1120423815314224, 0.5933178947332951, 0.2985046754931624, -0.14609882730443466, -0.13513822672602976, -0.18496900478444095, -0.9112668420519797, 0.6563722392949949, 0.938604477122318, -0.9158871292962866, -0.5394783004038138, -0.6621587591275423, -1.6001356216221863, -0.224997874339579, 0.32310887577876674, 0.6757037081183063, -0.9284434137733928, 0.3778635618771511, 0.1401164939157567, 0.7942366521006214, 1.0372745013964308, -0.013977656173557743, -1.5601329679607607, -0.1136754374457269, -1.100083678031301, -1.967094890090657, 0.49624928559371884, -0.8247091169891436, 0.5279378803083807, -0.49878247058879593, -0.0892604013189911, -0.9115792419583669, 0.5378076564220979, 0.7940137109910739, -0.16403334035785555, 0.8293938430088307, 0.008703513995842994, -0.2932344625072095, 1.531035132617402, -0.7454335784039362, 0.5508977510165745, 0.677545111221261, 1.3315527070759356, -0.12936494425512726, 2.0053333395503223, -0.6286390613143988, -2.0136758411926072, 0.5926088719741147, -1.3287926294924177, 0.3125993906768241, -1.9128788579416698, -0.31896458947576206, -0.796719503747144, 0.19663924730014468, 0.7122990389640131, -1.910020574021833, -1.3076070140146054, -0.6099181574727696, -0.9242510217930012, -1.2812648794661672, -0.0807379131663806, 0.1186734752662698, 2.2044531682257342, 0.3706079201885254, -0.9758862239567092, -0.047369341885564076, -1.418438844025996, 0.9846569891071667, 0.639713270004692, -0.8759854479926003, -0.2308235235766127, -0.9541327397213596, 0.9417459777144643, -0.28852581786300463, 0.12531472619909115, 0.06827191790097208, -1.0177120071724766, 0.2701592299408656, -0.8533431405115011, 0.03338213170958114, -0.34940382045346746, 0.5736696622178987, -1.0902776526269993, -1.9057860354593834, 0.8341904121048848]</Parameters>
			</FullConnection>
			<FullConnection class="pybrain.structure.connections.full.FullConnection" name="FullConnection-9">
				<inmod val="TanhLayer-19"/>
				<outmod val="TanhLayer-20"/>
				<Parameters>[0.5944146536222478, 1.7118810133317879, -2.4438187285368596, -0.18601891853569763, 0.20310033724684545, 1.3162881677436225, -1.1157901810607531, -0.6868639500008589, -0.16405415560173567, -1.0684663486416204, -0.9739838872515374, 5.776261809252043, 0.06666918090649214, -4.866075121001284, -0.9386451448226023, 0.6911836955088873, -1.683022217575947, 0.6182051119378532, -2.4539115911587874, -2.3048726790881346, 1.0733461061243064, -4.293745148622243, 0.5740124341174874, -0.4137035155695078, -1.5716650256776343, -0.054079218278543395, -3.145807125437958, -0.7755970134309901, 3.0159459770037427, 0.9644723856422079, -0.16507417025214513, -2.0384655869861215, -0.28303061067033963, 0.05062956594518372, -0.3077005573968301, -2.2759981456589564, -0.8714142855303103, 0.15636696085378152, 1.5917390857251492, -0.2245062370797394, 1.7400169356330004, 10.401261451405167, 0.43869672761819106, -1.028231444552705, -1.1457740795076452, 6.4048088515996895, 0.24004456264652155, -0.41431776156232036, -4.344363162995673, 1.5902638472243558, -0.3031718986874819, -3.2170058483264214, -0.5827847299184787, -0.9124309873066437, 0.3939404617106598, -0.7636804865765298, -0.364223939354182, -0.4461187830899926, -0.26636393226993693, 5.006825477725937, -0.296442873291777, -0.045830270387095404, -0.02917892158330781, 2.7470197788956368, -1.4335112257367257, 0.22814399701964522, -0.35840695869259553, 5.88333254556126, 0.527441123095109, -0.0005693509539905706, -1.8681956444322387, 0.5693571764639961, -0.5769384464239923, 0.2698384197996769, -0.9859524375894279, -1.5314772547268387, -1.7648395602749956, -0.1343869879518992, -3.0062660771356327, -0.9151774845782549, 5.36034449720717, -2.326712350703997, 2.5364812179361884, 1.1768657371831004, -2.078121348925167, -3.3249578518974694, 0.7584276386130638, -0.08988899054308949, -4.505561844285986, 1.7821930770532561, -0.09952071683155675, 0.9019750882749239, -0.24037162871158071, 0.9477783953260654, 3.7189098977609167, -2.061708622222969, -0.2915758198134207, 0.645593701898406, -0.7011162887395951, -0.5585956804144645]</Parameters>
			</FullConnection>
			<FullConnection class="pybrain.structure.connections.full.FullConnection" name="FullConnection-11">
				<inmod val="TanhLayer-20"/>
				<outmod val="SoftmaxLayer-16"/>
				<Parameters>[-4.096134174458128, 2.8096710617354455, -0.6068392425293202, -4.663382556209546, -1.56959669201595, -0.16410252056346758, 1.334332620390348, 1.0948096041023614, -0.08613309775423096, 0.790458838949126, 0.055682746970850606, -0.4524276079466407, 1.7779782188450752, 2.707307703418495, 3.85837917404072, 0.14668237518468177, 0.3755027066476504, 1.187709175831369, 1.5907995986504004, 0.050117471440735445, 0.8274747234065152, -2.712990209331687, -0.8893683066060959, -4.023149284565926, 1.793107451666346, 0.5813647269638396, 0.5087374786203224, 1.9127011725263332, 0.17885938335510265, -2.007267469951435, -0.5008429275796147, -0.3435006901610473, -0.6019759318444756, 2.873461638470828, 1.9637723844207613, -1.8403935693895224, 0.5162673070137496, 1.3765730115152848, 0.296176755762456, 1.0814809295280994, 1.1470963673356043, 1.5934811959862563, -0.6326452659174976, 1.0453596908102596, -1.729615594292379, -1.2284365354454225, 0.6835713106155411, -4.021922907103855, -0.9098299233906328, -1.318348743619939, 0.9437445495027109, -2.0855906092427543, 0.4568997277407426, 2.7483522695973406, -1.6074416604489579, -0.36275820809846776, -1.154120406711756, 1.3192807273075773, -0.7315162684625471, -2.903749815446102, 1.04902419834533, 1.4317938047594043, 0.9711263239029443, -0.9171877231936447, 0.5795982390169806, 1.3410825217400109, -2.3473125349917026, -1.6779018172251188, -0.3776101369631036, 1.1963682064994585, 0.49827141115877377, -1.5297055438989806, 0.7173979879270885, 4.389768698956509, -0.3011630595386401, -0.22919777204617783, 0.8194642202409721, 1.0126433724575166, -0.4752038622248703, 1.3250334975561733, 1.8691268413890385, 2.1669821060353427, -0.42694425879473624, -3.9914956255815803, -2.627185930056389, -3.2691229948942437, -0.8009202041332001, 0.2679253552311285, 0.5426026660735377, 1.7751478480644618, 0.9484185068147248, -1.2705858539274173, -1.5239158092991552, 2.276709586739259, 0.9013367057915759, 0.7238265529698686, 0.5593288319725426, 1.3005243802314117, -0.7662899856072101, 1.3684518758404938]</Parameters>
			</FullConnection>
		</Connections>
	</Network>
</PyBrain>
