<?xml version="1.0" ?>
<PyBrain>
	<Network class="pybrain.structure.networks.feedforward.FeedForwardNetwork" name="FeedForwardNetwork-15">
		<name val="'FeedForwardNetwork-15'"/>
		<Modules>
			<LinearLayer class="pybrain.structure.modules.linearlayer.LinearLayer" inmodule="True" name="LinearLayer-8">
				<dim val="400"/>
			</LinearLayer>
			<SoftmaxLayer class="pybrain.structure.modules.softmax.SoftmaxLayer" name="SoftmaxLayer-16" outmodule="True">
				<dim val="10"/>
			</SoftmaxLayer>
			<TanhLayer class="pybrain.structure.modules.tanhlayer.TanhLayer" name="TanhLayer-7">
				<dim val="10"/>
			</TanhLayer>
			<TanhLayer class="pybrain.structure.modules.tanhlayer.TanhLayer" name="TanhLayer-17">
				<dim val="10"/>
			</TanhLayer>
			<TanhLayer class="pybrain.structure.modules.tanhlayer.TanhLayer" name="TanhLayer-18">
				<dim val="10"/>
			</TanhLayer>
			<TanhLayer class="pybrain.structure.modules.tanhlayer.TanhLayer" name="TanhLayer-19">
				<dim val="10"/>
			</TanhLayer>
			<TanhLayer class="pybrain.structure.modules.tanhlayer.TanhLayer" name="TanhLayer-20">
				<dim val="10"/>
			</TanhLayer>
		</Modules>
		<Connections>
			<FullConnection class="pybrain.structure.connections.full.FullConnection" name="FullConnection-14">
				<inmod val="LinearLayer-8"/>
				<outmod val="TanhLayer-19"/>
				<Parameters>[10.070604021826282, 1.8841843232918754, -1.4963139854903318, 1.3446868406407126, -0.06550317070871473, -0.1108934016102793, 0.6935962498798326, 0.5159608939527882, -0.9027790492357891, -2.1383762093227725, -3.8072074970322225, -3.364196723092092, -4.8599349775258105, -3.0178266083960787, -5.081415945131388, -1.6761882122409129, -2.0189231282460796, -1.1059095977781788, 1.395048156191883, 2.655335308009403, 0.30616514420001717, -1.3299169345321795, -0.8031232862722869, -0.47879221440240105, -0.2523330205773677, 0.5902966421080144, 0.3605276386042944, 0.14751209301980076, 0.9940094527306517, 1.225238907210259, 0.5899637987096066, 0.6419947456993493, 1.3443884322316617, 2.4309257562991546, 3.27779723011182, 2.1543182783811377, 1.4632810495632522, -0.44414403877885406, -2.0923443059925435, 0.8695894767685407, 0.5784720417538449, 1.0164936416762986, 0.6012011020250118, 1.0647090100540841, 0.8561707811603824, -0.7449710933638016, 0.6200620074439496, -0.2850842095557274, -1.199499771583869, 0.6274139739509808, 0.5230305470104516, 0.24764622444920012, -0.30023505991309685, 1.3963319953984168, -0.7637680681428065, 0.6600563191862301, -0.5974767813685254, 0.5180094264063448, -0.6594763669750606, 0.27898803827579516, -0.3964132696869661, 0.32666248513002183, 0.9644067667785444, 0.7683242218960663, -1.033479044842045, -0.2780211110676165, -1.3445356955128394, -1.5478790473519402, -2.8221436410641543, 0.6951116994135227, 1.1023617549175528, -2.058452726987208, 0.9104856233119308, -0.2862702305203564, -3.2761804291321504, -3.4564190997360122, -3.6907247458065435, -3.1152056403299353, -2.1242954230101065, -0.6563494858891866, -0.48489206430456966, 0.0007945984566080009, 0.22304910598204675, -0.1690618724618605, -0.6865966525451015, 0.09059233570733582, 0.7159980393780303, 0.009332528573572342, 1.0371470923541277, -1.170109261839941, 0.534914698396027, -1.47103232066535, 0.2834937197815105, -0.2309497037753692, 0.5641141106100073, -0.23739078848680298, -0.038671335216507285, -0.01167757105576308, -1.0389803991541675, -0.7133979589156773, 0.09236832935682839, 1.1735148209318622, 0.4923964340792365, -0.4857159122290684, 0.3785784588792798, -0.6672715133454002, 1.5675305165975755, 0.2878612686656694, 0.06052558859184816, -0.03673321666332768, -0.6372211781410739, -0.9337161966684435, 1.08222159651709, -0.251767840411871, 1.2143783900882683, -0.9395910644108747, 1.6713148655813785, 0.6741030990777088, 1.2706591852348297, -1.2760792688994347, 0.9184062182964705, 0.19262430293706004, 0.09927565225104101, 0.6921561266166124, -1.6443526493021212, 0.17166611907141524, -0.4111297650949408, -0.3731608635550023, 0.3777770847966202, -0.2777953477223502, 0.2589888262157263, 0.10299224621527776, 0.05190750922280014, -0.26519527217051175, 0.0493654081028204, 0.15147074698333632, -0.19018615946852074, -1.2412882576658868, -0.852950959259672, -0.5403869945363894, 1.45331006610606, -0.678893690490157, 0.5902007368752925, -0.5510788334983805, -0.24103173700783598, -0.15293934223735178, 0.9299059661246512, -0.9903033331400868, -1.9743090524810192, -1.4251591310085316, 0.613231466662793, -0.49466141822348814, -0.26427972664938154, -0.48446850388603424, -0.9589897562853371, -0.1385855218838986, -1.3613491920344714, 0.9521392667499591, -0.6212553787530688, -0.25472061360491954, -0.6164301363711887, -0.707203934368661, 0.04437891910154631, 0.05393873904834891, -1.2935162611529298, -0.08605391037371381, -1.0307455182856575, -0.8905133720053969, 0.5925557349635284, -0.7476966981464145, -1.9676423886875183, 1.6335459036995055, -0.6149651014452807, -0.5466522551242787, -0.6495762108391336, -2.123825100259875, 1.7854277081716865, -0.4746331607764249, -1.8739136844409319, -0.03892860644596559, -1.2673586081984922, -1.1976542885771266, -1.04598489019592, -0.2038291342277756, 0.20952968898941526, -0.6050109819021694, 0.7994168922679511, 0.931490589524224, -0.028537897035934533, 0.41017575290923436, -0.875729983377251, 0.3655100039947895, -1.2845469148871884, 0.6087884377016771, -0.6235125162531858, 1.4088719500444504, 0.48656563187873164, -0.754344284186041, 1.0535204797517712, 1.3958253364219402, 0.47347565612016035, -0.6274452431372778, -0.16973336132094988, 1.5253279116905019, 0.40673664597632514, -0.19062450590798832, 0.32076576119405414, 1.6291950319310171, 2.9605582745517673, -1.142930625327208, 0.33698365938934405, 1.2234606129417438, 0.09429168161118454, 0.6665610937890004, -1.349934826105568, 1.043224207433118, -0.557059820345509, 1.7932715098726182, 2.616368723783785, -1.9473841353252541, 2.845488981918712, -0.5794533611705825, -0.4766816383943934, -0.18612202955439616, 2.0816471279723587, 0.5998068975030747, 1.5668114590829707, 0.41443568776924405, 1.1413895678578676, -0.4395253076022787, 0.7983220119433103, 0.4069852526796354, 0.1842320701217556, -0.2794684044747179, -1.9161535501405826, 2.0911860295567744, -1.0398286250343554, 0.6057150945007401, -0.9420484384325568, -1.1957518716472135, 0.17316910607742964, -0.5799896403076, 1.0288377159299746, -0.649957547216207, 0.017011456305259028, -0.9159432586664086, 0.7224231349511884, 0.9156852175301181, 0.3128277767128047, -0.48178970732276644, 0.9520590354234557, -1.1357527062869353, 1.9982178105014605, -1.069073557253987, -0.9045968412907842, -0.624894641173784, 0.2840088365164585, -0.9651272480460422, 0.8006619816530653, 2.5913176380730145, -0.11659001460759283, 0.013177627422299786, -0.22682728658759485, 1.8325423524266427, -0.7819577337446683, -0.7251321618251118, 0.04604530510832301, -0.6101623654067201, 1.232995693652383, 0.27609479053220054, -1.2600947966955707, 1.4677044123133909, -0.7430974146076984, -0.3618868537610205, -0.2718672362527976, -0.10224768914725728, 1.191122040297586, 1.2459440983705112, 0.08154072613671763, -0.49253683331690096, -1.2886612654449652, -1.242996471739165, 0.8163521668018673, 1.3548882650802423, -0.7871764231070597, 0.12909062427840295, -1.1022769794791338, -0.35406311318321043, 1.4086269609527249, -0.4102841063602657, -0.5051509372594319, -0.11101620183348657, 0.3467291789415111, 0.5133995828878225, -0.47477197865946896, -0.5404811148809144, 0.03156814082901687, 1.081176747358176, -1.4943872783000371, 0.7370669531389459, 0.46227385276864846, -0.6934133336397194, -0.5195640021198318, 0.5694386833056262, -0.49166446577726564, -0.6859192704855217, 0.27120864287318863, 0.9670095088686698, -1.7058827279234827, 0.7030633259839373, 0.49077604422609056, -0.9658413090168853, 0.3940211343759756, -0.6298286435247278, -0.5097805367895214, -0.5980322506027242, 0.7746367117529922, 0.09522647022686974, -0.5916791720073737, 0.006475395327424971, 0.47900482395211785, -0.09569863638670581, -0.11920204896702921, -0.32800616086371326, 0.7098790254416759, -0.11307544070583303, 1.3665208700151645, -0.7087992724012584, 0.5225306868543398, -0.06561061431974458, 0.20346388029832, -0.0534216700603858, 0.10460465982971148, -0.12498013260751538, 0.5917624879911277, 0.17725773234565842, -0.02597051831373485, -0.01835672787267879, -0.9278187070181838, -0.18477319261459466, 0.3752029375571522, -0.46377730503036074, -0.42753711118054954, 0.3318183435694818, -0.26659815932315756, 0.973789503152085, -0.3415841284436736, 0.11198367086326848, 0.3347322087455443, 0.07013602243059679, -0.44235874364019184, 0.30082515306035357, 0.1497105347878775, -0.8043522714415873, 0.3683032046430595, 0.11146018715919388, -0.012440999749449825, -1.7204307018390228, 1.5363439178164928, -0.16102527168111694, -0.3181546603876557, 1.1893429242341274, -0.8529081427728495, -0.5622885323236925, 0.4576756689377908, 0.24914139661927842, 0.09897749012919113, 1.0980468823860532, -0.35444270398080524, -0.08096502477834602, -0.03082535231645919, 0.2687242996591364, 0.4491650001094727, 0.1567881399211531, 0.056388210626151236, 0.4783099275907893, 0.47807496801193633, -0.8403069374450312, 0.604145327621194, 0.37310673634675934, 0.9179947914984393, -0.09082246916853297, 1.2566349569737605, -1.5159706828133073, -0.06406532762298243, -0.7649774521021069, 0.9734496240448611, 0.9073871050264687, 0.5372087623962624, 0.5567628893480789, -0.31505825003184107, 0.27484336497603445, -0.3594530739999997, 0.4525128126085818, -0.13947378804443836, 1.0857295264498041, -0.2950913728132922, 0.7109048501725743, 0.23364335400939693, 1.3751603886886594, 3.347880978222321, -1.2137880594594013, -1.980109322513563, -1.182986964866414, -1.7501399995170448, 4.409042750457546, 4.961480104244121, 0.18059265493054324, 2.5664477085207245, 3.1185077347682535, 1.555525500867713, 2.345167117665383, 0.8304450788416611, 4.20295878081748, 2.8474425990590784, 2.4096917852446933, -1.8260863256943383, 1.6796261324020003, 3.0696886911124794, 1.3353609982783314, 2.0864988231440407, 1.7598490046297495, 2.6871437001943215, 0.7109279844416059, 1.694576229777572, 1.9382137724617499, 2.0114283837087052, -0.054475927552919724, 1.400044230948134, 3.969518097432827, 1.224909671385722, -0.6127448368273248, 1.690085389620659, 2.6500334954494105, 1.1144656724146538, -1.0605661809195992, 0.902449791337668, 0.2437904193075987, -0.5931946422624564, 0.34215600838376264, 1.4152270326527143, 0.5970335394164814, 0.5602454820452878, -0.45212508618804387, 2.2240144480392274, -0.5645807073917299, 0.08244160444829336, 1.1333541494538033, 0.8023515093956411, -1.2266157279141727, -0.1491639718731507, -0.9491296648493537, 0.9310458858453567, 0.7631359102456478, 0.4800299630761804, -0.5069740151461513, 2.1107886402855294, 2.09007840388358, 0.9304957420356651, -1.6373395774202657, 2.767297482963473, -0.5659620901225956, -1.170994497648618, 0.7216071597467892, 3.0301466348046997, 0.47670501167122853, 1.7692170960813096, 1.133897079056329, -1.26975767050029, -1.7312134913024833, 1.2163986503318536, 1.0254906954536773, 2.0238696764882103, 0.5088579438245565, -0.4362029031715243, 1.3357849198771745, 0.7295332977651071, 1.1715946402399908, -0.7080386772788639, -1.0485081210606804, 0.8959651805472408, 0.11591213632820839, -1.2468239752835493, -1.190815703045394, 1.2519781217683241, -0.5406076680704491, 0.5437081003380698, 0.9803155289223876, 0.5494747352420091, 1.052105835765706, -1.9945286763330992, 1.218838597976825, -0.6578199746169235, 1.6063942057501055, -1.0664123692221767, 1.000874280364955, -0.6872790358538119, -0.5513163372089993, 0.6250768793544514, -1.9139406855141787, 1.6678991657743465, -1.440756244565332, 3.233953214825073, 0.4307642494712023, -0.3503192067544025, -0.8663725689262134, -0.5946023902013108, 0.0021208796765152813, 0.764747140497816, 1.651644833506147, -1.0508755837207753, -0.13525455240990805, -0.5798673625008691, -1.6048137210078943, 1.1457902548177865, -0.33674774920279377, 3.8193163497018388, 0.7479400234029957, 0.4229362274828138, -0.918647769240355, 0.22702211800798305, -1.6524300655959026, 1.1179048379334187, 1.6629722370006557, -0.8949876613800752, -2.2909807613770994, 0.5034471732786507, 1.3842594744325827, -0.4667908157358213, 0.7775081626938427, -0.6222376766139274, 1.0493837735823301, -1.5187847632943863, 0.6156354620992309, -1.4424866346754266, 0.6128821857552544, -0.3394718265478813, -0.2808794299461489, -0.14278670941716493, -0.43227247441963107, 0.24440953029839627, -0.45994375295259765, 0.36561938516903664, 0.8677534760912183, -1.2310455960402877, 0.07226937912664191, 1.1379960028431535, -1.071370909104125, -1.220912812101748, -0.25618019369934064, 0.2900218498583559, -0.8417008496647902, 1.2215198193141286, 0.3272759797648135, -1.2190336883533268, -0.011226354062306586, -0.40609449707571815, 1.8147302146557196, -0.138646469830945, -1.495253366032061, -1.8582029108900233, 0.6586937788381758, -0.14262193719265917, 0.8171173386119468, -0.6401387504988624, 0.7740274514178885, -0.9175605223951665, -0.02166879728036838, 0.9192272914869406, -1.0372038110347666, 2.379426282330759, 0.7683604591204476, 3.7791601308211757, 0.5206389011800046, 0.8858833424828475, 1.7761008166703374, 0.36192223682032393, 0.560248780457938, 1.0318855017285191, 1.3798418001301516, -2.3301868265401353, -1.4264449982031764, -1.0480798107205986, 0.5896727390841746, 3.348508176218719, 0.778423742761488, 4.226176473853382, 1.615819790017895, -0.011328749814344445, -1.2940081779277184, 0.5320910712910512, 0.9655555439115099, 0.19716868431514717, 4.2078058601646395, 4.622570783942313, 2.3199741557063733, -1.1726292141890244, 0.9380041156868703, 1.0976676253109678, -1.918213698349867, 0.16421513958554781, 0.17814430219153246, 0.5784131828410766, 2.1076720327432743, -1.9323205954184026, 1.5352451799564635, -0.6709476497690886, 2.503511511570108, 2.0222004035847037, 0.7509303257906484, 1.0837637692518898, -0.017916604017588305, 1.8894148045086177, -1.5920605973958633, -1.290242496663358, -0.9499930101019723, 2.405908040235645, 0.547927148920342, 0.4959639782080852, 1.532009242382376, -0.8008274360731965, 1.2217622723219688, -0.6177857963453433, -0.638806862856386, -0.37782525675382944, 0.9130288170210041, 1.315216547588071, 1.4920980287935075, -0.19781348390060421, 1.6926936466221933, 0.8492032636610435, -0.1850149874275871, -0.24309268919406588, -0.8089337705387574, 1.2473107189936918, -0.14311026487512826, 0.8897175012166747, 0.19215478620089743, -2.9991981101730425, -0.2535404725949919, -0.3333444165124956, -1.4947462508299636, -0.1539937343392687, -1.1840176215984812, 1.2375215476688164, 0.9536490587399714, 0.7078751443262672, -2.241702396776712, 1.1212903980504567, -0.16259730093058364, 0.7806395992262568, 0.5064855275061185, -1.1302422562645664, 1.9185439318320294, -0.07002424261314313, -0.5744262087270884, -1.1416209053981845, 2.8972265938927477, -0.7304507765994716, -0.8952789351735511, 1.1257953133785894, 0.2403970135097032, -2.5576505113569383, -0.48227836537693514, 0.13907553470554307, -1.2999262116048018, 0.9062204683365269, -0.05430295280239452, -1.5824024732930375, -0.22107592571386767, -0.760184378134608, 0.04537399524045336, 0.013605387726305462, -0.09468704032344931, 0.3923515441692953, 1.2316687165461138, -1.8656861865912626, -0.6071336835035896, -1.2474818955559044, 0.5721881710829065, 0.289258077914618, 0.34610700453925825, -1.1508113719153716, 0.2842122715719784, 0.8811538930811832, -1.6088584901700693, -0.31461777106756095, 0.2332214215734741, 2.736633874916545, 1.9445382929029886, -1.105510938467448, -0.2242290383453136, -1.0537632886590176, -2.0199795538600216, 0.1062685103801123, -0.2551256718556402, 0.1647707220667189, 1.5215712187929855, -0.7020083972490604, 0.6825227422317498, 0.04300650204794449, 1.5023693912316598, 0.16376721537707062, -1.7643074124349276, 0.6883887174742739, 0.5485281749341654, -1.1255911146080748, 2.0218572953791347, -0.8470652034204941, 1.136389691740278, -0.726864727316879, 1.7519817130786324, -1.0668252225341843, 2.2574566526572535, -1.046139422069058, -0.13939706396133805, 0.8509910156094382, 0.03641035767160962, -1.7943749796248207, 0.6073831022466908, -0.03192517579464933, 1.4973053466585158, 1.0386073050332427, 0.5268656588317503, 0.5673503292326999, -0.5942481709201438, 0.5651502548974041, 0.8569984903079857, 1.2330930203509185, -0.3335719800323741, -0.7640193826607609, 1.2465265512941641, -0.17890355118557194, -1.7297686143263127, -0.12390172948518088, 0.979518082960743, -0.2959045631713371, -0.5718284141471184, -0.8032819422019898, 2.650914701941467, -1.9924735465776937, -0.4167418406664249, 1.6106927722495274, -0.7792922043655636, -0.8638555854176304, 0.16538039396011628, 0.041388635673063986, 3.1755946506961346, -0.6116655299915984, 0.4602235527444931, -1.2538992577653, 0.011836773926708784, -0.5793948041383776, -0.2878973570787979, 1.6410368907094448, -0.09631858588265588, -0.85199787559987, -1.688708807163213, 2.62972324204547, -1.1934413508803137, 1.4585942645207788, 0.5277492913118914, 1.9362541335859387, -0.35594556489723306, 0.8201428753152437, 0.3597290453325814, 0.22330994612132948, -1.607004099322352, -0.9034855671002173, 0.03185627332325124, 0.4229824695575649, 0.8034525997575503, 0.1735017107269373, -0.5748302606164565, 0.143444393912657, -0.028016395769423597, -0.5236130384685149, 0.8224768234350103, -1.2264662844588703, -1.3719179259331986, 1.6545070948765797, 0.29733631311265857, -1.6645083628273498, 0.7474776942307653, -0.5411033650249745, 0.2070164488485163, 0.42907812807275575, -1.9263436219719223, -1.3037376382282688, 0.7571152917500367, 0.757009767860175, -0.8397445328800773, 1.3533860928421515, -0.5528550760251703, -1.6727477131108857, 2.4218032842018338, 0.588542072458448, 0.9780019534088343, -0.1394459497585738, -0.6342680556151005, 5.841530625716876, 1.4638196982950484, -6.443436786813574, -3.69543870377854, 0.9984910401507715, 0.24625817097425265, -1.3094896519148251, -0.654031161706755, 1.7159065188759515, 1.4854841191868995, 4.21363921255711, 1.6741404283897467, 0.241709992037021, -1.5426147745037333, -4.105392954468171, -3.2377796906576997, 1.8169403867222227, 1.3051040685042137, -1.529885081157716, -2.527774516746699, -0.619180298731894, -0.04944421723230086, -1.638196785184258, -1.533640276453148, -1.1832067941223192, -2.4408157620247897, -2.7001777845516544, -0.7874109316502181, -2.218972374829852, -1.9800629538719325, -1.8199281243489065, 0.5015198390763463, -0.13889372072269904, -0.14062322669793764, -1.275518541821026, -1.4789795425663799, -2.0420414104346625, -0.908225935099105, 1.199122103345158, 1.2303187507722884, 1.4503790282382563, 1.1690363741185723, 0.3408551526107441, 0.5730753821528701, -1.7320108716672014, -0.10244271213717826, -0.006403370356826535, 2.1501269473854725, -0.24629009299781848, -1.1948279552861336, -1.0193516150244768, -0.7366461723985439, 0.6661640612512397, -0.35430992970256553, -0.1980211828755647, 0.003474151929373893, 0.5421536403628581, 1.462872756564876, 0.20189483551318413, 0.9871932155556891, 1.478929688363628, 0.7447596143291046, 0.5215922332310088, 0.5268727347214941, 0.8924292001662056, 1.4558904345898596, -0.42166248360043107, 1.0782233599550806, 2.176227359845955, 1.3266971274602073, -0.4172665050321363, 0.5497143664008222, -2.3883641582264628, -2.0094809573827614, 2.0793128045690277, -1.5416436862227263, -1.4217582307569188, 1.3072321415910428, 1.001429636158552, 0.15822699631666728, -1.3481148293588865, -0.003858440686970407, 1.1966214216415578, 0.5214308643188424, 0.04955031470638378, -0.37287192047561424, 0.6547604667055452, 0.08266811226824462, -0.7658528455128562, -0.48841447041942215, 0.22139285616333684, 0.4490935076176503, 0.5618815955728901, -0.7519753228498268, -0.4558177615106447, 2.0642892352769935, -1.1494229837948928, -0.2917286705793651, 2.824569766948834, 0.02300267556642039, -0.5338412169712944, 0.045424412361808955, -0.07369817583207605, -1.0669424387859712, 1.0512428899660824, 0.034828878497203015, -0.8998990561566076, -0.8981604535944331, -0.14236676040544383, 2.749899931534649, 1.9151327541105583, 0.7034692305214357, 0.08700643762266955, -0.5587968036681349, -1.4558258612921766, 0.516864533081856, 0.11399376269372269, 0.2757253524990984, -0.03347775560822896, 1.9175252230097382, -0.5895156391453664, -0.7453684357610901, -0.4080318790215039, 0.18288131886417855, -0.4350854458507878, 0.7972214468202116, 0.5376002400746263, -0.2101336775274076, -0.1739248113882009, -0.816462915705333, 1.2532475077895155, -0.2687928172807461, 0.07397541792241237, -0.42381018919199137, -0.38011043530955163, 0.611868137465043, -0.8756272319724387, 0.32171519139584, 1.0388467326591913, -0.3404806166171793, -1.3021491750328775, 0.2955849134376598, -0.6358412419162798, 0.3595110081251788, 1.936609219972522, -0.7753980551880234, -0.4891296776026442, 0.6403816336145143, -0.45732448137461534, 0.5434406327985012, -0.8389036433775453, 0.020565515207253117, 0.2344256602211949, -0.9083383269490977, 1.2706933822808506, -1.853510194970152, 1.2579634907952135, -0.6982546120166515, -1.1788218149930079, 0.5577005684888732, 0.19651275258778364, 0.7475463461217196, 0.171839213896736, -1.4275935762366647, 1.306801615575184, -1.959086970201775, 0.6492195553579311, 1.1126431823075211, -1.004865476061422, 0.5348397269632058, -0.9357130652506228, -1.379525369153733, -1.8210419832859832, -2.2007555564463614, -1.0134839311639854, -1.8456800792217543, -0.5932911412687348, 1.2284191277130871, 0.949193786404005, -2.1397132257272116, 3.5072974432422335, -1.8176085039508403, -0.4479111963969211, -1.0921005867290838, -2.025021419619298, -3.6536934522221878, 0.7408059005163774, -1.993966041792698, 0.5343828131790499, -2.816334675210333, -3.0243483308908328, -1.7395530721586911, -0.44619144267040023, 1.7848321026784395, 3.1074051674820615, -0.9353855817917468, -1.831744487905723, -2.868153458415474, -2.7726976066899143, -0.9484430720810744, 1.176515204861959, 2.0810762619559724, -0.6732447336016021, -1.8451647024823463, -0.728625334914972, 0.8856027004222602, 2.6637616637858335, -0.6552700375390939, -2.1463495530581014, 1.037516065352341, -0.10580714237419026, -1.4040074066301431, 1.3897854227755202, 0.22446655359818604, 2.1048751474576974, -2.087175533668014, 0.43619002999524, 1.9984166688376563, 0.6643873937744257, -1.1677378472029225, 0.8696410619104817, 1.1124433198068289, 1.6376412094831758, -0.5849813045205422, -1.8057487801270533, -2.6708620110327868, -1.3134631610801535, -1.229668712822783, 0.540359412857474, 2.5575900963279556, -0.8657208645966956, 0.0568045597958678, 0.9924269325028491, 0.08846960900122569, 2.9732351051400565, 0.9443034824267574, 1.6785784271127335, 1.379680695009449, -0.4131564163510626, 1.9304969601729605, 1.3049002169989548, -1.2188312289343826, 1.8156821094583597, -0.9590506978273954, 1.5262972681825961, 0.3381393690810294, -0.8815433986074158, 0.21383848287247942, 0.2009778850112905, 0.46657675362349704, -1.2644478524978708, 0.6530521739067551, 1.0377265662606674, 0.462880455536242, -0.1922331023535022, -0.11044467032509883, 0.7383978282516542, 1.0049302288764388, 0.16036560994432697, -1.5830939204872891, 0.34165727612557134, 0.2355756911937225, 1.2278238977459932, -1.8873718896227127, -0.7031372322204013, 2.4895128032973, 1.0385787123966792, -0.20238154687442433, -0.4414388718225483, -0.08352888386129018, 0.8154247226417872, -1.015438743172287, 1.239090789925308, -1.3383289864834105, 1.324486744661348, -1.0504192270568429, -0.31472723935305313, -0.5731731529387183, 0.33708350954250943, -1.6456053008174947, 2.601351692594885, -0.4568634131456692, 1.2705416938866543, -0.3868643029540279, 0.20099462309697172, 1.005848220903251, -1.4497035781866068, 0.6341567606639943, -0.1507666686534812, -0.5609259501619196, -1.3616280101403766, 1.1321882134959231, 0.4458137502712225, -1.3383112264320454, 0.5859486879147096, 0.26930331645657907, -1.8018640661531873, 0.6208737426762375, 0.6548425816587556, -0.01614823395624679, 0.3034246063138417, 0.3923544383601408, -0.1467261319735624, 0.8330071626357193, 0.8528095865569318, -0.015836469095310734, 0.25381747283935907, -0.6714879637987525, 0.10210633705145065, 0.18695501632089975, -1.4875800941755974, 1.224985032384382, 1.0108786898860764, 0.36504232564244343, 0.3255937474969742, -0.524186857883532, -0.10314674621910004, 0.5444037545544921, 0.16203714219022142, -0.1594466837935694, 1.4237761913564433, 0.44906150994374183, 0.2579488725752772, -0.9416624123871463, 1.0481982819915765, 0.19622715889941691, 0.9870909909329189, -0.3662850633718889, -0.14068139816567718, 0.1813801729062013, 0.8086739732787526, -0.09398453850508989, -1.5829296844092613, 0.03568285962142086, 0.8929086649108336, -1.9806393837402851, 0.5186642530700193, 0.9281976579440304, -0.6194606204181435, -0.28105325166916245, 1.3699628663451895, -0.1560282514440144, 1.7091755937620667, -0.04392445192548743, -1.0992635894536027, 0.34724545888719394, -0.5270354037094629, 1.9586951310139555, -1.1692758354656352, 0.4484149806561404, 1.1464729748576288, -0.645279793010471, -0.05515295416010663, 0.8683937267302079, -0.3833624624686143, 0.6651518313102839, 0.793807288951031, 0.9887784922310808, 1.3243480331203903, 0.0770361639416499, 0.16444840630363888, -0.040731734395848686, 1.0479761430899968, -0.21450968001507, -0.07604460597123311, -0.5407013550671075, 0.5547756713818791, -1.7758623718213447, 0.3118868525895239, -0.5413527634853067, 1.6699455753718564, 0.10628504548473464, -0.38551519821312724, 0.026162986866909994, -0.18051558975884563, -1.2100392519628962, -0.43207641570321653, 1.2785836590908732, -0.7755411952148032, -1.08370499690403, -0.43727773804299763, 0.6128151482168853, 1.474933041650161, 0.10866101912897504, 1.0833611842710913, -0.4099804356964772, -0.030401140395453316, -1.2979754619523884, -0.21657574007413818, -0.937829334229896, 0.6828847714666485, 1.5966050469006625, -0.4262115938220392, -0.2233029712294527, 0.6398777535023645, 0.4874952894579969, 0.10541081500893794, 0.9580391787764878, 0.4821967488323698, 2.1026939580209696, 2.1444733039496118, 1.8990319124045467, -4.586189051690572, 6.429061133303684, -6.153490971363869, 3.2969702153289586, 5.523720626676059, 2.294055723050289, 2.271898563940299, 3.5619657106968283, 3.934534893638828, 4.16059274440813, 0.6084076574580137, -0.19064545671799357, 1.6223678981919876, 2.3890759292257338, 1.1168414844108456, 1.6162631772411307, 1.168241212116948, 1.2024407616171096, 0.44401669135485516, -0.32478253367523807, -0.3313574194861895, -0.7209510620929868, -0.7930408496169374, -0.6995281545334369, -0.2600673306600406, -0.5472877437303936, -0.27303739789985876, -0.5078131803315713, -0.3568297670758218, 0.23805807502466772, -0.09311082819038863, 0.22214364137526837, -0.6005992105667096, -0.6757663403734507, -0.05539391722495805, -1.147258367724911, 1.6122634244816052, -1.7555956201712037, 1.7666639020521806, 0.40604969399212515, 0.8387011321498885, 0.47829561304701634, -1.2886118754398392, -0.41053663727993966, 0.17879725468469046, 0.22916871444469428, 1.044050739796507, -0.3139024106949907, 0.1050089416324441, -0.5205211251160143, 0.5587446820505512, 0.4495235469507691, -0.08479637395672508, 0.0728337457341778, 0.33451439168308955, 0.9946268784833057, 0.8920235607244464, 0.503854037468806, 0.3335423597903541, 0.2525002528006902, -0.07936891881255038, 1.247214139487106, 0.2834318199774039, 0.551255911507603, -1.7818723316168676, 1.896530884707269, 2.1330601164589584, 0.1766465505219151, -0.11279526113778425, -0.520705710794258, -0.082844768910929, -0.9449540744540724, -1.2024193638654426, 0.19483960998740005, 1.209468818039315, -1.3483604685510433, 0.04209832374215464, -0.2401786939477824, 0.41742121720577996, 0.756687545143453, -0.18527719053920344, 0.11699144063940888, 0.3377092463775237, -1.1572656467001312, -0.805468985078279, 1.470739378522443, -1.1942239848308445, -1.4808894524738472, -1.4499239139743938, -0.5251552767142892, -0.21973956310293866, -0.5464539425141332, -0.5958689265665329, -0.8292007625721467, 0.1226020518803966, 0.7969746031125667, -0.8524050431729541, -0.6196351361658213, -1.8671302876319331, 0.30585443625398034, -0.33502749287314515, -0.3614087667709645, 1.4081637045147786, -0.35735347296593634, -1.7517336952947231, -1.595774857123612, -1.0391649480499017, -0.07843533250988868, -2.228583405041567, -1.3183107820617688, -2.172944952974468, 1.5327138828447817, -1.003690484409596, -2.2973341224714345, 2.0127375864417187, 1.1265962597837464, -0.6565764820358749, -0.7119166470343282, -1.6185730405145597, -0.5153145009122102, -0.33259224733210035, 1.688427876214989, 1.1160839430585556, -0.7855287370797795, 0.598359869121305, 1.606833040338015, -1.5417528513737604, -0.02645166849329795, 1.4684604167504762, 0.4933363190720763, -0.6660790557207471, 0.2687568975392193, 0.6151952638926171, -0.7710124847633735, -2.134709161269158, -0.05847764955516553, 0.45159326326471527, -0.011938318823602414, -0.5568695337782434, -1.519429689109488, 1.900298733906463, -0.4299752891422906, 0.8598388328646271, 0.284048656607338, -0.8808077777937732, -0.6113862318595612, -1.7503211425027527, 3.083280184059974, -2.1157313615070414, -0.4034970590979681, 1.334239043419111, -0.7753973592334031, 0.5047926701407397, -1.960054930900436, -0.32514346118472753, 0.7957348054986045, -1.9528925465145293, 0.005261028445234885, -3.674323380176082, -1.1092281124281589, -0.7533542167055327, -1.2307199150823538, 2.385535346202361, -2.193836656790478, -1.2110595259943304, -1.3986360681862355, 0.42842923772889024, -0.9392294318776994, -1.5303330514868334, -0.9109290804714724, 0.7098825148144842, 0.07395761113330639, -0.6185465713859868, -1.175472314004447, 0.24912940522329366, -1.776643648100226, 0.5443893249194229, -1.6329561904218426, 0.6523329195280253, -1.6125218214455712, -0.14163954907377438, 0.3096538798783898, -1.9148745278555932, -0.7785232737465864, 0.30286450797469194, -0.41022532145605983, -1.7829692680475815, 1.9840209816404455, 1.6588575780009591, 1.536009563022286, -1.8498673328022983, -1.0971926056939079, 0.25504193447912316, 3.3206551315677726, 3.4246929730487095, -2.744504528486917, 0.6751246362600252, 2.289822728457486, 2.103953021481804, 0.43165822152112626, -2.136323186912606, 1.8244589563708353, -1.4987151756737669, 1.0702813763039027, 2.598846014817608, 2.8497002576627315, 1.4093710534090298, 0.7555263212866788, -1.2735400035757078, -1.0760619555485278, 0.6930006468911988, -0.31968655530489154, -1.0574676191766237, 2.0718532958672022, 1.6895695354416065, 0.26045633971625093, -0.36471818886741786, -1.8036232072635328, 1.1502605779010517, 0.37810676125901516, 1.5176551307973147, 1.0307947292793551, -0.7563268690260069, -0.6235422943894482, 1.2676460659146778, 1.903589086869162, 0.6639308625008626, 1.3384980775209576, 0.20465513948246467, -0.4620265680108881, 2.164785803270504, -0.6868979337395066, 1.8141851779737455, 1.5668957546219562, -1.3024075917097107, -0.7704967209749768, 0.09980527505961705, -0.8417562857943265, -0.8290815911807481, 1.1105264873686362, -1.4147098446593638, 0.6536816496335869, -0.5388254882751996, 0.19702824488302972, -0.5303108485909658, 0.6713733223560793, 0.6679377489955977, 0.43666463103327685, -2.0790312435994727, 1.2926572709135182, 0.0916914316569673, -1.9511771419657324, -0.32557258907755227, 0.19505246394261247, 2.0123784630311268, -2.0162501092505476, -1.259297422636362, -0.5453377363555689, -0.32174202137765034, 1.5607726791824261, -2.6502416036844156, -0.4223775007014278, 0.7448879729109129, 0.7310791784160968, 0.3898645269430935, -0.7704371664384038, 1.4314089215459982, -2.170299355131165, 0.44924353630606634, 1.7280940348923757, 0.4740764793334506, -1.5142670332364596, 0.5051288129355328, -0.5531419689602791, 1.5332617168428289, 0.39017867589571215, 0.30435699027545127, -1.4961355194886816, 1.3196635819252605, 1.045143586923962, -1.2880405163707331, 2.5526426138922216, 0.937436384266553, -2.5182502484158085, 3.047033185548121, 2.380771229639759, 1.104157757374987, -0.11048186513549749, 2.7470070334206356, -1.48439616548162, 2.1949030192064036, 1.5286928371521982, 1.5834966913086395, 0.8508702054773812, 0.975724783448533, -1.1061325032481701, 1.662893324350299, 0.06265946956623557, 1.091983276134292, 0.2216383750226051, 0.26233161360412355, 0.05376942099283338, -0.7487009836553427, -1.4608645862108884, 2.395855785512313, 1.2840714396751851, 1.8525381622496766, 0.9241694973389748, 0.5332490412480685, -1.3470921461977179, -0.28978420190049986, 0.6740596931232836, -0.35954955216651663, -1.3256452382921484, 1.379850060239469, -0.2764321931273631, 0.8990554220779627, -0.9904160449616315, 0.9252202697844871, 0.14361451505253156, -0.48064469666344456, 1.9057988846084701, 1.0561025119176528, 0.28995386238996823, 0.5903167639188233, -2.165096975396493, 0.6330409972302637, 1.6517145402362774, 2.024697450857356, 0.6785393805680715, -0.48040512141497654, 2.3344986225045155, -0.7841954791301441, 0.4091352493838547, 0.26326531785113194, -0.23463110807923385, -2.6050915427999035, 1.9195955765526345, 1.0968940108766156, 1.763720717734337, -1.296150254348663, 0.23863393703365124, -0.3262796842203717, 1.1044649491915124, 0.6192663312039052, -0.797831819156988, 0.5349898566280628, -0.6565543289865853, 0.848401505001413, 0.3974305231159319, -0.7552691521400129, 0.22087715843443867, 1.2115263834168728, 1.6369895585959957, -2.782606180197828, -1.1454596272402517, -0.9724178015236525, 0.19582242638280822, -0.12700843519885935, -0.775521286778091, 1.7625356759985509, -0.3850499593104024, -0.4758885770590637, 0.057170499770953516, -0.15708529900019375, -0.9008798073032951, 1.1694206438611057, -0.5251664106966549, 1.146524328254142, -0.16553841552053755, 1.0258538300264999, -0.3605066295289621, 1.087871077054893, -0.9757419639288214, -1.0547598963860525, 0.20303661399571507, 1.2730416107604756, 0.08931247782921121, -0.29919253412820995, 0.02632736802896527, -0.5347122616790538, 0.9647955932414565, 0.11692981933602384, 0.8562628366868081, 0.3692105704775215, -1.1976026731714096, 0.6607419269197372, 0.062173259893164586, -0.2562910481518398, 0.16847267617339742, 0.11510486592081996, 0.5682023275409426, -0.5415281083579379, -0.5166137087337653, -0.3294267005505642, -0.758523878745586, 0.017726606443518828, -0.6943643116884752, -3.752645615980943, -6.005244329991897, -29.08548227268207, -9.000799405439478, 6.988710628298079, -3.3284930946893154, -1.8067531555710006, -0.3591093010733382, -1.4596697410886708, -0.8804494931950834, 0.18083150935232672, -0.6168013080743618, -0.16133937719026045, -0.024022964764496994, -2.7071409399211617, 0.7459648345722066, 0.8057879800205758, -0.7933051036302708, -1.9700424728840924, -1.1270802006468528, -1.9986910699645994, -1.6219944948239897, 0.29695238818691716, -1.1024641680988627, -0.6842438040184124, 0.0593971423500629, -0.405669331370939, 0.21866881208240235, -0.21877285858895246, 0.32507721858827265, -0.2660568786941754, -0.7540732021822992, -0.052115461729317435, 0.42757114650896777, -0.1557568834328193, -0.6981347116194597, -0.15700964007301307, 1.3739132774704053, 0.40911729580114586, -0.27286126001275385, 0.050094856508687155, -0.4823053248075966, 0.355665198125556, 0.3439844941397305, 0.25306061369279237, 0.19818404124729225, 1.3454459408471173, 0.21367844374509265, 0.20063993677321706, 0.45715272451141703, 0.3975190542150621, 0.7322612567900876, 0.6590502021114003, 0.056989439769374206, -0.16562894026581407, -0.10869191800566662, 0.5815941012391548, 0.8550557305813966, 0.9704051891016723, -0.1769611852956473, -0.18958180467852886, 0.32101202391495626, 1.035660776732415, -0.2602391134002287, 0.48572144253174226, 0.11162235441996851, -0.6674106066518822, 0.407894397312699, 0.3470007229216496, 0.5765349881292685, 0.3168838735150668, 0.7309327704298691, -0.05372727294812402, 0.1142263989526828, 0.46043051536483987, 0.0733515836379151, -0.23069781481113455, -0.11243959899564404, 0.6766601677216401, 0.04102616125691809, -0.46737314718533446, 0.03236242772566392, 0.8864719379836645, 0.23199077065535684, -0.6182228267066167, -0.5706231396549611, 0.4519523706975767, 0.26154427176931266, -0.017406983715743306, 0.4066942196356752, -0.3653158483214876, 1.2083877853013538, -0.36782768413431305, -0.1939096788186459, 0.634445870311299, -0.9637250778542229, -0.5535411613362388, 0.0719436423456903, 1.197829760551304, -0.3957949385856206, -0.20487755202690472, 0.2601015668490894, -0.14205573258644263, -1.1238431493614862, -1.059650747446515, 0.6521764600958554, -0.34623984283818426, -0.5088697046090199, -0.12066126950672894, -0.29903987239528257, 1.1184016071159624, 0.05936667499861149, -0.1448119512510501, -0.5798835785144943, -0.7457994312292489, -0.1419146711524239, 0.9656971963824171, 0.384409780682999, -0.27587232703831305, 0.67268241598906, -0.01820549796938162, 0.09779306457364756, -0.8487991023545877, -0.08496217658627367, 0.45410614605847516, -0.2624988122132665, 0.26494067064950166, -0.412215831336457, 0.43827093449274707, -0.4799470482949247, -0.4419435501751992, 1.2663851647660724, 0.09221096071492996, -0.3229346200148056, -0.7138633434737811, 0.08810033020982555, -0.4756749496964079, 0.30543181046537454, -0.9222893075417669, 0.41429330880567966, 0.5346116998565063, 0.6942915604160433, -1.1091890958129855, 0.6519614072052033, -0.542161409878538, -0.006648992841156332, 0.090764251049345, -0.3372393837631085, -0.24530922245318587, -0.9647338583224226, 0.0559104283115318, 0.225630867892918, 0.22386758225321446, 0.2220035433598209, -0.43494135943999984, 0.06107348158245332, 0.22798039181827998, 0.7715475515600775, 0.03950218493198426, -0.45849017644838147, 0.5458230749844023, 0.1452930618782391, -0.10065769178912382, -0.14145613954953248, -0.5815468581847031, 0.054140937680454145, 0.12553748992468092, 0.22893908253412135, -0.4833883135481089, 0.32549719048259346, 0.6854705425450468, -0.15499059896526168, -0.17457763802774312, 0.3457508010739322, 0.2236472215765928, -0.43167288990940716, -0.46823786309678833, 0.8419844198024856, -0.060092557376424896, 0.21002549095601067, 0.2615096412149181, -0.6775819213833968, -0.15071177709687175, 0.577329951405214, 0.3874678635293502, -0.664286106881793, 0.9769740584048955, -0.5507902778259909, 0.11152026669254524, -1.0131398854891556, -0.4194569491233985, 0.17140230852581834, -0.8544304548586769, 1.1093931341449506, 0.34457880958361836, -0.5384091964764803, 1.836929869653044, -0.34390201759612127, -1.10868529633422, -1.1505228125959344, 1.527758933868678, 0.4197755524662795, -1.5366193429784836, 1.1560108874730084, -0.17521518214743945, 0.26022027705439915, 0.01034046529380918, 0.25874288982398475, -0.5945641786413891, 0.11809905621422412, 0.0899857909836279, 0.4726209178128198, 0.38213517810181535, -0.08272091040722679, -1.7626766278972643, 0.18814029917228609, 1.020246341794609, -0.16558302141031436, 1.7184692125982115, -0.7342756348172494, 0.20641019859192528, 0.047284670883589494, 0.3873939005998724, 0.5922429116070362, -1.1401143905638245, -0.3957953436764111, -1.211589731872729, -0.2821717584959395, 0.8766884243529487, 1.5732110350624915, -0.5139952539467381, 0.3721316657835825, 0.022685929473009837, 1.1867404885931034, -0.530459922358432, 0.8208287035057857, -1.5390225070554242, 1.2297705374878665, 0.12133668674436672, 1.2464032954082886, -0.39973878023837117, -0.18539719068184238, 0.24471672499559624, -1.1587287502717778, 0.4163270712112012, 0.960192805552267, -0.5655208630426818, 0.4603708889021568, -0.11753309659510511, 0.35015820500733247, 0.14104056002700338, -0.7469263524833187, 0.7812853445086707, 0.25236020018655353, -0.8209389264508534, 0.7785212591172208, 0.6834379943366624, -1.0386935593675115, 0.29136945148141374, 0.35572802419803345, 0.6006507588334884, 0.5221640380884833, 0.264594796487248, -0.2873596602192712, 0.18674499109780848, -0.08691119951593264, 0.7511143197173773, -0.7220061794197407, 0.3514885074132938, 0.3456987334654655, -0.11037640562978952, 0.5344495387818561, -0.06361107016132586, -0.8859233258646454, 0.05474853894891039, 0.03688713196459926, -0.14263902065830972, -0.15603762050042588, 0.23308592784466514, 0.13060335074047377, 0.0014927449034459325, -0.4745154074422765, 0.10431849867273546, 0.3924193922531012, -0.7977003223950506, 1.2789644124345065, 0.4441445621935663, -0.23988723285971972, -0.9355255690362735, 0.5008118190454478, -1.1325710531143294, -0.29003286523737504, -0.30854925876190714, -1.8839085333393863, 0.10939843335381273, -0.027017171906231804, -0.5159977644121567, 1.1468891753249921, -0.9244806768989534, 0.4021168853380882, -0.3671923760104182, -0.09591154747803056, 0.17168805419391364, 0.3716382244784533, 0.5066867042430445, 0.12412609970364262, 0.24438304574318034, -0.8167186374223874, -1.4607015288977048, 1.24248595069214, -0.9725563760321106, -0.8255419195414355, 0.4648875792301299, -1.0038932720020735, 0.5546645755536136, -0.6386406321680644, -0.0416370255087432, -0.38663876370101913, -1.8888260798664336, 0.3991221269785965, 0.6041658223169649, 0.33547311322600576, 0.1829736405484452, -0.3018548229421236, 0.18371427826472508, -0.6294242475194838, 0.6325459709981196, -1.0216726873339523, 0.15524312086658987, -0.40102322303809923, 0.4565230800550896, -0.7823054228788887, 0.13298625606042314, -0.1821447748811514, -0.05378875822076463, -0.5806385318771848, -0.14771896152352332, 0.38670690716035583, -1.0784566338522847, 0.7504544989893194, 0.5101120587332045, 0.8798641283570025, -0.6934542078863056, 0.6695777927495279, -0.6903368866617265, 0.0904410099448978, -0.28240763221153065, 1.820488228494497, 0.014053164467468703, -0.29442355078282584, -0.4639924485529191, 0.38128799916526096, -0.1991563706271296, 0.07250809521541278, -1.0859753675841128, 0.8628387818984852, 0.7863867595500666, 0.3499864253439519, -0.21002994704014505, 0.22253270794597418, 0.09577094319521712, 1.8613819514259422, -1.1599729918876707, 0.28290440929491695, -0.2513355781656948, 0.028367244928767132, -0.23488454079075008, -0.16535870344138326, -0.3500373472950856, 0.39627476015610086, 0.2674732053000877, 0.7256781211745224, -0.11282156290125908, -0.12567311325229183, -0.5567977920526994, 0.11641230802156291, 0.7772321144908099, -0.29497131605096955, -0.13686347759457287, -0.24729530775357697, 0.1580534022575626, 0.7989937904736948, 0.7543931375910363, -0.5557968739238579, 0.4935106133141549, -0.8559208759019205, 0.2797205471269435, 0.5215067765517164, -0.3314021812521607, 0.28286556185845696, 0.3089747550530635, 0.3025803856938819, 0.471784048277197, -0.3104863662004841, 0.5852691308559078, 1.1545182241754444, -0.03727653353508031, 1.3618514550622047, -0.09167371059246943, 0.40621394608789074, 3.393830989110418, -0.5311761435269282, 6.682726789898443, 0.09497616083435319, 0.21253795938727904, -0.019804835809205112, -1.356017809473435, -3.3967498904341995, -4.094435599536664, -7.449033241656304, -5.758239691280093, -5.094559480075084, -8.819381654863605, -7.837327274664728, -2.6476378789711275, -3.5663322402708886, -4.36502254871839, -4.059687483610855, -4.132353242504105, -3.6254409620904315, -2.2986962043412302, -1.371528671441662, -2.208992734509293, -2.645201196630083, -1.5859129822894107, -0.9306223244793729, -0.13210567709319884, -0.24691206820912795, -0.4014204497873175, -0.18559263231314518, -0.16430871255909718, -0.9223413172123012, -1.2790044456118346, 0.14741468819133965, 0.3457829388155543, -0.88952598055213, 0.13218330528820602, 1.1859909962820818, 1.2614316187939438, -0.26689119980381626, 0.48631835132088136, 1.419377710775471, -0.49664366939832966, 1.2153326656602936, -1.3881420894237195, 2.4270547081241247, 0.6699098592557504, 1.4337337667048178, -0.020262227940463083, 0.4840374515262812, 1.4889426643606294, -0.06166099255645905, 0.7081695850500677, -0.21724032501660945, 1.0817425963591887, 0.6061504758910322, 0.2554285871163045, 0.8378394501815298, 2.0436866173241204, 0.0688572054852904, -0.09639306008600648, 0.2416182050917149, -0.6011312827126654, 0.7941878119989869, 0.3281567688576135, 0.3575710718290696, -0.9763809842501731, 0.6359369690104716, 1.0901222198932736, 0.05909114105122233, -0.2982300091866191, 1.0913434428798081, 0.2774079196871377, 0.6981521613944394, -0.024028883231376735, 0.9448134818907892, -0.14254825748189984, 0.016474983357330553, 1.22118696824375, -0.5526223863993013, -0.04723558099341688, -0.005677923103204829, 0.26275830228110747, 0.7539537336317258, -0.006873007142230411, -0.920657264688896, 0.3407787742184573, 0.22680587856369158, -1.5154984576678507, 1.7089015255269162, -0.9219971118019825, 1.280378216208071, 0.20098534879866528, -0.5153163288946458, 0.13871233706476802, 0.1492917737098892, -0.22709178175075975, 0.3919332578422086, 1.2599137422677937, 0.2957239827704303, -0.8404541326708166, 0.4554028671067306, -0.13666204194872744, -0.6743708840464322, 0.06168749068728427, 0.6983392013303019, -1.5514203753911757, -0.060631362350924235, -0.1648009152362698, 0.18018849753587593, -0.24744987415340158, -0.025177489238970334, -0.8585492882711527, 0.20204131974097822, -0.31082005697234794, -0.8214163991881552, -0.2843512207966512, 0.3985752748283462, -1.4102020492822955, 0.4330818706224616, 1.1665481788047285, -1.5214908439213994, -0.21610445481420115, 0.8414736266113124, 0.11980801018740404, -0.3009002093532729, -0.08448101684536863, 0.3755042516969412, -0.2213553872563273, -1.1241599957563224, 0.860961822112331, 0.5458438441609972, 0.0499221790070135, -1.0960277615973988, -0.23642995029425917, -0.43758444459408413, -0.34133477731122885, 1.087955807766062, -0.5401712192504164, 0.10882026988249056, 0.44622290801795195, -0.1496699407567737, -0.10319433360610752, 0.48953795997132105, 0.2411960038414272, 0.04677203158996109, -1.1649439523608245, -0.2612647067190284, 1.256018740222327, -0.2769520966518167, -0.08254275000462095, 0.8116136865754455, 0.8781633039340596, -0.41319970771188963, -0.04128264453883175, -0.20735794361331114, 0.27036926376304216, 0.360082331681107, 0.34446753114703793, -0.40897773604388876, 0.8256839860055725, -0.23767999451994037, -0.09370192391570743, -0.8226040802645337, 1.916709712241429, -0.6886254276096608, 0.2938548290069282, 0.43797609364569595, 0.22072426172281326, -0.16022402683699483, 0.9974188484113582, -0.20291701556049, 0.2947686855401149, 1.1910763734626482, 0.030341897867759784, 0.18031357429990458, 0.720147165572254, -0.05033201601723434, -0.0643060756170934, -0.22365601007907246, 0.7828757921410212, 0.485770156212347, 0.3100861126260657, 2.802591337592656, -0.4568958022063979, 0.35348163010849065, 0.8450364524553169, 0.027689533206769593, -0.5710062848780907, 0.003045037431847887, 0.2589092136179501, 0.664006570112992, -0.11376661362985073, 0.33635629374813214, 0.2569489850781017, 0.20757423866891195, 3.2351018859255944, -2.063052862764199, -0.09721249614253082, 0.2376472964137912, -0.26393774530997943, -0.7494196341507898, 0.07150675727203173, 0.31886033039566447, 1.4783280816683564, -1.2715564189003965, 0.24964151420316588, -0.8600159956343302, 0.4527206626276344, 0.831111927172036, -0.05470065634884787, -1.1507651833545018, -0.3485228418335848, -0.5653398653758233, 0.783765888720378, -0.23187045644101192, 0.6770547543073091, 0.5165084766499644, -1.2913984156111988, -0.9172838210308558, 0.7150926843242192, -0.45917488082051117, 0.3080176407459516, 1.446503911369991, -1.3683776936301864, -0.3917159639043979, -0.03340433583143441, 2.0844038956847335, -1.1328769354217676, -0.3946425374618699, -0.16618659954293113, -0.9353106180934323, 0.4595304303661028, 1.7677560224325353, -0.6676266463269525, -0.2589227906212848, -0.06217421363177776, 0.38233642931200046, 0.2227960234750658, 0.1364450927429271, -0.4832670485432754, 0.7995865441385934, -0.764935405054754, 1.004168689126729, -1.0843105534924156, -0.12520316049452254, 0.2295845777488192, 0.43172576298502785, -0.7015481785610975, 1.0419937006471005, -0.1947262369820513, -0.7602234426374173, -1.2432224245740389, 0.4322004142752135, -0.26342633013680433, 0.5194852109938354, -0.5583954865434747, 0.5575598823121162, -0.2296427856664246, -0.6777125353457663, -1.2250169193585663, 0.1292094986637459, 0.16696888118019423, -0.6309433079695285, 0.35407999627796666, 0.74152411187924, -0.2421472798761767, -0.10740510458614352, 0.2259146694399787, -0.3920513878640701, 0.264192586272442, 0.16554101827820292, -0.08227603668512203, -1.1035098480775787, 0.2623154203439877, 0.22638257446896848, -0.38977203107613856, -0.6163578794321564, 0.7049442056018611, -0.6239168982811139, 0.8950034541741934, -0.04108821301227316, 0.38189093396704876, -0.4924205501164719, -0.33845005194386085, -0.018921093226921856, 1.2958586935522454, 0.19958247375227356, 0.6930434774913209, -0.41740767319330807, -0.7086302659178229, 1.909947246446791, -1.125857345575868, 0.2854344203719821, 0.3334984877550883, 1.0826978468846011, -1.0684023806771494, -0.5340182456597783, 0.6113150180105368, 0.4989060084057687, -0.509456272768465, 0.05923183506377923, 0.803514369876842, -0.6208434523594681, 0.927851470734966, -0.6457431222348334, 0.7973996809163001, -0.050534441898743704, 0.35410458753014523, -0.3237899271575213, -0.5693365102019086, 0.23913077213484796, -0.12233312383800779, -0.14517589056592634, -0.30731924861048415, 0.9675115638711115, -0.6797174943211977, -0.20018283341713253, 0.9736672680132081, 0.020028011871274485, -0.21917388581424027, 0.0010369722689889615, -0.513148300802965, 0.7996785454859165, 0.5449516782827893, -0.9352518238729882, 0.35022064227550487, -0.280921220235308, -0.51144650702248, -0.21847027573633693, 0.3983797516681753, -0.13809596142388575, -0.0806729387055071, 0.15755231176463677, -0.17181581824661643, 0.25687806698745214, -0.17292984927148122, 0.021448679576490725, -0.5325697406800096, 1.4519165693512106, 0.31744254059155735, 0.36524525488011733, -0.33993209852769435, 0.504129505617899, -0.26368243488729154, 0.5787996695081838, -0.7999343248315494, 1.3136072461909503, 0.1986302819310013, -0.15206708745456046, 0.2750958802787165, 0.04894734535129947, -0.20923168335849912, 0.7200939771149502, 0.10540283222342334, 0.15796689550701498, -0.24145644135504032, 0.33116544937786174, -0.3709290145160356, 0.19529267186818083, -0.5540619801392268, 0.6798463220641491, -0.1318063522380923, 0.2766287975156063, -0.4627864303659031, 0.12563915770521025, 0.15379973972384042, -0.1775098137579728, -0.8392801074826286, 0.755112936762359, 0.08560836447560799, 0.3113865699213845, -0.2779833242881238, 0.1203705810131609, -0.17179292814517733, 0.4466592833171254, -0.8012208584003508, 0.19583594445139477, 0.7323201766863926, -0.0007458137288756443, -0.035494719290030695, 0.2764468187207581, 0.029985330456925776, -0.17070222792540313, 0.11372408332350395, -0.2434689368693929, -0.24388328818999455, 0.10453262928701539, 0.37674183624855134, 0.38144308806452887, 0.31436380187242763, -0.13462024011262716, 0.29161120170093763, 0.2363944153114618, -0.3791651770846265, -0.15371820489910834, -0.3373111647884088, 0.6110094300818952, -0.14888744479769334, -0.7207799370874166, 1.7993108475256527, 6.292026254427246, -8.283647113763898, 11.354674757094513, 2.8141548913291237, 2.1087443023663015, -1.7933002040257224, -2.2766281395015855, -2.7763156696982203, -2.7012264940937434, -3.827901310258101, -2.1266124698929736, -0.4828325797680128, -0.5247953595831047, 0.5973278678021251, 3.4900956073890534, 2.3720851205139186, 2.2453356565860694, -0.44512267652409465, -0.9474142108693258, 0.09202314699605599, 1.1982916275254258, 1.8189155573565932, 3.086771484030333, 2.7984972912112034, 1.3501853229395104, 1.1519158195778205, 0.4306167267443093, 0.39999101518260544, 0.44454945046567407, 0.5321965260067868, 2.5895838952229404, 1.9132394421558783, -1.2257736196899627, 0.23619499060349897, 1.501227893511902, -1.169082465516542, 0.6323021975924279, 0.8313967093803559, 0.6168193239578847, -2.316521763625499, -3.1295288221886226, -0.1311701221789479, -0.5232693908421333, 1.9313461373700946, 1.169118285093916, 1.7278090414853033, -0.795149982005491, 2.095194660920881, 2.518506948208703, -0.43230693523511143, 0.43729491236631846, -0.7772315792029912, 0.2597481604120768, 0.5366022749802815, -1.1071379561986736, 0.08134311981943845, -0.7790735035293919, -2.447110887225447, -0.8148786678295132, -0.7024616568625061, -0.2696306656067551, -0.6615462175552942, -2.088295683380757, -0.9239621895381186, -0.8169186926104407, 1.4071818195037316, -0.37613050975892776, -1.4226381708620228, -1.33315152815376, -0.09204742039453233, -1.2049118873251201, -0.5028252406041545, -1.2407238323544518, -0.2765915070371794, 0.001781798809550132, 2.2761683404766475, 0.5428173872828449, -0.5917966739249029, 0.33259913473222963, -0.25530053496036587, -0.8160209613729628, 0.7873445084165684, 0.9151292574709899, -0.47599719559873804, 0.5843470436715776, -1.0231829852453485, -0.4204880189608218, 0.5842688334942516, -3.0899948755619007, 1.0323253278556528, -1.099595688871327, -0.4021894086416632, -0.8835971371143183, 0.41780387435388744, -0.1520055585531589, 1.2783878701002314, -1.3342076368243245, -1.180581954914244, -0.1961758748593732, 1.7501761393706312, 0.05937700462160837, 0.1619613825603171, 1.2814888043455521, 0.09875742287580941, -0.5773014720927684, -0.5927875950351159, 0.505195432188512, 0.6466671187355716, 1.126523390953045, -1.142568911475301, -0.8639481118892129, 0.13026197319675742, 1.2057593150768684, 0.21085021146873006, 0.43128310188603775, -1.1037228290533607, 1.4031076708975228, 1.5870292786072506, -1.447356032558866, -1.254771002854853, 1.5943588243976619, 0.05410956613451681, -0.4680215786723682, 1.256643560577979, -0.6761665269866867, -0.9501857837339256, 1.3284117912450988, -0.44365958249874543, 1.839409375109353, -0.9983908438631947, -1.1348193861841267, 0.41046615051826835, 0.021855955989799114, 1.5652855140514508, 0.27584872826383006, -0.17783111722121722, 0.46992387471078073, 0.5144441404597119, 0.28152138828013606, -0.2517502257989166, -0.659799871975695, 0.3799017743394709, -1.5756015116460498, 1.6017263764984542, 0.4662695216705461, 0.9572889595941892, -0.3001575295252387, 0.9160381755175979, -0.5784323419052211, -0.9664551845280361, -1.7447914502755821, 0.716993722783187, -0.43898247356454045, 0.47255898540905844, 0.15080638128038026, -0.38213189017656485, 0.6365426297130685, -1.909396968243126, 0.8594482544251489, -0.8488228951772921, 0.3351233372784062, -0.5789019906763433, 0.3621057223092464, -0.5601488759431489, -0.13050329757902762, -0.2855633216788314, -0.4365489562958, -0.2579650445607551, -1.7464047749312863, 1.430098821654263, -1.3208648682518986, 0.7680150511185246, -0.7282033105600663, -1.4592601669558574, -0.8813755695949329, -0.5271828407288859, 0.5160592189761546, -0.9295065957019357, 0.4999024882904114, 0.007011184521044047, -2.1785857094038206, -0.20560903038395043, 2.115802354284708, -1.2667440746147065, 0.2038332430572142, -2.0938823435567713, -0.17903571531719042, -0.24208071155564537, 0.672807855319363, 1.0503296506004667, 0.2534574261355422, 1.468392177720057, 1.332298226413831, -3.1639163047840317, -0.9090343450291207, 1.3344199804392796, -1.9190026294373541, 1.0127321488602679, -1.1470689515133428, -0.1829032289877949, -0.0786384577528281, 0.04381778060930446, 0.2127908056274921, 1.044103450579452, 0.24341112260964884, 0.13236484664160758, -2.1393719931335675, -2.4320774469531905, 0.5126775510214449, 0.015788702505681235, 0.8859372930202722, -1.1969962417859932, -0.5956687958116699, 0.14786541939429096, 0.22311929463693272, -0.9300779580955252, 1.0503152186618072, 0.8697648208061791, -1.7321648120518653, -0.6991169475284129, 0.28717337181659786, -0.4107646757819142, -2.103736920046405, -0.31994051782800836, -1.3501817024048868, 1.5496751032993312, -0.7762934927574667, 0.5639485479106717, -1.374910607805259, 1.8151477866535004, -1.8356678099339234, 1.7357174154806272, -1.0383246876364527, -1.1989339952392182, 0.6673721958646225, -1.3564538126819299, 1.6398386720239568, 0.5442784047085777, -1.318122993106745, -0.4957975370605847, 0.5563328471318157, -0.036215679790590184, 0.40366419009281995, -0.8155625401265201, 1.9377422590125337, -0.04682813127866432, -2.037778396585295, 2.1861280349208516, -0.6495454596414432, -0.04324410554943999, 0.4494697267681817, 1.1570389668597219, -0.07204992864419546, -0.9062454356776004, -0.029080935716275208, 0.10523411805712483, -1.5292151733530577, 1.20160955140796, 0.5405655370081814, 1.0313176739516001, -0.021581859296392465, -1.7068708393969645, 1.6856957413944862, -0.019198336149482225, 0.5375973703207081, 0.09323581872802841, 0.372577814986151, -1.5120484689285676, 0.7697704107890625, -1.0815363420801745, -0.5300028219776993, 0.906378038551936, -0.104561333122045, 0.18853038658284496, -0.4012568994107702, 0.4386521452808443, 0.06873431500873574, -1.151661483386638, 0.4739201522954907, 0.6248764744530894, -0.21378459807159558, 0.12327736923860927, -0.16991898776328818, -0.040278440015000604, -0.24469938044741507, 0.10660840799105976, -0.36517685313317017, -0.5938480374730161, -0.2942146941715262, -0.08194105913905225, 0.45759078353168375, -2.1572209526959507, 0.38141772013588876, -0.7894369883131589, -0.0882144759329453, 0.5417761910109816, 0.569199915567022, -0.6193023575004476, -0.9116679975149582, 2.1749103889053107, -1.0632525640178954, -0.9387588436450152, 0.7863233270093193, -1.6755140162848057, -0.2627909975545746, -0.6176732664273824, 0.7540663672370924, -0.9676812615823395, 0.678780164072894, -0.2193291771893627, 0.8644146347209977, 0.21582141238913893, -0.04777621905782807, -0.6573078019662489, -0.2418275239483758, 0.39218589460941367, 0.5526587540167898, -0.7944027460836117, -0.4025959025056565, 1.2280703673687956, -0.020902892427015218, 0.3910640450044741, -1.490226388261661, 0.38972440674156394, 1.8353589830926051, 1.1132596448949348, -0.5563878148276603, 0.6409472569959135, -0.42902358858642986, 0.4009933513936435, 0.16653240779512454, 0.7373389755416543, 0.37954886219373396, -0.003576264435412257, -0.05810775168235687, 0.3015170913824084, 0.36299248811409923, 0.7850281105926912, -1.5682832418451123, 0.09746005090195185, 0.5706631311143395, -0.783708339749349, -0.533276699520053, -0.14866656952826057, 0.5590481093073159, -0.6292321309700862, 0.09028598703747046, -1.2023180998261178, -0.24392000075758097, -0.4875708417258891, 0.26932530631047, -0.6516747758863793, -0.45844924449571767, 0.7303072567317792, -2.5215871424774283, -0.21464993045268357, -0.7118944477364669, 0.24545551102704485, -0.4285723358813334, 0.8137453039502182, -1.172565276205539, -0.4899474714058481, -0.4228712266324149, -0.06573754238004935, 0.14888909006574488, 0.7097030913461531, 1.4649602260274965, -0.9445471964756383, -0.10052304599570253, -0.0687925059242557, -0.38953458662711254, 0.4167202054691356, 0.4070601177204039, 1.6579290155003947, -0.6421700116353092, 1.0784107346811806, -0.04386571860443315, -0.6044547644310657, 1.2703722094297751, 0.7686484876716941, -1.8333590280306773, 0.4010108184330672, 0.6883257665691349, -0.8743738767726449, 0.41729969156950064, 0.6853009885144166, -0.5606338144992604, -0.030657862965695223, -0.7991317477894655, -0.9982086827243934, 0.24316128574729753, -1.0471139673855523, 0.859202773371262, -1.0804578931689508, -1.1022011066672388, -0.8684328635156983, -1.3496213588533947, 0.8894375114563219, -1.2740511052984038, 9.869853227067097, -0.6831754069344825, -10.021901793453027, -4.964532720259668, -7.065878434370457, -0.19628133295791136, -2.080488913535862, -1.2988204285514635, -1.6222764166933066, -1.4057315873957315, -2.9407887722839208, -1.4344800238486832, -0.07391069600673231, -1.1972301667441239, 0.43422769174568243, -0.23987986420198634, 0.5436982411554688, -0.04400437038177913, -0.5017350873652272, 0.5871685195865637, 1.420002995519343, -0.29452784201765053, -0.056026362792291354, -0.137580398444511, -0.3091828943732878, 0.5185829106462468, 0.34394255478289437, 0.4096148945706293, 0.03295387550578101, 0.8260807966044519, 0.3575272145439268, 0.31096577540644504, 0.29313419920286615, -0.21277413364916303, -0.14133229232795036, 0.12461208750282736, 0.2844064955718958, 0.7573172304697041, -1.0174995460957934, 0.5839474527805297, -0.1370160017015065, -0.7653683350932087, -0.4470797115459771, -0.08671919619003582, 1.0477271981679006, -0.4339680441678451, 0.8458613370502661, -0.9926881820413846, -0.4545463394409748, 0.3990567335751689, -0.23531638467599605, 0.4875464744182759, 0.03314714309503988, 0.17150459948213445, -0.39737337795239946, 0.3751525699000281, 0.07180456517723866, -1.0215993349612589, 0.6285665063841159, -0.8032938869703335, -0.5060659719196133, 0.444806753283922, -0.5985894719636076, -0.04914490967143281, -0.266197425907435, -0.24643082529665777, -0.45206664496639265, -1.1619968978310258, -0.8675585636104459, -0.6425702485220487, 0.14619263283030084, 0.6062217345791011, -1.164123790610553, -0.3132781801935095, 0.4063836481811833, 0.9996948724815297, -0.4649088444525101, 0.6040797483464383, 0.32921102160602794, -0.04712819764912222, -0.47296307103528334, -0.21823195932452574, -0.7857246761754406, -0.08739416321116195, -0.36211407826737396, 0.3837022654917991, 0.7537316916761796, -0.009557913427092972, 0.17627646176968517, -0.1711476158392463, 0.19578809507358336, 2.4268465964420893, 0.020507896280988713, 0.10685387169281003, 1.9807412118510603, -1.0386453819111132, -0.4581885543024437, -0.07711364176978878, 0.1636747794417364, -0.38237632428600304, 0.384860630099561, 0.10359088128171555, 1.2777941263496049, 0.2560214908231809, -0.5591476209549402, 0.7517131507953614, 0.7286091925919, 0.365509923699851, 0.7821792393707404, 0.18234680809472625, 1.27883675519894, 0.7241990261370519, 1.756522583766517, -1.741446174804004, 1.199648314992544, -0.11711091882681209, 1.9916984406955118, -2.993358072926749, -0.08178655050499814, -0.2677253144691316, 1.5177189258588268, 0.2640111185684487, -0.4809060310291285, -0.06636826353322842, -0.7010280960984466, 0.24683094219686147, -0.7827290121358538, 0.29082723785540193, 0.46418316828780226, -0.3926510464518056, -0.0814564804831526, 0.5011026502861169, -0.22763377807312468, -0.5547490898254932, -0.8994577478271215, -0.15970598274719083, 1.0933667673367315, 1.0779210140188074, -0.8235976105598979, 0.289226134300131, -0.3899182630858235, 0.3532738538868261, 0.15645093174937033, 0.15389782878054203, -0.5008679364379612, 0.1036742677479008, -0.4178999982857135, -1.2445557630946629, 0.7995563160068297, 0.38213940232707855, 1.4064303144176182, -0.040175750523466405, -1.2952434545248939, 0.32812512223578605, -1.167530377085972, 1.8302927644571103, 0.7174588195095588, -0.15578817576283316, 1.030820420171378, -1.1319902433660387, 0.786904726179689, 0.8779682725044603, 0.15297104995573954, -0.23656377129960532, -0.018773203252517752, 0.6041278590857314, 0.04792943014629903, 1.2651575582297667, 0.217266445069928, 0.6352508573523852, 0.3533251889229178, 2.6443266579973126, 0.6215798552047053, -1.4306252541980666, -0.41427924387011583, 0.6214097928167559, -0.5753362846640211, 1.1498499310883925, -0.8752926688024968, 0.921031835017721, 0.8935304766000041, 1.0023322726556656, -1.0495123354311882, 3.0706955526872237, 0.7019719922957468, -0.6168289306863335, 1.0249279004051812, 1.2762443450626562, 0.6465192234613112, -1.0548714798522498, -1.6202133846935372, 0.34014126468135863, 1.6673915872963567, 1.509050817814439, 0.6041828717520195, -1.4280374878484206, 2.1537303925710436, -2.6263821435216332, 0.811128311358607, 0.30824054064016404, 0.45645097656551026, -0.9618458617376681, 0.8947096200293759, -0.04697430625196328, 0.5597410383441156, 0.6203792503648051, -0.33799434433751535, -1.5188969247962443, 0.7312716491375431, -0.29590219135681683, -1.1750155591099256, -0.24548019199268528, 0.6302260066731954, 1.4731163032481893, -1.3189308042017298, 1.4970129669209657, -1.480931567792477, -0.509080957766755, 1.5555506036285778, -1.4247850421624448, 0.756755579318398, -0.13812411835185218, -0.9207230238448414, 0.35476677015238145, 0.2892801157005741, 0.27704072943660724, -2.6960475380854105, 2.3404787173587436, -2.439069571379009, -3.079979189595392, 0.6329775429617823, -1.0614468149119516, -0.08569504277336629, -1.3851953360135978, -2.057851582862786, -0.684897291177924, 0.9677668689719031, -1.8678423416448307, -1.4549322438325147, 0.21084831627439857, -1.3081485186196826, -0.6155728320550173, -1.4215632313917268, 0.5772129465315035, -0.5013823486294758, -0.5270030897874449, -0.06758374261717337, 1.0350596702969157, -1.7203280347261978, 0.561769695039736, -0.9098169367517184, -2.1437697658126216, 0.013222732152995118, -1.2336835293960726, -1.813889306393281, -0.8339414463801602, -0.4950599558427732, -0.9937317430360523, -0.9520040363706216, 1.2054650768162352, -1.7392210308942238, -1.7509501476211609, 0.6683011975221345, 1.077729569837677, 1.52593092815551, -1.8112449098819523, -2.255807640844395, -0.7717011907767107, 0.5619242656223972, -0.42008698494952684, -0.8744308846120653, 0.08859529689161641, -1.8752658917403324, -0.9281683804993835, 0.740012187493678, 0.9773512081430383, -0.06412825617961647, -0.8613152011403609, -0.06231795780712733, -0.709840306383364, -0.7147496676370041, 1.3173252068730101, 0.8610534829216602, 1.0405538825501657, -2.4804215336232622, -0.25558743818014773, -0.4599746180455873, -0.014665950880754335, -1.0787702595831135, 0.2956907337419634, 1.0615377652043254, 0.7284575913605685, 1.9508164282839222, 0.43233237868831925, 0.3894942159136471, 0.6639006902851102, 0.9284535945884983, -1.0870848588699362, 1.1965506141463766, 0.09302130426109498, -1.3671082116613633, 0.5151669059601652, 0.5022863052146384, 1.8477619055402779, -1.0954225865930942, 0.6549208318950012, 1.3866442702660624, 1.4848799589252455, 0.2341447402611384, 0.7024152719202515, 1.8016163108030696, 0.21276292844780625, -0.7266849210744376, 3.0808572976523045, 0.7936757343816986, 2.513026890704676, -1.5311680567536134, 2.1449592416091123, 1.5339623326317824, 0.26242413371957385, 0.16189103216519085, -1.0380945064883582, 0.8073516007956968, 1.824616477837661, 0.6357956815790302, 0.45888363644898433, 0.6509652732553779, 1.3693773428582328, -0.7872770904893699, 0.268575794901936, -0.11854839793995921, 0.01235310397741303, -0.7331333441896357, 0.7526412498750124, -0.49469871955959005, 2.1125621632186937, -0.3654415606515523, -1.4543278299377929, -0.585574972081306, 0.22739925862321186, 0.16921445359851503, -0.34497662134593027, -0.9056298318485204, 1.3551670331709291, 0.2090637894758232, -0.3103409856002214, -0.10829712177484992, 1.0011611635655397, -0.9862824396278054, -0.39766062569431215, -0.46308930444923324, 0.9019138481392432, 0.18004538917980764, 0.13913339766834595, -0.522470176881933, 0.1763029576034233, 0.43850207761682897, 0.8188404359207945, -0.5205801396683954, -0.8238704317421437, -0.07830702535056755, 0.5084124693572738, 0.0023218023692631465, -0.3948695668412719, 0.22487001946403878, -0.1314497491239877, -0.28883660603643946, 0.09835211720023228, -1.1207083849184947, 0.32283575402169495, -0.927427126469354, 0.3617845260339801, -0.38492246600889246, 0.4474548978816373, -1.7023229837345542, 1.5656258180096279, 0.2486693616164328, -1.9404028595953025, 0.0077937652842863915, -0.23260825867304266, -0.07559907140754885, 1.487262065404339, -1.2379545970826862, 0.04145430996693748, -0.720032298091291, -0.9809252396132456, -0.04035265129705015, 0.8929548477222465, -0.47276372574110254, -0.3140227810514825, 1.1090792200258384, -0.41900139491477767, -0.07248065923500699, -0.4243378284394197, 0.2718901586740363, 1.036773030639297, -0.04771588967523098, 0.4098537918531374, -0.9373751069016795, -0.1096783431650668, 5.229609388420825, 6.092738025426123, -0.5839998409728716, 2.354200664568099, 3.667772626150809, 3.7866917507543714, 3.4420736022627008, 2.1309618283033207, 1.9335845738781865, 1.498586940709723, 1.2668260167752416, -0.14203041851070025, 0.9825513529211334, 3.4546539734849224, -1.1341928050505246, 1.1191858456321695, 0.39683985941557726, 0.9820299419930653, 1.0752698045137525, 1.6546916693109985, 1.737640586232405, 1.0362914645661703, 2.043428416662843, 0.4536388091712524, 0.9301337820488084, 0.4485036626233123, -0.04737110591693676, 0.36494265155381805, 0.4070910161189569, 0.3678850280074394, 0.17536498057092254, 0.002001174638649366, 0.34712885812374056, 0.6356290345946091, 0.3935298632426367, -0.7075086222852921, 0.08792123859479122, -0.029806565159953547, 0.733712739729396, -0.17896824644858486, -0.05621531517968208, -0.7209925403528289, 0.46212269162077074, 0.06364608076826402, 0.9622959295201693, -1.5644492701270087, -1.984054212018317, 0.8184751125783579, -0.3456548044522323, -1.976166651159608, 0.2751276935306816, 0.27580348301248764, -0.15371693809574022, -1.0756474346636378, 0.34373359839832224, -0.5868966954208991, 0.7115430334911718, -0.9208220306062971, -0.6234910302917823, -0.6428599960936812, -0.17563379065461932, 0.22300356536335156, 0.15115767180663092, -0.07391982388448531, -1.1118560367068715, -0.14279983936395105, 0.4337095368988, -0.21274640875744164, -0.31933060552022396, -0.4448909948005261, 0.25165809662339994, 0.22363407785174128, 0.36713788145842485, 0.6732114477299855, 0.7901740579434966, 0.1064966579990205, -0.7497776185837832, 0.4669175837144924, 0.1287410638134191, -0.30868115514219613, 0.6074225629192078, -0.18044934664274384, 0.32720147247497117, -0.15153742610147644, -0.5460718280065382, 0.17728794196035458, 0.10962768185633351, -0.45680143057669326, -0.3130218121282211, 0.5362920419692652, -0.4373717053352396, 0.4886501096339, 0.5928134880134343, 0.36749757660380244, -0.1700832244495427, -1.11955239546837, 0.5235658689933282, -0.6395975565857812, -0.5327701991602137, -0.3801996763945084, 0.8220345387486081, 0.17191427531836614, -0.05258487505694279, -0.2924745081581656, -0.3991344500717338, -0.01456152393988642, -0.21185330912389028, 0.29309056889596385, 0.4279538467437847, -0.2662306110879485, -0.5560371914563456, -0.145555220594179, -0.20080431146281405, -0.03693082124059709, -0.18187524001202296, 0.3877327920181467, -0.5069006362391207, -0.868693322638214, -1.085442237954694, 0.738402296753055, 0.4711105521915343, -0.6746350257640672, -0.3689693428339127, 0.6639359347514844, -1.1124159162639795, -1.2343451094527056, -0.034485991439114835, 0.024666556141626935, -0.3862705225606538, -0.8100277820638937, 0.005114440214012608, 0.5832027070444439, -0.43329469001401044, -0.5502229467915537, -0.40427898192926787, -0.39890412218984184, 0.07995137944823269, 0.49328304918672483, 0.20013066727706633, 0.40775790428832, -0.8055885169719613, 0.0932375337564804, -1.1753886934680409, 0.02517776117912246, 0.3500171495176216, -0.2831938407141131, -0.6969094215694955, -0.4302813582453855, 1.5078553118639786, 0.26899913995465224, -0.5914050731418333, 0.47995731379575385, -0.45070419792056626, -0.19769929681543816, 1.1859723387496777, -1.2186172839382958, 0.8127248189316301, 0.6935141271610353, 0.22085982700565363, -1.2970039954301111, 0.49986162136080525, 1.377890984718372, 0.99602518133416, -0.7119707017928236, 0.966853790463637, 0.3056412676027154, 0.16110572306263762, 1.4332736846859127, -0.35404521953130624, 1.2837717255813612, 0.7783837728279251, -0.9273613590850844, 0.08914490436586743, 0.5078098286497793, 1.1994482721366637, 0.9293620641393721, 0.2889269911696291, -0.24591492214128213, 0.4781206004137505, 1.2218147315419583, 0.6794335197440802, 0.503963310454261, 0.768608957890135, 0.3283571394430392, 1.334064674386734, -0.9125327834132982, 1.134599609830592, -0.6293232432783735, 0.18213799000553685, 0.9226927755139595, -0.33543443110649224, 1.4108199838238145, 0.30391657022831975, -0.3273446820311134, -0.5745140502812225, -0.5656500463350779, 0.6680207727271499, 0.2340211517700352, 0.17026762635564816, -1.4932912010270762, 0.7145675324352414, -0.11072660971064834, 0.3756910426087751, 1.7445999720428185, -1.9169345766527834, -0.01474454326012349, -0.2664304935345476, -0.1384415305418996, -0.13549370812411823, 1.4397364671729314, -0.3154897709871428, -1.311351193789411, -0.2072515546887058, -1.0110985419336085, 0.28321827902776825, 1.3480879846046063, -1.220083474848541, 1.2666943846451675, 0.28879143093193355, -3.5182354314536495, 0.41337095591450235, 0.38902043747527687, 0.7382215363278519, -0.30666292553623764, 0.07083452250629223, -0.9872964228526917, -1.2386952015004582, 0.7882595873529257, -1.3055131425621116, -0.8219392540454561, 0.062196044170654004, -0.10169762769799635, 0.06732499817423418, -0.10356821848474389, 0.7720681709876438, -0.3514747180561726, -0.870014932913767, 1.4760707642813504, -1.0785688423410589, 0.13921077648752686, -0.421646736523973, -0.6761344352534628, 0.8541671629338007, -0.2610074852934293, 0.7097954785644832, 0.222350139963415, -0.25791273395263714, 0.6486919547932104, -0.025637154637288512, -0.2941037010196574, -0.0638529891873938, -0.9707318162274445, -1.2124330803723153, 0.2974101361200467, -0.9995802444523892, 1.0140351913437926, -0.3292155068489315, 0.2455742264347589, 1.8010762541725078, -1.0657704690103253, 0.3348835836480919, -0.14866663843886446, 0.10835557927833268, -0.08323883420082115, 0.6937844759751117, 0.7785409261991718, -0.9910565877082852, 0.479940820643384, -0.5085613106290268, -0.46282802143711854, 0.35466074560913685, 0.3149128690270161, -0.5942077359624284, -0.7917638647434145, 0.4501096335934787, -0.19950891184570135, 0.015494673766853177, -0.42836733358476015, -0.011529589063195315, -0.11786906815706046, 0.9062309720537677, -0.3138424349325825, 0.24132657217372339, -0.35062917745326544, -0.9899002311908546, 0.29886067349049666, -0.8412406843921522, 0.23551515214648358, -0.5886764322500804, 0.062252648200082694, -0.9628807007104896, 0.7776340523738519, -0.36203543931448645, -1.7570093737808279, 0.7275299388068817, 0.8645738946654953, -0.6142702043880583, -0.7102207342243516, -0.1660970964517998, 0.4904549414203053, 0.1038358968328187, 0.17148074199318533, -0.12296281780000143, 0.6813140685562312, -0.22357903830233278, -0.04927277429770755, -0.3081191726244843, 0.7237117523783524, -0.40984200226944234, 1.315300667436018, -1.039689729018209, 1.1144436875623995, 0.1606407130913179, -0.08419812218533877, 0.17263273962326567, 0.362876194784364, 0.19194429372399258, -0.41155047617797336, 0.2665890515994703, -0.5286131954839307, 1.0355447444656203, -0.42702734473802717, 1.1931682538793784, -0.6572392552550822, -0.05042407759138504, 0.12667092166247965, 0.39214546516344134, 0.054421178024209406, 0.33487358518382687, -0.5457948628231479, 0.6628595671748021, -0.6523285342460811, -0.37847921609121177, 0.8662245319083889, -1.0990954485669626, 1.429810726594933, -0.5877068269263886, 0.3169283357810041, -0.2148279569508873, 0.8386769996977843, 0.5151028498294926, 0.5999434439469623, -1.1191010154233674, 0.9122555987223678, -0.5122845129017519, 0.3014055628781332, -0.08540502764738155, 0.929102432989897, -1.0529651243223, 0.5804627624363246, 0.3925745475137336, -0.015276389803106274, 0.03460964744238454, 0.1972846138117599, 0.025138098599056382, 0.8361284672775285, -0.4168088914099706, -0.0871453464328389, 1.444038746600719, -0.5132060316727993, 0.3744905332459908, -0.481231393825407, -0.13924721831316145, 0.7674598619058809, -0.9902063601149877, -0.021837868906587135, 0.6918866588184656, -0.9914959062560792, -0.07571348778429796, 0.5142632067738673, -0.03306523823248495, 0.5053956307848151, -0.2082827508840856, 0.040739377393753086, 0.001959376980946394, -1.3015286680007774, -0.10327257693241775, 0.07351942275734095, -0.34333295305925693, -0.6233716299920601, 0.36102571788982735, -0.6033882290337855, 0.8689234574689998, 0.33808410793038407, 0.1548019195228045, -0.009548628335008413, -0.10108915342060662, -0.6243858912510795, 0.3407149847613182, 0.1455281747640939, 0.16593633214515277, 0.16983932539280677, 0.041884418168551193, 0.5734350853166342, 0.5340548124679547, 0.4391377052167198, 0.21110613820317084, 0.9978628497063834, 0.5449802638313863, 1.5709498175286878, -18.35895585385253, -9.663533382421134, 7.865116888441645, -2.092974383939369, 12.170670237886641, 3.7054295797660943, -1.7061276279305269, -1.144054978111998, -0.620874861219977, 0.1699731926933142, -0.6484212119149344, 0.03907931319486379, 0.10158559393922528, -1.0262971744539329, 1.0374953464824865, -1.335826750983622, 1.9637919018995635, 2.58014149678034, 1.6943130049030657, -0.5097587939900711, 1.4316159185443387, 1.814911258100516, 2.2975985273683266, 2.500846859549422, 1.047987589332258, 1.1295869567389247, 0.9600410067328236, 0.7789254458066728, 0.1430419991645106, 0.5608951802531581, 1.6825865829253144, 2.355817021107581, 0.8954774173315159, -0.3157634022152697, 0.5338161353657394, 0.13617999377978854, 0.5831524042705782, -0.14296885159307718, 0.5531721090375404, -0.3372680990714746, 1.263040690313784, 0.3371853166837109, 0.4873553046428882, 0.32158716191575765, 1.1380938982809807, -0.5277592077360802, 0.7648498654372711, 0.536193092379313, 0.2129211632724976, -0.5309087358161404, -0.02813196715260606, 0.2578735264175039, 0.757866642915663, 0.045435657315997725, 1.426160057322127, 0.5945259814657606, -0.03980460765240573, 0.8169939290866255, 1.6319463089773685, -0.5982530493653427, 1.6559609293352198, -0.2433498011106263, -0.23575359500847298, 1.3088368077108492, 0.7018230053896276, 0.37600847777341784, 0.38243850875669, 0.3195687114433895, 1.584133665748772, -0.4436991761466164, -0.5118493683023982, -0.16019747196929912, -0.8741464607202195, -1.119689659945456, 0.9752461031076944, 0.9712886104479348, -0.13699164054467688, 0.24887016310776414, 0.5710134949109854, -0.4150893768346669, -0.3043454126026308, 0.40869302980325495, -0.6890109337097039, -0.5352257981218954, 0.9227264990270585, -0.30277132183918465, 0.24456102563041993, 0.33402772643505896, -0.5478219341150193, -0.23245107699619008, -0.7098769758301895, 1.6595758223043606, -0.48061005783552646, 0.2783515868220687, 0.8080803548723522, -1.417853458633749, -0.4265560843673416, 0.1789474200931756, 1.510226137096756, -0.708663092154358, 0.4747911358245407, -0.20528370889812994, -0.10850710026355384, -0.500449908119617, -0.2549962254733074, 0.5134367711080712, 0.6509471223029131, -0.5980636363314755, -0.7601615239365036, 0.6133103380357527, 1.8239311679204309, 0.026946397733416578, -1.0247702882650451, 0.160353454378816, 0.05175768346082009, 0.1886140579354358, -0.02843887217412699, -1.1743830867133491, -0.15836383858389655, -0.5542802344288801, 0.09528605834091128, 0.8829116148554806, -0.47559513611177184, 0.4685059931877952, 0.3000986240901334, 0.365058999760516, -0.21176879510670643, 0.4377538503750139, -0.17511580030044946, -0.36014258766803103, 0.16309494471129554, 0.5104360883498541, -0.57444589329263, 0.1237685598984283, 0.041586912183229914, -0.023041396592688074, 0.9803417248433501, 0.32760318775898034, 0.8817908038234992, -0.00835714324679699, -1.8819261552276783, 0.051648124547126674, 0.7226700110348359, 0.21448733228380873, -0.10642964601068206, -0.06631388249093192, -0.0642135458368179, -0.8646063239022402, 1.2641669322601217, 1.0752650331964528, 0.050667535897228805, -0.04849222332975748, -1.0601398144124896, 0.16024015229521346, -0.15698755203655584, 0.25298818324704936, -0.5873553263777065, 0.5175299206200524, 0.19190883156418984, -0.4829339370585401, 0.10691409930605845, 0.12128671438608093, 0.6586833552010115, -0.22757680082682027, -0.24443228528067396, 0.01480453587358096, -0.47234365004483825, 0.0829629258101157, 0.1644395498929589, 0.6416185937358737, -1.539261078071142, -0.4062111751175859, -0.0014979404115751044, 0.5738500404613146, -0.6172652591184872, -1.1087585618150289, 1.5046225033245653, -0.46985453937585775, -0.44252816588561233, 0.21629553618447028, 0.7288588454632021, 0.17674682164014524, -0.0038809545957166017, -1.5483123777386008, -1.1387461477032117, 0.26797683185038607, -0.3508616527148824, -0.08450593868659408, -0.4041641597118567, -0.7478731653493198, -0.4788627731675385, 1.0224275320099407, -1.0165906221289416, 0.7113026498842774, 0.01319674927212287, 0.03049548859349071, 0.4062995008795249, -0.18349754111943567, 0.0014095362938012432, -0.22932366777628396, 0.8080411275467987, -0.8991280111291746, 1.191541964824237, -1.1552939340644872, 0.3387072322699618, 0.5775063694254501, -0.07052238646235179, -1.2557814376709797, 0.9978781703163032, -1.9354403210459796, -0.21078657241628798, -0.32946378068409626, 0.33411589260324087, 1.0567483731182339, -0.24774457132002894, 0.2716422989971324, 0.6161224111088353, -0.17094561841842432, 0.4419009592021166, -1.0782116333999943, -0.38145669993745246, 0.043037859609362177, 0.688167263024089, 0.055582234879299884, -0.5643987646972602, 0.7436069005364966, -0.3316603619653092, -0.5876762249522663, -1.0483672127745463, -0.3496486461231888, 0.776103973893175, 0.07069433287199492, -0.07908950361573815, -0.04773378452288164, 0.13315792165044282, -0.31046237966314577, 0.5272909229990723, -1.2253415720906635, -0.4215435382583823, 0.36361576472567364, 0.09968195554522112, -0.31803427188382993, 0.1293085296825082, 0.018747279864693107, 0.8397532338581416, -0.2529026010646597, -0.2688188749157449, 0.050759531406563356, -0.531626076860762, 0.07112267945058022, -0.21335278365348825, 0.0844405674212672, -0.21266116308445085, -0.4464462483657944, 0.23913017617160007, -0.1784514728399084, 0.3539710480412687, -0.45080891099809134, 0.20928624567803358, -0.6629015944186316, -1.1784499504584072, -1.2597917127982756, 0.6766800034325176, 0.34513416138427333, 1.0107946968035724, -1.003794468945208, 0.5496845828900255, 0.13138231416628796, -0.49431489749157403, 0.6113639626763187, -0.2278600017599123, -0.24360877701113862, 0.6939194328630331, -0.055147283858546205, 0.6719344626374931, -0.17106466803614406, -0.6269743618410348, -0.778864836608785, 0.3846540616323945, 0.24007308607414887, 0.6775961557109149, 0.16398299491225535, 1.0729834894140426, 0.41892796597322424, -0.42931446873002327, 0.33236891470669216, -0.8292519540392593, 0.5412301370475459, -0.04840542617907841, 0.25081922537746904, 1.5798535806590859, 0.10636663340902397, 0.8859906675339646, -0.4942450137668556, 0.10355546570847099, 0.3062689826854224, 0.3376631468634801, 0.4997539410605251, 0.037980883737332854, 0.1649373396801555, -0.4723463717541261, 0.20155486200922837, 0.5843226161638171, 0.19543062802468117, 0.23450877709222653, 0.6155338114481834, 0.4105256652106004, -1.7133159597457608, 0.320715886981206, 0.691631553623146, -0.24236666625489842, 1.0818197816665915, -0.7580714169446117, 0.38435862291292944, 0.8079011708044578, -0.0030690352204252947, -0.12567810574553578, 0.40208030986951376, -1.6193230469248918, 1.3670794739442114, -0.13167042691086153, 0.6649580150693303, -1.0638070815159162, 0.624488860994384, 0.06778322087608708, -1.559206691023599, -0.3008615958824631, 0.8467373316978368, -0.6103679351238965, 0.10834596481563993, 0.07824289550679256, -0.43814562387239303, -0.30229302078832704, -0.2702277295946527, 0.056872114397302144, -0.1036665084048932, -0.3418624338802064, 0.3228273776188127, -0.5092669924692679, 1.1599830747479776, -0.9512776937127572, 0.8267938595871677, 0.22411347675825627, -0.05545371651001298, -0.695052755774923, -0.31948865723709224, 0.23187000158497498, 0.8774547336749408, -0.6679228935533718, -0.871242143208754, -0.1813420563016125, 0.004940613863741429, 0.4762598227149162, -0.6738770397141236, 0.0005055469393599174, 0.5908989643108442, -0.1704785459696257, 0.09738668848408938, -0.5681614756810867, 0.1857547381051785, -0.16415071645042198, 0.6612837625053214, -0.021360076122394284, 0.1480811665659227, -0.4712382499059169, 0.15477602161036594, -0.8979131621030958, -0.3214702712741181, -0.6163991406321416, 0.24939602764262883, 0.6731950320471594, -0.4271718365425984, 0.26039428627225625, 0.22857047690463994, -0.2861769532747064, 0.18254113480995982, 0.5803930981904035, -0.12980221184587845, -0.672615734561971, 0.7072127964531547, 0.4934594008920414, 1.2013618172104332, -1.747902082789423, 0.19174374324662125, 0.7634133090654437, -0.7505408046166583, -0.0685491557982971, 0.47486344284759985, -0.14017391433942633, 0.23587792129578705, -0.26676400462258476, 0.6796232716309616, 0.44078419597906415, -0.7830542206971923, -0.6509182317771756, 0.5623603750280785, 0.38143849999534996, 0.036476375704606656, -0.0381467224465758, -0.8312909924625197]</Parameters>
			</FullConnection>
			<FullConnection class="pybrain.structure.connections.full.FullConnection" name="FullConnection-13">
				<inmod val="TanhLayer-7"/>
				<outmod val="TanhLayer-17"/>
				<Parameters>[-0.05768934224685303, -0.3156353295429076, 0.8063018514154578, 0.2741988639616015, 1.4920595409288893, -1.1598409010023258, 0.5492273144822519, -1.6576414524587186, -0.9495156128215057, -0.3907392022718328, -0.49676502466170563, 2.06357968828677, 0.5703025267279493, 1.3753146208756633, 2.020836949600178, 2.0715513874107447, -0.291674938278093, -0.5733810448454072, 1.2016980246344666, 0.06251190777640528, 1.5506258860839872, -1.6035775520149946, -0.4273695886677031, 1.6765336317590505, 0.3094772090437592, -0.279886118564532, -0.31740673144143156, 0.1169848936267919, -0.22054975345169944, -0.9249417057274537, -0.6635863043552589, -0.6825649305067389, 0.6780335286611311, 1.0042331210017577, 1.3000029561914381, 0.6316173504059404, -0.7336839491807428, -1.6757075146634837, 0.19698456862653455, 0.10225449487383323, 1.8441600687753057, 0.1699208428825875, -0.20367372089096658, 0.2337656480485798, -0.7559318311997961, -0.9385487369110664, 0.9089081689693702, -2.9903725610010796, 0.47508720588262054, 1.484124160598864, 0.8284612408283292, 0.8518440005658271, 0.7566620440865469, -1.3569604974764824, -0.49903838489430713, 0.4889210096861652, -0.9676982991999484, 0.11959000822868206, -1.9011446252783257, 0.46922447694450525, 0.5295539960554159, 1.19592980666906, 0.38826768428839253, 0.05014292196184734, 0.2243474475337905, -0.14723746097294013, -0.7985322545333444, 0.47252915265652784, 0.7043353929213332, 0.5422479416211473, -2.459764206538898, -0.27777933693396645, -0.9265722042418302, 0.83924225368801, -1.2369122691028778, 1.621281949690092, -1.5104130510646716, 0.5861382965512226, -1.7882144621273015, -1.1894583645913115, 0.5952521210745277, -0.8235382202268507, -0.15926756072697704, -1.50392372894292, -1.2034537264621352, 2.2404973148811473, 0.7912443958384439, -2.1762604623192656, 1.5235351056192135, -1.4023921547258957, -0.2097008430356077, -0.645547544171042, -1.3259789560007655, 1.6015242740749447, 0.9318894000200106, 1.1167480867433208, 0.7697517167823401, -1.0448578301805105, 0.13999973262694532, -0.5668735761283344]</Parameters>
			</FullConnection>
			<FullConnection class="pybrain.structure.connections.full.FullConnection" name="FullConnection-12">
				<inmod val="TanhLayer-17"/>
				<outmod val="TanhLayer-18"/>
				<Parameters>[0.6085038831802496, 1.9982973600872898, -0.363750493307547, -2.6048283286389, 1.4449173437594063, 0.49714155112082425, -1.8467768814406431, -0.5036499205331376, 0.334440003859049, 0.08920698316547467, 0.5562840445452426, 0.9000120759386173, 2.2897726891145167, -0.5183554069423443, 1.493354776264789, 1.1449560104316894, 2.4494188597050233, -1.4707177451540407, 1.0106427492833132, 0.3700596896904909, 0.5490981214997851, 0.6583149337689571, -0.43675341713716687, -0.5712937728645849, -0.2517450855437494, 1.2301802763776688, -1.8504940056535464, -2.01108473181299, -1.9238744376564376, 0.6031120835989622, -1.063550875320102, -0.30680157955413717, 0.18290899107493017, -0.3527982242879278, -0.5505259623687973, 0.781322498084036, 0.48040558250851884, 0.5526472298671583, 1.4793649773873099, -0.6610483284347732, -0.4532500132097635, 0.4980477061433804, 0.6034855382984646, -1.3048126354610718, 0.7500571946347167, 0.04077094481328238, -0.11968696475179033, -1.4573646281343855, 0.7165067320477896, -2.108542728271007, 0.4679847745904096, 1.9364970974091484, 2.188205057173688, -0.8081577406971815, -1.8059573027267297, -0.052919488519802126, -2.8388882778483886, -0.8484845557544767, -0.8134345039415425, -0.4347665575715009, 0.10401420271753603, -0.8164897161453534, 0.5194885442194067, 1.780060286938618, 0.6777854589001419, 0.24263292538727643, 0.3075105927012521, -0.10369211651328995, -0.12239727180226394, -0.18837159368915926, 0.5338998664338153, 1.138257743932869, 0.4005477633029391, 0.7526006345103138, -0.7927632696659913, -0.1971462091683108, 0.9680407917183047, -1.1615010569248942, 0.8694480962682157, -0.5264022528046677, -0.9440267696743099, -1.924000226831055, 0.25946623493860954, -1.2955966768224683, -0.9030615707555558, -0.5565958352839727, 0.9131923414821647, -0.490429390547945, 0.6728652445516237, 0.8345324562454789, 1.7573802287929654, 1.4455751856461434, 0.45394235649985887, 0.5508177644245049, -0.2807280330349885, -0.6673319138348236, -1.0246421737601479, 0.6119340029977117, 1.6527372034776615, -0.8415809137833915]</Parameters>
			</FullConnection>
			<FullConnection class="pybrain.structure.connections.full.FullConnection" name="FullConnection-10">
				<inmod val="TanhLayer-18"/>
				<outmod val="TanhLayer-19"/>
				<Parameters>[-1.1041046991190442, 2.843898041061169, -0.2256409066204826, -0.6108095065579994, -0.33626903532639674, 1.7869644137820553, 0.6099748819919545, 0.33303982035383095, 2.389640281459619, 1.3190154143513162, 0.8675961828629738, -0.3634795222247223, -0.15759626271867755, 1.070134514979709, -1.0430981189821797, -1.1120423815314224, 0.5933178947332951, 0.2985046754931624, -0.14609882730443466, -0.13513822672602976, -0.18496900478444095, -0.9112668420519797, 0.6563722392949949, 0.938604477122318, -0.9158871292962866, -0.5394783004038138, -0.6621587591275423, -1.6001356216221863, -0.224997874339579, 0.32310887577876674, 0.6757037081183063, -0.9284434137733928, 0.3778635618771511, 0.1401164939157567, 0.7942366521006214, 1.0372745013964308, -0.013977656173557743, -1.5601329679607607, -0.1136754374457269, -1.100083678031301, -1.967094890090657, 0.49624928559371884, -0.8247091169891436, 0.5279378803083807, -0.49878247058879593, -0.0892604013189911, -0.9115792419583669, 0.5378076564220979, 0.7940137109910739, -0.16403334035785555, 0.8293938430088307, 0.008703513995842994, -0.2932344625072095, 1.531035132617402, -0.7454335784039362, 0.5508977510165745, 0.677545111221261, 1.3315527070759356, -0.12936494425512726, 2.0053333395503223, -0.6286390613143988, -2.0136758411926072, 0.5926088719741147, -1.3287926294924177, 0.3125993906768241, -1.9128788579416698, -0.31896458947576206, -0.796719503747144, 0.19663924730014468, 0.7122990389640131, -1.910020574021833, -1.3076070140146054, -0.6099181574727696, -0.9242510217930012, -1.2812648794661672, -0.0807379131663806, 0.1186734752662698, 2.2044531682257342, 0.3706079201885254, -0.9758862239567092, -0.047369341885564076, -1.418438844025996, 0.9846569891071667, 0.639713270004692, -0.8759854479926003, -0.2308235235766127, -0.9541327397213596, 0.9417459777144643, -0.28852581786300463, 0.12531472619909115, 0.06827191790097208, -1.0177120071724766, 0.2701592299408656, -0.8533431405115011, 0.03338213170958114, -0.34940382045346746, 0.5736696622178987, -1.0902776526269993, -1.9057860354593834, 0.8341904121048848]</Parameters>
			</FullConnection>
			<FullConnection class="pybrain.structure.connections.full.FullConnection" name="FullConnection-9">
				<inmod val="TanhLayer-19"/>
				<outmod val="TanhLayer-20"/>
				<Parameters>[0.7174756982596893, 1.6142213937323813, -2.513396178828353, -0.10450070735492452, 0.1646287225415367, 1.2361014954954976, -1.1006435901585752, -0.8373158187580501, -0.09307557993085554, -1.0452044989642382, -0.9699832649462901, 5.805040571992597, -0.1287295814625497, -4.918938947458057, -0.9814708537207877, 0.6352921254625262, -1.5860734400573238, 0.6060700701741963, -2.47436012631877, -2.2775986976195024, 1.1565016788303422, -4.265754320806971, 0.6512769593139451, -0.26059765960860337, -1.5870970422924897, -0.06712446383118041, -3.1231652317158645, -0.7780300793939112, 3.008654842091208, 0.9662866702718464, -0.11280537253576664, -2.0281418856919706, -0.2941006851781535, 0.1753191146980155, -0.4332773218518159, -2.313983754553445, -0.8515261577973368, 0.1490429046123978, 1.661573479322511, -0.13250545218530133, 1.7318842880652667, 10.468294006910117, 0.35071841600539255, -0.9504155933713995, -0.9989610860268957, 6.390816537821977, 0.2574833286796198, -0.35814860801253723, -4.347675772441588, 1.6169650003687128, -0.3307898649167038, -3.255991400407512, -0.6114716630106253, -0.9305236962862454, 0.4518040527007167, -0.7955701601832177, -0.44195195994773245, -0.6070330487346094, -0.18394718626943724, 4.957722645047606, -0.32036276754247817, -0.0376984640873226, -0.13282377938375087, 2.6428470792124736, -1.472203022582236, 0.2365115362179978, -0.3099959126961452, 5.977416084243443, 0.49707097700658887, 0.07979344187595679, -1.8080221267983607, 0.6097782633485098, -0.6423091439996742, 0.2854186452849262, -0.9510654917200154, -1.5406663492318557, -1.6786098515122472, -0.16936249041827256, -3.074561953506978, -0.8566097154110317, 5.451125673778115, -2.380699420051666, 2.5487499739706068, 1.251063713181509, -2.043414673905232, -3.318411312236569, 0.6433804826174051, -0.0962680550752408, -4.485298302269321, 1.757642951079513, -0.07068229982912777, 0.8547906286013013, -0.23844597799604902, 0.9579983638108883, 3.7107109706411228, -2.0834663364643116, -0.29289153842114224, 0.5344967338325847, -0.7796361517501089, -0.6274397368829683]</Parameters>
			</FullConnection>
			<FullConnection class="pybrain.structure.connections.full.FullConnection" name="FullConnection-11">
				<inmod val="TanhLayer-20"/>
				<outmod val="SoftmaxLayer-16"/>
				<Parameters>[-4.143202396239965, 2.7449716511265208, -0.6030311055295856, -4.608740989866494, -1.6283140505046296, -0.22002342337295974, 1.2798553045499443, 1.1666551808568264, -0.010970635385875992, 0.8357303038015045, 0.1137122388303928, -0.475435509510143, 1.9043634618785799, 2.664429528441337, 3.7397327067964734, 0.11567111771033298, 0.31258285156540705, 1.186939634451802, 1.5879940538136819, 0.10514252523553486, 0.8574548816407418, -2.746627175239683, -0.8478907428549536, -4.088218853341315, 1.8542189464394572, 0.5697556849392583, 0.5457366010440313, 1.8536603876960323, 0.1990022454106246, -2.129938518014359, -0.52096916601935, -0.40539510266956497, -0.5878617842645537, 2.947648007959724, 1.981148414810122, -1.7966515298334815, 0.6519618114487498, 1.4342595049642954, 0.2784645912492749, 1.0760390814062775, 1.1565848380948252, 1.6718869629721376, -0.6211810134783821, 1.0277375665573705, -1.7186761853116614, -1.2856734200934516, 0.746519155154999, -4.054081767958677, -0.9378588639013229, -1.1971812385710756, 0.8515988198813171, -2.128094707271331, 0.42101416978475087, 2.7996832956285784, -1.5892475139574465, -0.2791814395498006, -1.227720021022553, 1.2659753800347886, -0.7021821613274017, -2.9590650861691747, 1.0607848263722242, 1.4181316964383772, 0.955563806797667, -0.9336431917395364, 0.6473726291243664, 1.340826854485379, -2.3005092956503224, -1.6983683426339038, -0.46468299899656224, 1.2703909758744774, 0.6085515602237124, -1.433229738706467, 0.7180673794671487, 4.306848697679653, -0.18096449676394383, -0.3100301967687174, 0.8404417202157838, 1.0246714437569995, -0.4648313358697433, 1.25665908225069, 1.8986177150490609, 2.1781839757492847, -0.5039977519113534, -3.9463391215851313, -2.685776645960658, -3.2140488378181216, -0.8299368308063283, 0.29498161750997587, 0.5350599549643246, 1.7231089355447358, 0.8587289250528783, -1.2172643988811203, -1.5933329764647695, 2.2763394587076835, 0.841697213911972, 0.7782997667227718, 0.47592003316484616, 1.2976490361960449, -0.7581397205181367, 1.3768065775026432]</Parameters>
			</FullConnection>
		</Connections>
	</Network>
</PyBrain>
